Workbook

Sheet NAC
B1: Índices | Y1: Tasas de inflación mensual | AV1: Tasas de inflación interanual
R2: =+SUM(C3:N3) -> 1 | S2: =+SUM($C$3:$E$3,$G$3,$K$3,$M$3:$N$3) -> 0.66456407 | T2: =+SUM($E$3,$G$3,$K$3,$M$3:$N$3) -> 0.35975272 | U2: =+SUM($E$3,$G$3,$K$3,$N$3) -> 0.27075759 | W2: =+SUM(E3,G3:L3,N3) -> 0.51189203 | AT2: =+SUM(AB3,AD3:AI3,AK3) -> 0.51189203 | BL2: =+SUM(AW3:BH3) -> 1 | BQ2: =+SUM(AY3,BA3:BF3,BH3) -> 0.51189203
C3: 0.26984735 | D3: 0.034964 | E3: 0.09889825 | F3: 0.09430149 | G3: 0.0640437 | H3: 0.0797777 | I3: 0.11018341 | J3: 0.02820723 | K3: 0.07259865 | L3: 0.0229661 | M3: 0.08899513 | N3: 0.03521699 | R3: headline | V3: no food & energy | W3: no food & energy & shelter | Z3: 0.26984735 | AA3: 0.034964 | AB3: 0.09889825 | AC3: 0.09430149 | AD3: 0.0640437 | AE3: 0.0797777 | AF3: 0.11018341 | AG3: 0.02820723 | AH3: 0.07259865 | AI3: 0.0229661 | AJ3: 0.08899513 | AK3: 0.03521699 | AO3: headline | AS3: no food & energy | AT3: no food & energy & shelter | AW3: 0.26984735 | AX3: 0.034964 | AY3: 0.09889825 | AZ3: 0.09430149 | BA3: 0.0640437 | BB3: 0.0797777 | BC3: 0.11018341 | BD3: 0.02820723 | BE3: 0.07259865 | BF3: 0.0229661 | BG3: 0.08899513 | BH3: 0.03521699 | BL3: headline | BP3: no food & energy | BQ3: no food & energy & shelter
A4: Fecha | B4: Nivel general | C4: Alimentos y bebidas no alcohólicas | D4: Bebidas alcohólicas y tabaco | E4: Prendas de vestir y calzado | F4: Vivienda, agua, electricidad, gas y otros combustibles | G4: Equipamiento y mantenimiento del hogar | H4: Salud | I4: Transporte | J4: Comunicación | K4: Recreación y cultura | L4: Educación | M4: Restaurantes y hoteles | N4: Bienes y servicios varios | O4: Estacional | P4: Núcleo | Q4: Regulados | R4: Nivel General | S4: Subyacente | T4: Subyacente-AyB | U4: Subyacente-Food | V4: Core | W4: Supercore | Y4: Nivel general | Z4: Alimentos y bebidas no alcohólicas | AA4: Bebidas alcohólicas y tabaco | AB4: Prendas de vestir y calzado | AC4: Vivienda, agua, electricidad, gas y otros combustibles | AD4: Equipamiento y mantenimiento del hogar | AE4: Salud | AF4: Transporte | AG4: Comunicación | AH4: Recreación y cultura | AI4: Educación | AJ4: Restaurantes y hoteles | AK4: Bienes y servicios varios | AL4: Estacional | AM4: Núcleo | AN4: Regulados | AO4: =+R4 -> Nivel General | AP4: =+S4 -> Subyacente | AQ4: =+T4 -> Subyacente-AyB | AR4: =+U4 -> Subyacente-Food | AS4: Core | AT4: Supercore | AV4: Nivel general | AW4: Alimentos y bebidas no alcohólicas | AX4: Bebidas alcohólicas y tabaco | AY4: Prendas de vestir y calzado | AZ4: Vivienda, agua, electricidad, gas y otros combustibles | BA4: Equipamiento y mantenimiento del hogar | BB4: Salud | BC4: Transporte | BD4: Comunicación | BE4: Recreación y cultura | BF4: Educación | BG4: Restaurantes y hoteles | BH4: Bienes y servicios varios | BI4: Estacional | BJ4: Núcleo | BK4: Regulados | BL4: =+AO4 -> Nivel General | BM4: =+AP4 -> Subyacente | BN4: =+AQ4 -> Subyacente-AyB | BO4: =+AR4 -> Subyacente-Food | BP4: Core | BQ4: Supercore
A5: =+[1]NAC!A6 -> 42705 | B5: =+[1]NAC!B6 -> 100 | C5: =+[1]NAC!C6 -> 100 | D5: =+[1]NAC!D6 -> 100 | E5: =+[1]NAC!E6 -> 100 | F5: =+[1]NAC!F6 -> 100 | G5: =+[1]NAC!G6 -> 100 | H5: =+[1]NAC!H6 -> 100 | ... N5: =+[1]NAC!N6 -> 100 | O5: =+[1]NAC!P6 -> 100 | P5: =+[1]NAC!Q6 -> 100 | Q5: =+[1]NAC!R6 -> 100 | R5: =+SUMPRODUCT($C$3:$N$3,C5:N5) -> 100 | S5: =+($C$3*$C5+$D$3*$D5+$E$3*$E5+$G$3*$G5+$K$3*$K5+$M$3*$M5+$N$3*$N5)/SUM($C$3:$E$3,$G$3,$K$3,$M$3:$N$3) -> 100 | T5: =+($E$3*$E5+$G$3*$G5+$K$3*$K5+$M$3*$M5+$N$3*$N5)/SUM($E$3,$G$3,$K$3,$M$3:$N$3) -> 100 | U5: =+($E$3*$E5+$G$3*$G5+$K$3*$K5+$N$3*$N5)/SUM($E$3,$G$3,$K$3,$N$3) -> 100 | W5: =($E$3*$E5+SUMPRODUCT($G$3:$L$3,$G5:$L5)+$N$3*$N5)/SUM($E$3,$G$3:$L$3,$N$3) -> 100
A6: =+[1]NAC!A7 -> 42736 | B6: =+[1]NAC!B7 -> 101.6 | C6: =+[1]NAC!C7 -> 101.3 | D6: =+[1]NAC!D7 -> 100.9 | E6: =+[1]NAC!E7 -> 99 | F6: =+[1]NAC!F7 -> 101.5 | G6: =+[1]NAC!G7 -> 100.9 | H6: =+[1]NAC!H7 -> 102.4 | ... N6: =+[1]NAC!N7 -> 101.9 | O6: =+[1]NAC!P7 -> 101.7 | P6: =+[1]NAC!Q7 -> 101.5 | Q6: =+[1]NAC!R7 -> 101.8 | R6: =+SUMPRODUCT($C$3:$N$3,C6:N6) -> 101.58624 | S6: =+($C$3*$C6+$D$3*$D6+$E$3*$E6+$G$3*$G6+$K$3*$K6+$M$3*$M6+$N$3*$N6)/SUM($C$3:$E$3,$G$3,$K$3,$M$3:$N$3) -> 101.37853 | T6: =+($E$3*$E6+$G$3*$G6+$K$3*$K6+$M$3*$M6+$N$3*$N6)/SUM($E$3,$G$3,$K$3,$M$3:$N$3) -> 101.48395 | U6: =+($E$3*$E6+$G$3*$G6+$K$3*$K6+$N$3*$N6)/SUM($E$3,$G$3,$K$3,$N$3) -> 100.95277 | W6: =($E$3*$E6+SUMPRODUCT($G$3:$L$3,$G6:$L6)+$N$3*$N6)/SUM($E$3,$G$3:$L$3,$N$3) -> 101.53672 | Y6: =+B6/B5-1 -> 0.016 | Z6: =+C6/C5-1 -> 0.013 | AA6: =+D6/D5-1 -> 0.009 | AB6: =+E6/E5-1 -> -0.01 | AC6: =+F6/F5-1 -> 0.015 | AD6: =+G6/G5-1 -> 0.009 | AE6: =+H6/H5-1 -> 0.024 | AF6: =+I6/I5-1 -> 0.021 | ... AT6: =+W6/W5-1 -> 0.015367225
A7: =+[1]NAC!A8 -> 42767 | B7: =+[1]NAC!B8 -> 103.7 | C7: =+[1]NAC!C8 -> 103.2 | D7: =+[1]NAC!D8 -> 105.2 | E7: =+[1]NAC!E8 -> 98.9 | F7: =+[1]NAC!F8 -> 107 | G7: =+[1]NAC!G8 -> 101.3 | H7: =+[1]NAC!H8 -> 105.1 | ... N7: =+[1]NAC!N8 -> 103.8 | O7: =+[1]NAC!P8 -> 102.3 | P7: =+[1]NAC!Q8 -> 103.2 | Q7: =+[1]NAC!R8 -> 105.9 | R7: =+SUMPRODUCT($C$3:$N$3,C7:N7) -> 103.67106 | S7: =+($C$3*$C7+$D$3*$D7+$E$3*$E7+$G$3*$G7+$K$3*$K7+$M$3*$M7+$N$3*$N7)/SUM($C$3:$E$3,$G$3,$K$3,$M$3:$N$3) -> 102.80721 | T7: =+($E$3*$E7+$G$3*$G7+$K$3*$K7+$M$3*$M7+$N$3*$N7)/SUM($E$3,$G$3,$K$3,$M$3:$N$3) -> 102.28002 | U7: =+($E$3*$E7+$G$3*$G7+$K$3*$K7+$N$3*$N7)/SUM($E$3,$G$3,$K$3,$N$3) -> 101.41886 | W7: =($E$3*$E7+SUMPRODUCT($G$3:$L$3,$G7:$L7)+$N$3*$N7)/SUM($E$3,$G$3:$L$3,$N$3) -> 102.98802 | Y7: =+B7/B6-1 -> 0.020669291 | Z7: =+C7/C6-1 -> 0.01875617 | AA7: =+D7/D6-1 -> 0.042616452 | AB7: =+E7/E6-1 -> -0.001010101 | AC7: =+F7/F6-1 -> 0.054187192 | AD7: =+G7/G6-1 -> 0.0039643211 | AE7: =+H7/H6-1 -> 0.026367187 | AF7: =+I7/I6-1 -> 0.018609207 | ... AT7: =+W7/W6-1 -> 0.014293358
A8: =+[1]NAC!A9 -> 42795 | B8: =+[1]NAC!B9 -> 106.1 | C8: =+[1]NAC!C9 -> 106 | D8: =+[1]NAC!D9 -> 107.3 | E8: =+[1]NAC!E9 -> 102.3 | F8: =+[1]NAC!F9 -> 110.8 | G8: =+[1]NAC!G9 -> 102.2 | H8: =+[1]NAC!H9 -> 107.1 | ... N8: =+[1]NAC!N9 -> 105.7 | O8: =+[1]NAC!P9 -> 104.8 | P8: =+[1]NAC!Q9 -> 105.2 | Q8: =+[1]NAC!R9 -> 110 | R8: =+SUMPRODUCT($C$3:$N$3,C8:N8) -> 106.18771 | S8: =+($C$3*$C8+$D$3*$D8+$E$3*$E8+$G$3*$G8+$K$3*$K8+$M$3*$M8+$N$3*$N8)/SUM($C$3:$E$3,$G$3,$K$3,$M$3:$N$3) -> 105.08105 | T8: =+($E$3*$E8+$G$3*$G8+$K$3*$K8+$M$3*$M8+$N$3*$N8)/SUM($E$3,$G$3,$K$3,$M$3:$N$3) -> 104.1761 | U8: =+($E$3*$E8+$G$3*$G8+$K$3*$K8+$N$3*$N8)/SUM($E$3,$G$3,$K$3,$N$3) -> 103.5766 | W8: =($E$3*$E8+SUMPRODUCT($G$3:$L$3,$G8:$L8)+$N$3*$N8)/SUM($E$3,$G$3:$L$3,$N$3) -> 105.39365 | Y8: =+B8/B7-1 -> 0.023143684 | Z8: =+C8/C7-1 -> 0.027131783 | AA8: =+D8/D7-1 -> 0.019961977 | AB8: =+E8/E7-1 -> 0.03437816 | AC8: =+F8/F7-1 -> 0.035514019 | AD8: =+G8/G7-1 -> 0.0088845015 | AE8: =+H8/H7-1 -> 0.019029496 | AF8: =+I8/I7-1 -> 0.011538462 | ... AT8: =+W8/W7-1 -> 0.023358301
A9: =+[1]NAC!A10 -> 42826 | B9: =+[1]NAC!B10 -> 109 | C9: =+[1]NAC!C10 -> 108.4 | D9: =+[1]NAC!D10 -> 109.8 | E9: =+[1]NAC!E10 -> 106.9 | F9: =+[1]NAC!F10 -> 117.4 | G9: =+[1]NAC!G10 -> 103.3 | H9: =+[1]NAC!H10 -> 109.1 | ... N9: =+[1]NAC!N10 -> 107.5 | O9: =+[1]NAC!P10 -> 108.2 | P9: =+[1]NAC!Q10 -> 107.4 | Q9: =+[1]NAC!R10 -> 114.5 | R9: =+SUMPRODUCT($C$3:$N$3,C9:N9) -> 109.04433 | S9: =+($C$3*$C9+$D$3*$D9+$E$3*$E9+$G$3*$G9+$K$3*$K9+$M$3*$M9+$N$3*$N9)/SUM($C$3:$E$3,$G$3,$K$3,$M$3:$N$3) -> 107.64676 | T9: =+($E$3*$E9+$G$3*$G9+$K$3*$K9+$M$3*$M9+$N$3*$N9)/SUM($E$3,$G$3,$K$3,$M$3:$N$3) -> 106.8725 | U9: =+($E$3*$E9+$G$3*$G9+$K$3*$K9+$N$3*$N9)/SUM($E$3,$G$3,$K$3,$N$3) -> 106.5019 | W9: =($E$3*$E9+SUMPRODUCT($G$3:$L$3,$G9:$L9)+$N$3*$N9)/SUM($E$3,$G$3:$L$3,$N$3) -> 107.97464 | Y9: =+B9/B8-1 -> 0.027332705 | Z9: =+C9/C8-1 -> 0.022641509 | AA9: =+D9/D8-1 -> 0.023299161 | AB9: =+E9/E8-1 -> 0.044965787 | AC9: =+F9/F8-1 -> 0.059566787 | AD9: =+G9/G8-1 -> 0.010763209 | AE9: =+H9/H8-1 -> 0.018674136 | AF9: =+I9/I8-1 -> 0.0066539924 | ... AT9: =+W9/W8-1 -> 0.024489086
A10: =+[1]NAC!A11 -> 42856 | B10: =+[1]NAC!B11 -> 110.5 | C10: =+[1]NAC!C11 -> 109.8 | D10: =+[1]NAC!D11 -> 111.7 | E10: =+[1]NAC!E11 -> 108.7 | F10: =+[1]NAC!F11 -> 119.5 | G10: =+[1]NAC!G11 -> 106.2 | H10: =+[1]NAC!H11 -> 110.7 | ... N10: =+[1]NAC!N11 -> 108.9 | O10: =+[1]NAC!P11 -> 109.1 | P10: =+[1]NAC!Q11 -> 109.2 | Q10: =+[1]NAC!R11 -> 115.7 | R10: =+SUMPRODUCT($C$3:$N$3,C10:N10) -> 110.59514 | S10: =+($C$3*$C10+$D$3*$D10+$E$3*$E10+$G$3*$G10+$K$3*$K10+$M$3*$M10+$N$3*$N10)/SUM($C$3:$E$3,$G$3,$K$3,$M$3:$N$3) -> 109.23839 | T10: =+($E$3*$E10+$G$3*$G10+$K$3*$K10+$M$3*$M10+$N$3*$N10)/SUM($E$3,$G$3,$K$3,$M$3:$N$3) -> 108.57789 | U10: =+($E$3*$E10+$G$3*$G10+$K$3*$K10+$N$3*$N10)/SUM($E$3,$G$3,$K$3,$N$3) -> 108.24193 | W10: =($E$3*$E10+SUMPRODUCT($G$3:$L$3,$G10:$L10)+$N$3*$N10)/SUM($E$3,$G$3:$L$3,$N$3) -> 109.47138 | Y10: =+B10/B9-1 -> 0.013761468 | Z10: =+C10/C9-1 -> 0.012915129 | AA10: =+D10/D9-1 -> 0.017304189 | AB10: =+E10/E9-1 -> 0.016838167 | AC10: =+F10/F9-1 -> 0.017887564 | AD10: =+G10/G9-1 -> 0.028073572 | AE10: =+H10/H9-1 -> 0.014665445 | AF10: =+I10/I9-1 -> 0.0094428706 | ... AT10: =+W10/W9-1 -> 0.013861955
A11: =+[1]NAC!A12 -> 42887 | B11: =+[1]NAC!B12 -> 111.8 | C11: =+[1]NAC!C12 -> 110.7 | D11: =+[1]NAC!D12 -> 112.5 | E11: =+[1]NAC!E12 -> 109.7 | F11: =+[1]NAC!F12 -> 121.6 | G11: =+[1]NAC!G12 -> 107.5 | H11: =+[1]NAC!H12 -> 112.4 | ... N11: =+[1]NAC!N12 -> 110.4 | O11: =+[1]NAC!P12 -> 110.1 | P11: =+[1]NAC!Q12 -> 110.7 | Q11: =+[1]NAC!R12 -> 116.7 | R11: =+SUMPRODUCT($C$3:$N$3,C11:N11) -> 111.87598 | S11: =+($C$3*$C11+$D$3*$D11+$E$3*$E11+$G$3*$G11+$K$3*$K11+$M$3*$M11+$N$3*$N11)/SUM($C$3:$E$3,$G$3,$K$3,$M$3:$N$3) -> 110.44671 | T11: =+($E$3*$E11+$G$3*$G11+$K$3*$K11+$M$3*$M11+$N$3*$N11)/SUM($E$3,$G$3,$K$3,$M$3:$N$3) -> 110.05715 | U11: =+($E$3*$E11+$G$3*$G11+$K$3*$K11+$N$3*$N11)/SUM($E$3,$G$3,$K$3,$N$3) -> 109.78012 | W11: =($E$3*$E11+SUMPRODUCT($G$3:$L$3,$G11:$L11)+$N$3*$N11)/SUM($E$3,$G$3:$L$3,$N$3) -> 110.83159 | Y11: =+B11/B10-1 -> 0.011764706 | Z11: =+C11/C10-1 -> 0.0081967213 | AA11: =+D11/D10-1 -> 0.0071620412 | AB11: =+E11/E10-1 -> 0.009199632 | AC11: =+F11/F10-1 -> 0.017573222 | AD11: =+G11/G10-1 -> 0.012241055 | AE11: =+H11/H10-1 -> 0.01535682 | AF11: =+I11/I10-1 -> 0.0065481759 | ... AT11: =+W11/W10-1 -> 0.012425193
A12: =+[1]NAC!A13 -> 42917 | B12: =+[1]NAC!B13 -> 113.8 | C12: =+[1]NAC!C13 -> 112 | D12: =+[1]NAC!D13 -> 115.8 | E12: =+[1]NAC!E13 -> 108.4 | F12: =+[1]NAC!F13 -> 124.1 | G12: =+[1]NAC!G13 -> 110.1 | H12: =+[1]NAC!H13 -> 116.1 | ... N12: =+[1]NAC!N13 -> 111.8 | O12: =+[1]NAC!P13 -> 110.6 | P12: =+[1]NAC!Q13 -> 112.6 | Q12: =+[1]NAC!R13 -> 119.4 | R12: =+SUMPRODUCT($C$3:$N$3,C12:N12) -> 113.81624 | S12: =+($C$3*$C12+$D$3*$D12+$E$3*$E12+$G$3*$G12+$K$3*$K12+$M$3*$M12+$N$3*$N12)/SUM($C$3:$E$3,$G$3,$K$3,$M$3:$N$3) -> 112.1048 | T12: =+($E$3*$E12+$G$3*$G12+$K$3*$K12+$M$3*$M12+$N$3*$N12)/SUM($E$3,$G$3,$K$3,$M$3:$N$3) -> 111.82429 | U12: =+($E$3*$E12+$G$3*$G12+$K$3*$K12+$N$3*$N12)/SUM($E$3,$G$3,$K$3,$N$3) -> 111.17489 | W12: =($E$3*$E12+SUMPRODUCT($G$3:$L$3,$G12:$L12)+$N$3*$N12)/SUM($E$3,$G$3:$L$3,$N$3) -> 112.74652 | Y12: =+B12/B11-1 -> 0.017889088 | Z12: =+C12/C11-1 -> 0.011743451 | AA12: =+D12/D11-1 -> 0.029333333 | AB12: =+E12/E11-1 -> -0.011850501 | AC12: =+F12/F11-1 -> 0.020559211 | AD12: =+G12/G11-1 -> 0.024186047 | AE12: =+H12/H11-1 -> 0.032918149 | AF12: =+I12/I11-1 -> 0.021375465 | ... AT12: =+W12/W11-1 -> 0.017277841
A13: =+[1]NAC!A14 -> 42948 | B13: =+[1]NAC!B14 -> 115.4 | C13: =+[1]NAC!C14 -> 114.3 | D13: =+[1]NAC!D14 -> 117.3 | E13: =+[1]NAC!E14 -> 107.7 | F13: =+[1]NAC!F14 -> 126.8 | G13: =+[1]NAC!G14 -> 111.2 | H13: =+[1]NAC!H14 -> 119 | ... N13: =+[1]NAC!N14 -> 113.6 | O13: =+[1]NAC!P14 -> 111.8 | P13: =+[1]NAC!Q14 -> 114.2 | Q13: =+[1]NAC!R14 -> 121.1 | R13: =+SUMPRODUCT($C$3:$N$3,C13:N13) -> 115.41012 | S13: =+($C$3*$C13+$D$3*$D13+$E$3*$E13+$G$3*$G13+$K$3*$K13+$M$3*$M13+$N$3*$N13)/SUM($C$3:$E$3,$G$3,$K$3,$M$3:$N$3) -> 113.40939 | T13: =+($E$3*$E13+$G$3*$G13+$K$3*$K13+$M$3*$M13+$N$3*$N13)/SUM($E$3,$G$3,$K$3,$M$3:$N$3) -> 112.36322 | U13: =+($E$3*$E13+$G$3*$G13+$K$3*$K13+$N$3*$N13)/SUM($E$3,$G$3,$K$3,$N$3) -> 111.62802 | W13: =($E$3*$E13+SUMPRODUCT($G$3:$L$3,$G13:$L13)+$N$3*$N13)/SUM($E$3,$G$3:$L$3,$N$3) -> 113.90882 | Y13: =+B13/B12-1 -> 0.014059754 | Z13: =+C13/C12-1 -> 0.020535714 | AA13: =+D13/D12-1 -> 0.012953368 | AB13: =+E13/E12-1 -> -0.0064575646 | AC13: =+F13/F12-1 -> 0.021756648 | AD13: =+G13/G12-1 -> 0.0099909173 | AE13: =+H13/H12-1 -> 0.024978467 | AF13: =+I13/I12-1 -> 0.010919017 | ... AT13: =+W13/W12-1 -> 0.010309044
A14: =+[1]NAC!A15 -> 42979 | B14: =+[1]NAC!B15 -> 117.6 | C14: =+[1]NAC!C15 -> 116.4 | D14: =+[1]NAC!D15 -> 118.1 | E14: =+[1]NAC!E15 -> 111.8 | F14: =+[1]NAC!F15 -> 129.3 | G14: =+[1]NAC!G15 -> 112.3 | H14: =+[1]NAC!H15 -> 121.9 | ... N14: =+[1]NAC!N15 -> 115.5 | O14: =+[1]NAC!P15 -> 116.2 | P14: =+[1]NAC!Q15 -> 116.1 | Q14: =+[1]NAC!R15 -> 123.2 | R14: =+SUMPRODUCT($C$3:$N$3,C14:N14) -> 117.62312 | S14: =+($C$3*$C14+$D$3*$D14+$E$3*$E14+$G$3*$G14+$K$3*$K14+$M$3*$M14+$N$3*$N14)/SUM($C$3:$E$3,$G$3,$K$3,$M$3:$N$3) -> 115.67394 | T14: =+($E$3*$E14+$G$3*$G14+$K$3*$K14+$M$3*$M14+$N$3*$N14)/SUM($E$3,$G$3,$K$3,$M$3:$N$3) -> 114.89355 | U14: =+($E$3*$E14+$G$3*$G14+$K$3*$K14+$N$3*$N14)/SUM($E$3,$G$3,$K$3,$N$3) -> 114.46413 | W14: =($E$3*$E14+SUMPRODUCT($G$3:$L$3,$G14:$L14)+$N$3*$N14)/SUM($E$3,$G$3:$L$3,$N$3) -> 116.33162 | Y14: =+B14/B13-1 -> 0.019064125 | Z14: =+C14/C13-1 -> 0.018372703 | AA14: =+D14/D13-1 -> 0.0068201194 | AB14: =+E14/E13-1 -> 0.038068709 | AC14: =+F14/F13-1 -> 0.019716088 | AD14: =+G14/G13-1 -> 0.0098920863 | AE14: =+H14/H13-1 -> 0.024369748 | AF14: =+I14/I13-1 -> 0.0081008101 | ... AT14: =+W14/W13-1 -> 0.021269587
A15: =+[1]NAC!A16 -> 43009 | B15: =+[1]NAC!B16 -> 119.4 | C15: =+[1]NAC!C16 -> 118.2 | D15: =+[1]NAC!D16 -> 121.7 | E15: =+[1]NAC!E16 -> 114.1 | F15: =+[1]NAC!F16 -> 130.4 | G15: =+[1]NAC!G16 -> 113.1 | H15: =+[1]NAC!H16 -> 123.2 | ... N15: =+[1]NAC!N16 -> 117.1 | O15: =+[1]NAC!P16 -> 119 | P15: =+[1]NAC!Q16 -> 117.6 | Q15: =+[1]NAC!R16 -> 125.3 | R15: =+SUMPRODUCT($C$3:$N$3,C15:N15) -> 119.39189 | S15: =+($C$3*$C15+$D$3*$D15+$E$3*$E15+$G$3*$G15+$K$3*$K15+$M$3*$M15+$N$3*$N15)/SUM($C$3:$E$3,$G$3,$K$3,$M$3:$N$3) -> 117.47653 | T15: =+($E$3*$E15+$G$3*$G15+$K$3*$K15+$M$3*$M15+$N$3*$N15)/SUM($E$3,$G$3,$K$3,$M$3:$N$3) -> 116.52339 | U15: =+($E$3*$E15+$G$3*$G15+$K$3*$K15+$N$3*$N15)/SUM($E$3,$G$3,$K$3,$N$3) -> 116.10378 | W15: =($E$3*$E15+SUMPRODUCT($G$3:$L$3,$G15:$L15)+$N$3*$N15)/SUM($E$3,$G$3:$L$3,$N$3) -> 118.11138 | Y15: =+B15/B14-1 -> 0.015306122 | Z15: =+C15/C14-1 -> 0.015463918 | AA15: =+D15/D14-1 -> 0.030482642 | AB15: =+E15/E14-1 -> 0.020572451 | AC15: =+F15/F14-1 -> 0.0085073473 | AD15: =+G15/G14-1 -> 0.0071237756 | AE15: =+H15/H14-1 -> 0.010664479 | AF15: =+I15/I14-1 -> 0.0125 | ... AT15: =+W15/W14-1 -> 0.015299068
A16: =+[1]NAC!A17 -> 43040 | B16: =+[1]NAC!B17 -> 121 | C16: =+[1]NAC!C17 -> 119.6 | D16: =+[1]NAC!D17 -> 123 | E16: =+[1]NAC!E17 -> 115.7 | F16: =+[1]NAC!F17 -> 132 | G16: =+[1]NAC!G17 -> 114.1 | H16: =+[1]NAC!H17 -> 124.8 | ... N16: =+[1]NAC!N17 -> 118.5 | O16: =+[1]NAC!P17 -> 121.1 | P16: =+[1]NAC!Q17 -> 119.1 | Q16: =+[1]NAC!R17 -> 127.1 | R16: =+SUMPRODUCT($C$3:$N$3,C16:N16) -> 121.04068 | S16: =+($C$3*$C16+$D$3*$D16+$E$3*$E16+$G$3*$G16+$K$3*$K16+$M$3*$M16+$N$3*$N16)/SUM($C$3:$E$3,$G$3,$K$3,$M$3:$N$3) -> 118.915 | T16: =+($E$3*$E16+$G$3*$G16+$K$3*$K16+$M$3*$M16+$N$3*$N16)/SUM($E$3,$G$3,$K$3,$M$3:$N$3) -> 118.00416 | U16: =+($E$3*$E16+$G$3*$G16+$K$3*$K16+$N$3*$N16)/SUM($E$3,$G$3,$K$3,$N$3) -> 117.34815 | W16: =($E$3*$E16+SUMPRODUCT($G$3:$L$3,$G16:$L16)+$N$3*$N16)/SUM($E$3,$G$3:$L$3,$N$3) -> 119.82831 | Y16: =+B16/B15-1 -> 0.013400335 | Z16: =+C16/C15-1 -> 0.011844332 | AA16: =+D16/D15-1 -> 0.010682005 | AB16: =+E16/E15-1 -> 0.014022787 | AC16: =+F16/F15-1 -> 0.012269939 | AD16: =+G16/G15-1 -> 0.008841733 | AE16: =+H16/H15-1 -> 0.012987013 | AF16: =+I16/I15-1 -> 0.029982363 | ... AT16: =+W16/W15-1 -> 0.014536514
A17: =+[1]NAC!A18 -> 43070 | B17: =+[1]NAC!B18 -> 124.8 | C17: =+[1]NAC!C18 -> 120.4 | D17: =+[1]NAC!D18 -> 123.7 | E17: =+[1]NAC!E18 -> 116.6 | F17: =+[1]NAC!F18 -> 155.6 | G17: =+[1]NAC!G18 -> 117.4 | H17: =+[1]NAC!H18 -> 127.8 | ... N17: =+[1]NAC!N18 -> 119.8 | O17: =+[1]NAC!P18 -> 121.5 | P17: =+[1]NAC!Q18 -> 121.1 | Q17: =+[1]NAC!R18 -> 138.7 | R17: =+SUMPRODUCT($C$3:$N$3,C17:N17) -> 124.825 | S17: =+($C$3*$C17+$D$3*$D17+$E$3*$E17+$G$3*$G17+$K$3*$K17+$M$3*$M17+$N$3*$N17)/SUM($C$3:$E$3,$G$3,$K$3,$M$3:$N$3) -> 120.17705 | T17: =+($E$3*$E17+$G$3*$G17+$K$3*$K17+$M$3*$M17+$N$3*$N17)/SUM($E$3,$G$3,$K$3,$M$3:$N$3) -> 119.66742 | U17: =+($E$3*$E17+$G$3*$G17+$K$3*$K17+$N$3*$N17)/SUM($E$3,$G$3,$K$3,$N$3) -> 118.86786 | W17: =($E$3*$E17+SUMPRODUCT($G$3:$L$3,$G17:$L17)+$N$3*$N17)/SUM($E$3,$G$3:$L$3,$N$3) -> 122.03885 | Y17: =+B17/B16-1 -> 0.031404959 | Z17: =+C17/C16-1 -> 0.0066889632 | AA17: =+D17/D16-1 -> 0.0056910569 | AB17: =+E17/E16-1 -> 0.0077787381 | AC17: =+F17/F16-1 -> 0.17878788 | AD17: =+G17/G16-1 -> 0.028921998 | AE17: =+H17/H16-1 -> 0.024038462 | AF17: =+I17/I16-1 -> 0.032534247 | ... AT17: =+W17/W16-1 -> 0.018447587 | AV17: =+B17/B5-1 -> 0.248 | AW17: =+C17/C5-1 -> 0.204 | AX17: =+D17/D5-1 -> 0.237 | AY17: =+E17/E5-1 -> 0.166 | AZ17: =+F17/F5-1 -> 0.556 | BA17: =+G17/G5-1 -> 0.174 | BB17: =+H17/H5-1 -> 0.278 | BC17: =+I17/I5-1 -> 0.206 | ... BQ17: =+W17/W5-1 -> 0.22038854
A18: =+[1]NAC!A19 -> 43101 | B18: =+[1]NAC!B19 -> 127 | C18: =+[1]NAC!C19 -> 122.9 | D18: =+[1]NAC!D19 -> 126.6 | E18: =+[1]NAC!E19 -> 115.7 | F18: =+[1]NAC!F19 -> 157.2 | G18: =+[1]NAC!G19 -> 118.7 | H18: =+[1]NAC!H19 -> 130 | ... N18: =+[1]NAC!N19 -> 122.7 | O18: =+[1]NAC!P19 -> 124.7 | P18: =+[1]NAC!Q19 -> 122.9 | Q18: =+[1]NAC!R19 -> 141.7 | R18: =+SUMPRODUCT($C$3:$N$3,C18:N18) -> 127.02727 | S18: =+($C$3*$C18+$D$3*$D18+$E$3*$E18+$G$3*$G18+$K$3*$K18+$M$3*$M18+$N$3*$N18)/SUM($C$3:$E$3,$G$3,$K$3,$M$3:$N$3) -> 122.43069 | T18: =+($E$3*$E18+$G$3*$G18+$K$3*$K18+$M$3*$M18+$N$3*$N18)/SUM($E$3,$G$3,$K$3,$M$3:$N$3) -> 121.67345 | U18: =+($E$3*$E18+$G$3*$G18+$K$3*$K18+$N$3*$N18)/SUM($E$3,$G$3,$K$3,$N$3) -> 120.34997 | W18: =($E$3*$E18+SUMPRODUCT($G$3:$L$3,$G18:$L18)+$N$3*$N18)/SUM($E$3,$G$3:$L$3,$N$3) -> 123.90447 | Y18: =+B18/B17-1 -> 0.017628205 | Z18: =+C18/C17-1 -> 0.02076412 | AA18: =+D18/D17-1 -> 0.023443816 | AB18: =+E18/E17-1 -> -0.0077186964 | AC18: =+F18/F17-1 -> 0.010282776 | AD18: =+G18/G17-1 -> 0.011073254 | AE18: =+H18/H17-1 -> 0.017214397 | AF18: =+I18/I17-1 -> 0.021558872 | ... AT18: =+W18/W17-1 -> 0.015287026 | AV18: =+B18/B6-1 -> 0.25 | AW18: =+C18/C6-1 -> 0.21322804 | AX18: =+D18/D6-1 -> 0.25470763 | AY18: =+E18/E6-1 -> 0.16868687 | AZ18: =+F18/F6-1 -> 0.54876847 | BA18: =+G18/G6-1 -> 0.17641229 | BB18: =+H18/H6-1 -> 0.26953125 | BC18: =+I18/I6-1 -> 0.20666014 | ... BQ18: =+W18/W6-1 -> 0.22029215
A19: =+[1]NAC!A20 -> 43132 | B19: =+[1]NAC!B20 -> 130.1 | C19: =+[1]NAC!C20 -> 125.6 | D19: =+[1]NAC!D20 -> 128.7 | E19: =+[1]NAC!E20 -> 115 | F19: =+[1]NAC!F20 -> 163.2 | G19: =+[1]NAC!G20 -> 120.7 | H19: =+[1]NAC!H20 -> 133.1 | ... N19: =+[1]NAC!N20 -> 124.9 | O19: =+[1]NAC!P20 -> 123.9 | P19: =+[1]NAC!Q20 -> 125.5 | Q19: =+[1]NAC!R20 -> 148.5 | R19: =+SUMPRODUCT($C$3:$N$3,C19:N19) -> 130.12872 | S19: =+($C$3*$C19+$D$3*$D19+$E$3*$E19+$G$3*$G19+$K$3*$K19+$M$3*$M19+$N$3*$N19)/SUM($C$3:$E$3,$G$3,$K$3,$M$3:$N$3) -> 124.33286 | T19: =+($E$3*$E19+$G$3*$G19+$K$3*$K19+$M$3*$M19+$N$3*$N19)/SUM($E$3,$G$3,$K$3,$M$3:$N$3) -> 122.95795 | U19: =+($E$3*$E19+$G$3*$G19+$K$3*$K19+$N$3*$N19)/SUM($E$3,$G$3,$K$3,$N$3) -> 121.20208 | W19: =($E$3*$E19+SUMPRODUCT($G$3:$L$3,$G19:$L19)+$N$3*$N19)/SUM($E$3,$G$3:$L$3,$N$3) -> 126.83914 | Y19: =+B19/B18-1 -> 0.024409449 | Z19: =+C19/C18-1 -> 0.021969081 | AA19: =+D19/D18-1 -> 0.016587678 | AB19: =+E19/E18-1 -> -0.0060501296 | AC19: =+F19/F18-1 -> 0.038167939 | AD19: =+G19/G18-1 -> 0.0168492 | AE19: =+H19/H18-1 -> 0.023846154 | AF19: =+I19/I18-1 -> 0.045454545 | ... AT19: =+W19/W18-1 -> 0.023684988 | AV19: =+B19/B7-1 -> 0.25458052 | AW19: =+C19/C7-1 -> 0.21705426 | AX19: =+D19/D7-1 -> 0.22338403 | AY19: =+E19/E7-1 -> 0.1627907 | AZ19: =+F19/F7-1 -> 0.52523364 | BA19: =+G19/G7-1 -> 0.19151037 | BB19: =+H19/H7-1 -> 0.26641294 | BC19: =+I19/I7-1 -> 0.23846154 | ... BQ19: =+W19/W7-1 -> 0.23159118
A20: =+[1]NAC!A21 -> 43160 | B20: =+[1]NAC!B21 -> 133.1 | C20: =+[1]NAC!C21 -> 128.5 | D20: =+[1]NAC!D21 -> 129.6 | E20: =+[1]NAC!E21 -> 120.1 | F20: =+[1]NAC!F21 -> 164.1 | G20: =+[1]NAC!G21 -> 126.2 | H20: =+[1]NAC!H21 -> 134.8 | ... N20: =+[1]NAC!N21 -> 127.2 | O20: =+[1]NAC!P21 -> 125.9 | P20: =+[1]NAC!Q21 -> 128.7 | Q20: =+[1]NAC!R21 -> 151.5 | R20: =+SUMPRODUCT($C$3:$N$3,C20:N20) -> 133.21068 | S20: =+($C$3*$C20+$D$3*$D20+$E$3*$E20+$G$3*$G20+$K$3*$K20+$M$3*$M20+$N$3*$N20)/SUM($C$3:$E$3,$G$3,$K$3,$M$3:$N$3) -> 127.44051 | T20: =+($E$3*$E20+$G$3*$G20+$K$3*$K20+$M$3*$M20+$N$3*$N20)/SUM($E$3,$G$3,$K$3,$M$3:$N$3) -> 126.43592 | U20: =+($E$3*$E20+$G$3*$G20+$K$3*$K20+$N$3*$N20)/SUM($E$3,$G$3,$K$3,$N$3) -> 125.06723 | W20: =($E$3*$E20+SUMPRODUCT($G$3:$L$3,$G20:$L20)+$N$3*$N20)/SUM($E$3,$G$3:$L$3,$N$3) -> 130.70398 | Y20: =+B20/B19-1 -> 0.023059185 | Z20: =+C20/C19-1 -> 0.023089172 | AA20: =+D20/D19-1 -> 0.006993007 | AB20: =+E20/E19-1 -> 0.044347826 | AC20: =+F20/F19-1 -> 0.0055147059 | AD20: =+G20/G19-1 -> 0.045567523 | AE20: =+H20/H19-1 -> 0.012772352 | AF20: =+I20/I19-1 -> 0.017857143 | ... AT20: =+W20/W19-1 -> 0.030470416 | AV20: =+B20/B8-1 -> 0.25447691 | AW20: =+C20/C8-1 -> 0.21226415 | AX20: =+D20/D8-1 -> 0.20782852 | AY20: =+E20/E8-1 -> 0.17399804 | AZ20: =+F20/F8-1 -> 0.48104693 | BA20: =+G20/G8-1 -> 0.23483366 | BB20: =+H20/H8-1 -> 0.25863679 | BC20: =+I20/I8-1 -> 0.24619772 | ... BQ20: =+W20/W8-1 -> 0.24015047
A21: =+[1]NAC!A22 -> 43191 | B21: =+[1]NAC!B22 -> 136.8 | C21: =+[1]NAC!C22 -> 130 | D21: =+[1]NAC!D22 -> 131.3 | E21: =+[1]NAC!E22 -> 124.9 | F21: =+[1]NAC!F22 -> 177.2 | G21: =+[1]NAC!G22 -> 127.8 | H21: =+[1]NAC!H22 -> 137.2 | ... N21: =+[1]NAC!N22 -> 129.3 | O21: =+[1]NAC!P22 -> 127 | P21: =+[1]NAC!Q22 -> 131.5 | Q21: =+[1]NAC!R22 -> 159.5 | R21: =+SUMPRODUCT($C$3:$N$3,C21:N21) -> 136.84927 | S21: =+($C$3*$C21+$D$3*$D21+$E$3*$E21+$G$3*$G21+$K$3*$K21+$M$3*$M21+$N$3*$N21)/SUM($C$3:$E$3,$G$3,$K$3,$M$3:$N$3) -> 129.79367 | T21: =+($E$3*$E21+$G$3*$G21+$K$3*$K21+$M$3*$M21+$N$3*$N21)/SUM($E$3,$G$3,$K$3,$M$3:$N$3) -> 129.49251 | U21: =+($E$3*$E21+$G$3*$G21+$K$3*$K21+$N$3*$N21)/SUM($E$3,$G$3,$K$3,$N$3) -> 128.14243 | W21: =($E$3*$E21+SUMPRODUCT($G$3:$L$3,$G21:$L21)+$N$3*$N21)/SUM($E$3,$G$3:$L$3,$N$3) -> 133.97038 | Y21: =+B21/B20-1 -> 0.027798648 | Z21: =+C21/C20-1 -> 0.011673152 | AA21: =+D21/D20-1 -> 0.013117284 | AB21: =+E21/E20-1 -> 0.039966694 | AC21: =+F21/F20-1 -> 0.079829372 | AD21: =+G21/G20-1 -> 0.012678288 | AE21: =+H21/H20-1 -> 0.017804154 | AF21: =+I21/I20-1 -> 0.039664378 | ... AT21: =+W21/W20-1 -> 0.024990783 | AV21: =+B21/B9-1 -> 0.25504587 | AW21: =+C21/C9-1 -> 0.19926199 | AX21: =+D21/D9-1 -> 0.19581056 | AY21: =+E21/E9-1 -> 0.16838167 | AZ21: =+F21/F9-1 -> 0.50936968 | BA21: =+G21/G9-1 -> 0.23717328 | BB21: =+H21/H9-1 -> 0.25756187 | BC21: =+I21/I9-1 -> 0.28706327 | ... BQ21: =+W21/W9-1 -> 0.24075778
A22: =+[1]NAC!A23 -> 43221 | B22: =+[1]NAC!B23 -> 139.6 | C22: =+[1]NAC!C23 -> 134.2 | D22: =+[1]NAC!D23 -> 133.4 | E22: =+[1]NAC!E23 -> 127.4 | F22: =+[1]NAC!F23 -> 175.9 | G22: =+[1]NAC!G23 -> 130.6 | H22: =+[1]NAC!H23 -> 140.3 | ... N22: =+[1]NAC!N23 -> 131.9 | O22: =+[1]NAC!P23 -> 130.2 | P22: =+[1]NAC!Q23 -> 135 | Q22: =+[1]NAC!R23 -> 160 | R22: =+SUMPRODUCT($C$3:$N$3,C22:N22) -> 139.71396 | S22: =+($C$3*$C22+$D$3*$D22+$E$3*$E22+$G$3*$G22+$K$3*$K22+$M$3*$M22+$N$3*$N22)/SUM($C$3:$E$3,$G$3,$K$3,$M$3:$N$3) -> 133.17826 | T22: =+($E$3*$E22+$G$3*$G22+$K$3*$K22+$M$3*$M22+$N$3*$N22)/SUM($E$3,$G$3,$K$3,$M$3:$N$3) -> 132.39032 | U22: =+($E$3*$E22+$G$3*$G22+$K$3*$K22+$N$3*$N22)/SUM($E$3,$G$3,$K$3,$N$3) -> 130.9409 | W22: =($E$3*$E22+SUMPRODUCT($G$3:$L$3,$G22:$L22)+$N$3*$N22)/SUM($E$3,$G$3:$L$3,$N$3) -> 136.89231 | Y22: =+B22/B21-1 -> 0.020467836 | Z22: =+C22/C21-1 -> 0.032307692 | AA22: =+D22/D21-1 -> 0.015993907 | AB22: =+E22/E21-1 -> 0.020016013 | AC22: =+F22/F21-1 -> -0.0073363431 | AD22: =+G22/G21-1 -> 0.021909233 | AE22: =+H22/H21-1 -> 0.022594752 | AF22: =+I22/I21-1 -> 0.019075569 | ... AT22: =+W22/W21-1 -> 0.02181026 | AV22: =+B22/B10-1 -> 0.26334842 | AW22: =+C22/C10-1 -> 0.22222222 | AX22: =+D22/D10-1 -> 0.19427037 | AY22: =+E22/E10-1 -> 0.17203312 | AZ22: =+F22/F10-1 -> 0.47196653 | BA22: =+G22/G10-1 -> 0.22975518 | BB22: =+H22/H10-1 -> 0.26738934 | BC22: =+I22/I10-1 -> 0.29934518 | ... BQ22: =+W22/W10-1 -> 0.25048486
A23: =+[1]NAC!A24 -> 43252 | B23: =+[1]NAC!B24 -> 144.8 | C23: =+[1]NAC!C24 -> 141.2 | D23: =+[1]NAC!D24 -> 134.6 | E23: =+[1]NAC!E24 -> 129.8 | F23: =+[1]NAC!F24 -> 180.6 | G23: =+[1]NAC!G24 -> 135.8 | H23: =+[1]NAC!H24 -> 146.3 | ... N23: =+[1]NAC!N24 -> 136.1 | O23: =+[1]NAC!P24 -> 134.5 | P23: =+[1]NAC!Q24 -> 140.5 | Q23: =+[1]NAC!R24 -> 164.7 | R23: =+SUMPRODUCT($C$3:$N$3,C23:N23) -> 144.91444 | S23: =+($C$3*$C23+$D$3*$D23+$E$3*$E23+$G$3*$G23+$K$3*$K23+$M$3*$M23+$N$3*$N23)/SUM($C$3:$E$3,$G$3,$K$3,$M$3:$N$3) -> 138.14922 | T23: =+($E$3*$E23+$G$3*$G23+$K$3*$K23+$M$3*$M23+$N$3*$N23)/SUM($E$3,$G$3,$K$3,$M$3:$N$3) -> 136.2058 | U23: =+($E$3*$E23+$G$3*$G23+$K$3*$K23+$N$3*$N23)/SUM($E$3,$G$3,$K$3,$N$3) -> 134.82721 | W23: =($E$3*$E23+SUMPRODUCT($G$3:$L$3,$G23:$L23)+$N$3*$N23)/SUM($E$3,$G$3:$L$3,$N$3) -> 141.78786 | Y23: =+B23/B22-1 -> 0.037249284 | Z23: =+C23/C22-1 -> 0.052160954 | AA23: =+D23/D22-1 -> 0.0089955022 | AB23: =+E23/E22-1 -> 0.018838305 | AC23: =+F23/F22-1 -> 0.026719727 | AD23: =+G23/G22-1 -> 0.039816233 | AE23: =+H23/H22-1 -> 0.042765502 | AF23: =+I23/I22-1 -> 0.05975522 | ... AT23: =+W23/W22-1 -> 0.035762105 | AV23: =+B23/B11-1 -> 0.29516995 | AW23: =+C23/C11-1 -> 0.27551942 | AX23: =+D23/D11-1 -> 0.19644444 | AY23: =+E23/E11-1 -> 0.18322698 | AZ23: =+F23/F11-1 -> 0.48519737 | BA23: =+G23/G11-1 -> 0.26325581 | BB23: =+H23/H11-1 -> 0.30160142 | BC23: =+I23/I11-1 -> 0.36802974 | ... BQ23: =+W23/W11-1 -> 0.27930917
A24: =+[1]NAC!A25 -> 43282 | B24: =+[1]NAC!B25 -> 149.3 | C24: =+[1]NAC!C25 -> 146.8 | D24: =+[1]NAC!D25 -> 138.1 | E24: =+[1]NAC!E25 -> 129.6 | F24: =+[1]NAC!F25 -> 182.4 | G24: =+[1]NAC!G25 -> 141.5 | H24: =+[1]NAC!H25 -> 150.4 | ... N24: =+[1]NAC!N25 -> 141.4 | O24: =+[1]NAC!P25 -> 139.6 | P24: =+[1]NAC!Q25 -> 145 | Q24: =+[1]NAC!R25 -> 169 | R24: =+SUMPRODUCT($C$3:$N$3,C24:N24) -> 149.37523 | S24: =+($C$3*$C24+$D$3*$D24+$E$3*$E24+$G$3*$G24+$K$3*$K24+$M$3*$M24+$N$3*$N24)/SUM($C$3:$E$3,$G$3,$K$3,$M$3:$N$3) -> 142.71894 | T24: =+($E$3*$E24+$G$3*$G24+$K$3*$K24+$M$3*$M24+$N$3*$N24)/SUM($E$3,$G$3,$K$3,$M$3:$N$3) -> 140.10667 | U24: =+($E$3*$E24+$G$3*$G24+$K$3*$K24+$N$3*$N24)/SUM($E$3,$G$3,$K$3,$N$3) -> 138.6955 | W24: =($E$3*$E24+SUMPRODUCT($G$3:$L$3,$G24:$L24)+$N$3*$N24)/SUM($E$3,$G$3:$L$3,$N$3) -> 146.28401 | Y24: =+B24/B23-1 -> 0.031077348 | Z24: =+C24/C23-1 -> 0.039660057 | AA24: =+D24/D23-1 -> 0.026002972 | AB24: =+E24/E23-1 -> -0.001540832 | AC24: =+F24/F23-1 -> 0.0099667774 | AD24: =+G24/G23-1 -> 0.04197349 | AE24: =+H24/H23-1 -> 0.028024607 | AF24: =+I24/I23-1 -> 0.051630435 | ... AT24: =+W24/W23-1 -> 0.03171041 | AV24: =+B24/B12-1 -> 0.31195079 | AW24: =+C24/C12-1 -> 0.31071429 | AX24: =+D24/D12-1 -> 0.1925734 | AY24: =+E24/E12-1 -> 0.19557196 | AZ24: =+F24/F12-1 -> 0.46978243 | BA24: =+G24/G12-1 -> 0.28519528 | BB24: =+H24/H12-1 -> 0.29543497 | BC24: =+I24/I12-1 -> 0.40855323 | ... BQ24: =+W24/W12-1 -> 0.29745929
A25: =+[1]NAC!A26 -> 43313 | B25: =+[1]NAC!B26 -> 155.1 | C25: =+[1]NAC!C26 -> 152.7 | D25: =+[1]NAC!D26 -> 140 | E25: =+[1]NAC!E26 -> 130.1 | F25: =+[1]NAC!F26 -> 193.7 | G25: =+[1]NAC!G26 -> 146 | H25: =+[1]NAC!H26 -> 156.5 | ... N25: =+[1]NAC!N26 -> 148.3 | O25: =+[1]NAC!P26 -> 142.3 | P25: =+[1]NAC!Q26 -> 149.8 | Q25: =+[1]NAC!R26 -> 179.5 | R25: =+SUMPRODUCT($C$3:$N$3,C25:N25) -> 155.16175 | S25: =+($C$3*$C25+$D$3*$D25+$E$3*$E25+$G$3*$G25+$K$3*$K25+$M$3*$M25+$N$3*$N25)/SUM($C$3:$E$3,$G$3,$K$3,$M$3:$N$3) -> 147.08139 | T25: =+($E$3*$E25+$G$3*$G25+$K$3*$K25+$M$3*$M25+$N$3*$N25)/SUM($E$3,$G$3,$K$3,$M$3:$N$3) -> 143.55515 | U25: =+($E$3*$E25+$G$3*$G25+$K$3*$K25+$N$3*$N25)/SUM($E$3,$G$3,$K$3,$N$3) -> 142.12705 | W25: =($E$3*$E25+SUMPRODUCT($G$3:$L$3,$G25:$L25)+$N$3*$N25)/SUM($E$3,$G$3:$L$3,$N$3) -> 151.65799 | Y25: =+B25/B24-1 -> 0.038847957 | Z25: =+C25/C24-1 -> 0.040190736 | AA25: =+D25/D24-1 -> 0.013758146 | AB25: =+E25/E24-1 -> 0.0038580247 | AC25: =+F25/F24-1 -> 0.061951754 | AD25: =+G25/G24-1 -> 0.03180212 | AE25: =+H25/H24-1 -> 0.040558511 | AF25: =+I25/I24-1 -> 0.040697674 | ... AT25: =+W25/W24-1 -> 0.03673661 | AV25: =+B25/B13-1 -> 0.3440208 | AW25: =+C25/C13-1 -> 0.33595801 | AX25: =+D25/D13-1 -> 0.19352089 | AY25: =+E25/E13-1 -> 0.20798514 | AZ25: =+F25/F13-1 -> 0.52760252 | BA25: =+G25/G13-1 -> 0.31294964 | BB25: =+H25/H13-1 -> 0.31512605 | BC25: =+I25/I13-1 -> 0.450045 | ... BQ25: =+W25/W13-1 -> 0.33139811
A26: =+[1]NAC!A27 -> 43344 | B26: =+[1]NAC!B27 -> 165.2 | C26: =+[1]NAC!C27 -> 163.4 | D26: =+[1]NAC!D27 -> 146.2 | E26: =+[1]NAC!E27 -> 142.8 | F26: =+[1]NAC!F27 -> 198.1 | G26: =+[1]NAC!G27 -> 160.2 | H26: =+[1]NAC!H27 -> 163.6 | ... N26: =+[1]NAC!N27 -> 160.1 | O26: =+[1]NAC!P27 -> 148 | P26: =+[1]NAC!Q27 -> 161.3 | Q26: =+[1]NAC!R27 -> 187.9 | R26: =+SUMPRODUCT($C$3:$N$3,C26:N26) -> 165.34949 | S26: =+($C$3*$C26+$D$3*$D26+$E$3*$E26+$G$3*$G26+$K$3*$K26+$M$3*$M26+$N$3*$N26)/SUM($C$3:$E$3,$G$3,$K$3,$M$3:$N$3) -> 157.91047 | T26: =+($E$3*$E26+$G$3*$G26+$K$3*$K26+$M$3*$M26+$N$3*$N26)/SUM($E$3,$G$3,$K$3,$M$3:$N$3) -> 154.93095 | U26: =+($E$3*$E26+$G$3*$G26+$K$3*$K26+$N$3*$N26)/SUM($E$3,$G$3,$K$3,$N$3) -> 154.44809 | W26: =($E$3*$E26+SUMPRODUCT($G$3:$L$3,$G26:$L26)+$N$3*$N26)/SUM($E$3,$G$3:$L$3,$N$3) -> 163.20773 | Y26: =+B26/B25-1 -> 0.065119278 | Z26: =+C26/C25-1 -> 0.070072037 | AA26: =+D26/D25-1 -> 0.044285714 | AB26: =+E26/E25-1 -> 0.097617218 | AC26: =+F26/F25-1 -> 0.022715539 | AD26: =+G26/G25-1 -> 0.097260274 | AE26: =+H26/H25-1 -> 0.045367412 | AF26: =+I26/I25-1 -> 0.10366232 | ... AT26: =+W26/W25-1 -> 0.076156481 | AV26: =+B26/B14-1 -> 0.4047619 | AW26: =+C26/C14-1 -> 0.40378007 | AX26: =+D26/D14-1 -> 0.23793395 | AY26: =+E26/E14-1 -> 0.27728086 | AZ26: =+F26/F14-1 -> 0.5320959 | BA26: =+G26/G14-1 -> 0.42653606 | BB26: =+H26/H14-1 -> 0.34208368 | BC26: =+I26/I14-1 -> 0.5875 | ... BQ26: =+W26/W14-1 -> 0.40295249
A27: =+[1]NAC!A28 -> 43374 | B27: =+[1]NAC!B28 -> 174.1 | C27: =+[1]NAC!C28 -> 173 | D27: =+[1]NAC!D28 -> 149.6 | E27: =+[1]NAC!E28 -> 150 | F27: =+[1]NAC!F28 -> 215.5 | G27: =+[1]NAC!G28 -> 167 | H27: =+[1]NAC!H28 -> 172.6 | ... N27: =+[1]NAC!N28 -> 170 | O27: =+[1]NAC!P28 -> 157.2 | P27: =+[1]NAC!Q28 -> 168.6 | Q27: =+[1]NAC!R28 -> 201.9 | R27: =+SUMPRODUCT($C$3:$N$3,C27:N27) -> 174.28502 | S27: =+($C$3*$C27+$D$3*$D27+$E$3*$E27+$G$3*$G27+$K$3*$K27+$M$3*$M27+$N$3*$N27)/SUM($C$3:$E$3,$G$3,$K$3,$M$3:$N$3) -> 165.37572 | T27: =+($E$3*$E27+$G$3*$G27+$K$3*$K27+$M$3*$M27+$N$3*$N27)/SUM($E$3,$G$3,$K$3,$M$3:$N$3) -> 161.19003 | U27: =+($E$3*$E27+$G$3*$G27+$K$3*$K27+$N$3*$N27)/SUM($E$3,$G$3,$K$3,$N$3) -> 161.15389 | W27: =($E$3*$E27+SUMPRODUCT($G$3:$L$3,$G27:$L27)+$N$3*$N27)/SUM($E$3,$G$3:$L$3,$N$3) -> 171.31333 | Y27: =+B27/B26-1 -> 0.053874092 | Z27: =+C27/C26-1 -> 0.05875153 | AA27: =+D27/D26-1 -> 0.023255814 | AB27: =+E27/E26-1 -> 0.050420168 | AC27: =+F27/F26-1 -> 0.087834427 | AD27: =+G27/G26-1 -> 0.042446941 | AE27: =+H27/H26-1 -> 0.055012225 | AF27: =+I27/I26-1 -> 0.076490439 | ... AT27: =+W27/W26-1 -> 0.049664304 | AV27: =+B27/B15-1 -> 0.45812395 | AW27: =+C27/C15-1 -> 0.46362098 | AX27: =+D27/D15-1 -> 0.22925226 | AY27: =+E27/E15-1 -> 0.31463628 | AZ27: =+F27/F15-1 -> 0.65260736 | BA27: =+G27/G15-1 -> 0.47656941 | BB27: =+H27/H15-1 -> 0.40097403 | BC27: =+I27/I15-1 -> 0.68783069 | ... BQ27: =+W27/W15-1 -> 0.45043878
A28: =+[1]NAC!A29 -> 43405 | B28: =+[1]NAC!B29 -> 179.6 | C28: =+[1]NAC!C29 -> 178.9 | D28: =+[1]NAC!D29 -> 156.5 | E28: =+[1]NAC!E29 -> 153.4 | F28: =+[1]NAC!F29 -> 220.1 | G28: =+[1]NAC!G29 -> 173 | H28: =+[1]NAC!H29 -> 182.3 | ... N28: =+[1]NAC!N29 -> 177.5 | O28: =+[1]NAC!P29 -> 161.9 | P28: =+[1]NAC!Q29 -> 174.2 | Q28: =+[1]NAC!R29 -> 207.5 | R28: =+SUMPRODUCT($C$3:$N$3,C28:N28) -> 179.78539 | S28: =+($C$3*$C28+$D$3*$D28+$E$3*$E28+$G$3*$G28+$K$3*$K28+$M$3*$M28+$N$3*$N28)/SUM($C$3:$E$3,$G$3,$K$3,$M$3:$N$3) -> 170.67857 | T28: =+($E$3*$E28+$G$3*$G28+$K$3*$K28+$M$3*$M28+$N$3*$N28)/SUM($E$3,$G$3,$K$3,$M$3:$N$3) -> 165.88975 | U28: =+($E$3*$E28+$G$3*$G28+$K$3*$K28+$N$3*$N28)/SUM($E$3,$G$3,$K$3,$N$3) -> 166.05073 | W28: =($E$3*$E28+SUMPRODUCT($G$3:$L$3,$G28:$L28)+$N$3*$N28)/SUM($E$3,$G$3:$L$3,$N$3) -> 176.91676 | Y28: =+B28/B27-1 -> 0.03159104 | Z28: =+C28/C27-1 -> 0.034104046 | AA28: =+D28/D27-1 -> 0.046122995 | AB28: =+E28/E27-1 -> 0.022666667 | AC28: =+F28/F27-1 -> 0.021345708 | AD28: =+G28/G27-1 -> 0.035928144 | AE28: =+H28/H27-1 -> 0.056199305 | AF28: =+I28/I27-1 -> 0.026645768 | ... AT28: =+W28/W27-1 -> 0.032708648 | AV28: =+B28/B16-1 -> 0.48429752 | AW28: =+C28/C16-1 -> 0.4958194 | AX28: =+D28/D16-1 -> 0.27235772 | AY28: =+E28/E16-1 -> 0.3258427 | AZ28: =+F28/F16-1 -> 0.66742424 | BA28: =+G28/G16-1 -> 0.51621385 | BB28: =+H28/H16-1 -> 0.46073718 | BC28: =+I28/I16-1 -> 0.68236301 | ... BQ28: =+W28/W16-1 -> 0.47641869
... A118: =+[1]NAC!A119 -> 46143 | B118: =+[1]NAC!B119 -> 11607.4 | C118: =+[1]NAC!C119 -> 12495 | D118: =+[1]NAC!D119 -> 8033.3 | E118: =+[1]NAC!E119 -> 8350.2 | F118: =+[1]NAC!F119 -> 12790.1 | G118: =+[1]NAC!G119 -> 9312.2 | H118: =+[1]NAC!H119 -> 12832 | ... N118: =+[1]NAC!N119 -> 11171.6 | O118: =+[1]NAC!P119 -> 9420.5 | P118: =+[1]NAC!Q119 -> 11824.7 | Q118: =+[1]NAC!R119 -> 12111.5 | R118: =+SUMPRODUCT($C$3:$N$3,C118:N118) -> 11618.873 | S118: =+($C$3*$C118+$D$3*$D118+$E$3*$E118+$G$3*$G118+$K$3*$K118+$M$3*$M118+$N$3*$N118)/SUM($C$3:$E$3,$G$3,$K$3,$M$3:$N$3) -> 11249.073 | T118: =+($E$3*$E118+$G$3*$G118+$K$3*$K118+$M$3*$M118+$N$3*$N118)/SUM($E$3,$G$3,$K$3,$M$3:$N$3) -> 10627.051 | U118: =+($E$3*$E118+$G$3*$G118+$K$3*$K118+$N$3*$N118)/SUM($E$3,$G$3,$K$3,$N$3) -> 9422.5857 | W118: =($E$3*$E118+SUMPRODUCT($G$3:$L$3,$G118:$L118)+$N$3*$N118)/SUM($E$3,$G$3:$L$3,$N$3) -> 10721.509 | Y118: =+B118/B117-1 -> 0.021499415 | Z118: =+C118/C117-1 -> 0.024608648 | AA118: =+D118/D117-1 -> 0.0079422836 | AB118: =+E118/E117-1 -> 0.0028222465 | AC118: =+F118/F117-1 -> 0.025612035 | AD118: =+G118/G117-1 -> 0.014091562 | AE118: =+H118/H117-1 -> 0.025870615 | AF118: =+I118/I117-1 -> 0.019757518 | ... AT118: =+W118/W117-1 -> 0.020226474 | AV118: =+B118/B106-1 -> 0.33196397 | AW118: =+C118/C106-1 -> 0.33418043 | AX118: =+D118/D106-1 -> 0.24012782 | AY118: =+E118/E106-1 -> 0.12026081 | AZ118: =+F118/F106-1 -> 0.48006156 | BA118: =+G118/G106-1 -> 0.23495789 | BB118: =+H118/H106-1 -> 0.29540269 | BC118: =+I118/I106-1 -> 0.42121946 | ... BQ118: =+W118/W106-1 -> 0.29758896

Sheet GBA
B1: Índices | Y1: Tasas de inflación mensual | AV1: Tasas de inflación interanual | BS1: Incidencia mensual | CH1: Incidencia Feb 21 - Jun 24
R2: =+SUM(C3:N3) -> 1 | S2: =+SUM($C$3:$E$3,$G$3,$K$3,$M$3:$N$3) -> 0.6332 | T2: =+SUM($E$3,$G$3,$K$3,$M$3:$N$3) -> 0.3661 | U2: =+SUM($E$3,$G$3,$K$3,$N$3) -> 0.2577 | W2: =+SUM(E3,G3:L3,N3) -> 0.5199 | AT2: =+SUM(AB3,AD3:AI3,AK3) -> 0.5199 | BL2: =+SUM(AW3:BH3) -> 1 | BQ2: =+SUM(AY3,BA3:BF3,BH3) -> 0.5199
C3: =+[1]GBA!C$3 -> 0.2344 | D3: =+[1]GBA!D$3 -> 0.0327 | E3: =+[1]GBA!E$3 -> 0.0849 | F3: =+[1]GBA!F$3 -> 0.1046 | G3: =+[1]GBA!G$3 -> 0.0627 | H3: =+[1]GBA!H$3 -> 0.088 | I3: =+[1]GBA!I$3 -> 0.1159 | J3: =+[1]GBA!J$3 -> 0.0281 | ... N3: =+[1]GBA!N$3 -> 0.0355 | R3: headline | V3: no food & energy | W3: no food & energy & shelter | Z3: =+C3 -> 0.2344 | AA3: =+D3 -> 0.0327 | AB3: =+E3 -> 0.0849 | AC3: =+F3 -> 0.1046 | AD3: =+G3 -> 0.0627 | AE3: =+H3 -> 0.088 | AF3: =+I3 -> 0.1159 | AG3: =+J3 -> 0.0281 | ... AK3: =+N3 -> 0.0355 | AL3: 0.108 | AM3: 0.699 | AN3: 0.194 | AO3: headline | AS3: no food & energy | AT3: no food & energy & shelter | AW3: =+Z3 -> 0.2344 | AX3: =+AA3 -> 0.0327 | AY3: =+AB3 -> 0.0849 | AZ3: =+AC3 -> 0.1046 | BA3: =+AD3 -> 0.0627 | BB3: =+AE3 -> 0.088 | BC3: =+AF3 -> 0.1159 | BD3: =+AG3 -> 0.0281 | ... BH3: =+AK3 -> 0.0355 | BL3: headline | BP3: no food & energy | BQ3: no food & energy & shelter | BT3: =+AW3 -> 0.2344 | BU3: =+AX3 -> 0.0327 | BV3: =+AY3 -> 0.0849 | BW3: =+AZ3 -> 0.1046 | BX3: =+BA3 -> 0.0627 | BY3: =+BB3 -> 0.088 | BZ3: =+BC3 -> 0.1159 | CA3: =+BD3 -> 0.0281 | ... CE3: =+BH3 -> 0.0355 | CH3: 1 | CI3: =+BT3 -> 0.2344 | CJ3: =+BU3 -> 0.0327 | CK3: =+BV3 -> 0.0849 | CL3: =+BW3 -> 0.1046 | CM3: =+BX3 -> 0.0627 | CN3: =+BY3 -> 0.088 | CO3: =+BZ3 -> 0.1159 | CP3: =+CA3 -> 0.0281 | ... CT3: =+CE3 -> 0.0355
A4: Fecha | B4: Nivel general | C4: Alimentos y bebidas no alcohólicas | D4: Bebidas alcohólicas y tabaco | E4: Prendas de vestir y calzado | F4: Vivienda, agua, electricidad, gas y otros combustibles | G4: Equipamiento y mantenimiento del hogar | H4: Salud | I4: Transporte | J4: Comunicación | K4: Recreación y cultura | L4: Educación | M4: Restaurantes y hoteles | N4: Bienes y servicios varios | O4: Estacional | P4: Núcleo | Q4: Regulados | R4: Nivel General | S4: Subyacente | T4: Subyacente-AyB | U4: Subyacente-Food | V4: Core | W4: Supercore | Y4: Nivel general | Z4: Alimentos y bebidas no alcohólicas | AA4: Bebidas alcohólicas y tabaco | AB4: Prendas de vestir y calzado | AC4: Vivienda, agua, electricidad, gas y otros combustibles | AD4: Equipamiento y mantenimiento del hogar | AE4: Salud | AF4: Transporte | AG4: Comunicación | AH4: Recreación y cultura | AI4: Educación | AJ4: Restaurantes y hoteles | AK4: Bienes y servicios varios | AL4: Estacional | AM4: Núcleo | AN4: Regulados | AO4: =+R4 -> Nivel General | AP4: =+S4 -> Subyacente | AQ4: =+T4 -> Subyacente-AyB | AR4: =+U4 -> Subyacente-Food | AS4: Core | AT4: Supercore | AV4: Nivel general | AW4: Alimentos y bebidas no alcohólicas | AX4: Bebidas alcohólicas y tabaco | AY4: Prendas de vestir y calzado | AZ4: Vivienda, agua, electricidad, gas y otros combustibles | BA4: Equipamiento y mantenimiento del hogar | BB4: Salud | BC4: Transporte | BD4: Comunicación | BE4: Recreación y cultura | BF4: Educación | BG4: Restaurantes y hoteles | BH4: Bienes y servicios varios | BI4: Estacional | BJ4: Núcleo | BK4: Regulados | BL4: =+AO4 -> Nivel General | BM4: =+AP4 -> Subyacente | BN4: =+AQ4 -> Subyacente-AyB | BO4: =+AR4 -> Subyacente-Food | BP4: Core | BQ4: Supercore | BS4: Fecha | BT4: Alimentos y bebidas no alcohólicas | BU4: Bebidas alcohólicas y tabaco | BV4: Prendas de vestir y calzado | BW4: Vivienda, agua, electricidad, gas y otros combustibles | BX4: Equipamiento y mantenimiento del hogar | BY4: Salud | BZ4: Transporte | CA4: Comunicación | CB4: Recreación y cultura | CC4: Educación | CD4: Restaurantes y hoteles | CE4: Bienes y servicios varios | CF4: Nivel general | CH4: Fecha | CI4: Alimentos y bebidas no alcohólicas | CJ4: Bebidas alcohólicas y tabaco | CK4: Prendas de vestir y calzado | CL4: Vivienda, agua, electricidad, gas y otros combustibles | CM4: Equipamiento y mantenimiento del hogar | CN4: Salud | CO4: Transporte | CP4: Comunicación | CQ4: Recreación y cultura | CR4: Educación | CS4: Restaurantes y hoteles | CT4: Bienes y servicios varios | CU4: Nivel general
A5: =+[1]NAC!A6 -> 42705 | B5: =+[1]GBA!B6 -> 100 | C5: =+[1]GBA!C6 -> 100 | D5: =+[1]GBA!D6 -> 100 | E5: =+[1]GBA!E6 -> 100 | F5: =+[1]GBA!F6 -> 100 | G5: =+[1]GBA!G6 -> 100 | H5: =+[1]GBA!H6 -> 100 | I5: =+[1]GBA!I6 -> 100 | ... N5: =+[1]GBA!N6 -> 100 | O5: =+[1]GBA!R6 -> 100 | P5: =+[1]GBA!S6 -> 100 | Q5: =+[1]GBA!T6 -> 100 | R5: =+SUMPRODUCT($C$3:$N$3,C5:N5) -> 100 | S5: =+($C$3*$C5+$D$3*$D5+$E$3*$E5+$G$3*$G5+$K$3*$K5+$M$3*$M5+$N$3*$N5)/SUM($C$3:$E$3,$G$3,$K$3,$M$3:$N$3) -> 100 | T5: =+($E$3*$E5+$G$3*$G5+$K$3*$K5+$M$3*$M5+$N$3*$N5)/SUM($E$3,$G$3,$K$3,$M$3:$N$3) -> 100 | U5: =+($E$3*$E5+$G$3*$G5+$K$3*$K5+$N$3*$N5)/SUM($E$3,$G$3,$K$3,$N$3) -> 100 | W5: =($E$3*$E5+SUMPRODUCT($G$3:$L$3,$G5:$L5)+$N$3*$N5)/SUM($E$3,$G$3:$L$3,$N$3) -> 100 | BS5: =+A5 -> 42705
A6: =+[1]NAC!A7 -> 42736 | B6: =+[1]GBA!B7 -> 101.3 | C6: =+[1]GBA!C7 -> 101.3 | D6: =+[1]GBA!D7 -> 100.5 | E6: =+[1]GBA!E7 -> 97.9 | F6: =+[1]GBA!F7 -> 100 | G6: =+[1]GBA!G7 -> 100.9 | H6: =+[1]GBA!H7 -> 101.4 | I6: =+[1]GBA!I7 -> 101.8 | ... N6: =+[1]GBA!N7 -> 102.1 | O6: =+[1]GBA!R7 -> 101.6 | P6: =+[1]GBA!S7 -> 101.3 | Q6: =+[1]GBA!T7 -> 101.1 | R6: =+SUMPRODUCT($C$3:$N$3,C6:N6) -> 101.3239 | S6: =+($C$3*$C6+$D$3*$D6+$E$3*$E6+$G$3*$G6+$K$3*$K6+$M$3*$M6+$N$3*$N6)/SUM($C$3:$E$3,$G$3,$K$3,$M$3:$N$3) -> 101.37429 | T6: =+($E$3*$E6+$G$3*$G6+$K$3*$K6+$M$3*$M6+$N$3*$N6)/SUM($E$3,$G$3,$K$3,$M$3:$N$3) -> 101.49995 | U6: =+($E$3*$E6+$G$3*$G6+$K$3*$K6+$N$3*$N6)/SUM($E$3,$G$3,$K$3,$N$3) -> 100.74276 | W6: =($E$3*$E6+SUMPRODUCT($G$3:$L$3,$G6:$L6)+$N$3*$N6)/SUM($E$3,$G$3:$L$3,$N$3) -> 101.24083 | Y6: =+B6/B5-1 -> 0.013 | Z6: =+C6/C5-1 -> 0.013 | AA6: =+D6/D5-1 -> 0.005 | AB6: =+E6/E5-1 -> -0.021 | AC6: =+F6/F5-1 -> 0 | AD6: =+G6/G5-1 -> 0.009 | AE6: =+H6/H5-1 -> 0.014 | AF6: =+I6/I5-1 -> 0.018 | ... AT6: =+W6/W5-1 -> 0.012408348 | BS6: =+A6 -> 42736 | BT6: =(C6-C5)/$B5*C$3 -> 0.0030472 | BU6: =(D6-D5)/$B5*D$3 -> 0.0001635 | BV6: =(E6-E5)/$B5*E$3 -> -0.0017829 | BW6: =(F6-F5)/$B5*F$3 -> 0 | BX6: =(G6-G5)/$B5*G$3 -> 0.0005643 | BY6: =(H6-H5)/$B5*H$3 -> 0.001232 | BZ6: =(I6-I5)/$B5*I$3 -> 0.0020862 | CA6: =(J6-J5)/$B5*J$3 -> 0.0010678 | ... CE6: =(N6-N5)/$B5*N$3 -> 0.0007455 | CF6: =+SUM(BT6:CE6) -> 0.013239 | CH6: =+CH$3*(B$95-B$55)/$B$55 -> 14.606196 | CI6: =+CI$3*(C$95-C$55)/$B$55 -> 3.9148576 | CJ6: =+CJ$3*(D$95-D$55)/$B$55 -> 0.36350082 | CK6: =+CK$3*(E$95-E$55)/$B$55 -> 1.1726089 | CL6: =+CL$3*(F$95-F$55)/$B$55 -> 1.2681357 | CM6: =+CM$3*(G$95-G$55)/$B$55 -> 0.87024803 | CN6: =+CN$3*(H$95-H$55)/$B$55 -> 1.3690706 | CO6: =+CO$3*(I$95-I$55)/$B$55 -> 1.6954719 | ... CT6: =+CT$3*(N$95-N$55)/$B$55 -> 0.50825266
A7: =+[1]NAC!A8 -> 42767 | B7: =+[1]GBA!B8 -> 103.8 | C7: =+[1]GBA!C8 -> 103.2 | D7: =+[1]GBA!D8 -> 105.5 | E7: =+[1]GBA!E8 -> 97.4 | F7: =+[1]GBA!F8 -> 108.4 | G7: =+[1]GBA!G8 -> 101.2 | H7: =+[1]GBA!H8 -> 104.7 | I7: =+[1]GBA!I8 -> 103.5 | ... N7: =+[1]GBA!N8 -> 104.1 | O7: =+[1]GBA!R8 -> 102.1 | P7: =+[1]GBA!S8 -> 103.2 | Q7: =+[1]GBA!T8 -> 106.3 | R7: =+SUMPRODUCT($C$3:$N$3,C7:N7) -> 103.79967 | S7: =+($C$3*$C7+$D$3*$D7+$E$3*$E7+$G$3*$G7+$K$3*$K7+$M$3*$M7+$N$3*$N7)/SUM($C$3:$E$3,$G$3,$K$3,$M$3:$N$3) -> 102.73057 | T7: =+($E$3*$E7+$G$3*$G7+$K$3*$K7+$M$3*$M7+$N$3*$N7)/SUM($E$3,$G$3,$K$3,$M$3:$N$3) -> 102.18266 | U7: =+($E$3*$E7+$G$3*$G7+$K$3*$K7+$N$3*$N7)/SUM($E$3,$G$3,$K$3,$N$3) -> 100.95549 | W7: =($E$3*$E7+SUMPRODUCT($G$3:$L$3,$G7:$L7)+$N$3*$N7)/SUM($E$3,$G$3:$L$3,$N$3) -> 102.76642 | Y7: =+B7/B6-1 -> 0.024679171 | Z7: =+C7/C6-1 -> 0.01875617 | AA7: =+D7/D6-1 -> 0.049751244 | AB7: =+E7/E6-1 -> -0.0051072523 | AC7: =+F7/F6-1 -> 0.084 | AD7: =+G7/G6-1 -> 0.0029732408 | AE7: =+H7/H6-1 -> 0.032544379 | AF7: =+I7/I6-1 -> 0.016699411 | ... AT7: =+W7/W6-1 -> 0.015068839 | BS7: =+A7 -> 42767 | BT7: =(C7-C6)/$B6*C$3 -> 0.0043964462 | BU7: =(D7-D6)/$B6*D$3 -> 0.0016140178 | BV7: =(E7-E6)/$B6*E$3 -> -0.00041905232 | BW7: =(F7-F6)/$B6*F$3 -> 0.0086736426 | BX7: =(G7-G6)/$B6*G$3 -> 0.00018568608 | BY7: =(H7-H6)/$B6*H$3 -> 0.0028667325 | BZ7: =(I7-I6)/$B6*I$3 -> 0.0019450148 | CA7: =(J7-J6)/$B6*J$3 -> 0.0011650543 | ... CE7: =(N7-N6)/$B6*N$3 -> 0.00070088845 | CF7: =+SUM(BT7:CE7) -> 0.02443998
A8: =+[1]NAC!A9 -> 42795 | B8: =+[1]GBA!B9 -> 106.3 | C8: =+[1]GBA!C9 -> 106.8 | D8: =+[1]GBA!D9 -> 107.1 | E8: =+[1]GBA!E9 -> 102.1 | F8: =+[1]GBA!F9 -> 110.8 | G8: =+[1]GBA!G9 -> 102.1 | H8: =+[1]GBA!H9 -> 106.7 | I8: =+[1]GBA!I9 -> 104.6 | ... N8: =+[1]GBA!N9 -> 105.6 | O8: =+[1]GBA!R9 -> 105.9 | P8: =+[1]GBA!S9 -> 105.1 | Q8: =+[1]GBA!T9 -> 109.9 | R8: =+SUMPRODUCT($C$3:$N$3,C8:N8) -> 106.27748 | S8: =+($C$3*$C8+$D$3*$D8+$E$3*$E8+$G$3*$G8+$K$3*$K8+$M$3*$M8+$N$3*$N8)/SUM($C$3:$E$3,$G$3,$K$3,$M$3:$N$3) -> 105.31429 | T8: =+($E$3*$E8+$G$3*$G8+$K$3*$K8+$M$3*$M8+$N$3*$N8)/SUM($E$3,$G$3,$K$3,$M$3:$N$3) -> 104.20355 | U8: =+($E$3*$E8+$G$3*$G8+$K$3*$K8+$N$3*$N8)/SUM($E$3,$G$3,$K$3,$N$3) -> 103.36376 | W8: =($E$3*$E8+SUMPRODUCT($G$3:$L$3,$G8:$L8)+$N$3*$N8)/SUM($E$3,$G$3:$L$3,$N$3) -> 105.09642 | Y8: =+B8/B7-1 -> 0.024084778 | Z8: =+C8/C7-1 -> 0.034883721 | AA8: =+D8/D7-1 -> 0.015165877 | AB8: =+E8/E7-1 -> 0.04825462 | AC8: =+F8/F7-1 -> 0.022140221 | AD8: =+G8/G7-1 -> 0.0088932806 | AE8: =+H8/H7-1 -> 0.019102197 | AF8: =+I8/I7-1 -> 0.010628019 | ... AT8: =+W8/W7-1 -> 0.022672833 | BS8: =+A8 -> 42795 | BT8: =(C8-C7)/$B7*C$3 -> 0.0081294798 | BU8: =(D8-D7)/$B7*D$3 -> 0.00050404624 | BV8: =(E8-E7)/$B7*E$3 -> 0.0038442197 | BW8: =(F8-F7)/$B7*F$3 -> 0.0024184971 | BX8: =(G8-G7)/$B7*G$3 -> 0.00054364162 | BY8: =(H8-H7)/$B7*H$3 -> 0.0016955684 | BZ8: =(I8-I7)/$B7*I$3 -> 0.0012282274 | CA8: =(J8-J7)/$B7*J$3 -> 0.00073092486 | ... CE8: =(N8-N7)/$B7*N$3 -> 0.00051300578 | CF8: =+SUM(BT8:CE8) -> 0.023871002
A9: =+[1]NAC!A10 -> 42826 | B9: =+[1]GBA!B10 -> 109.1 | C9: =+[1]GBA!C10 -> 109.2 | D9: =+[1]GBA!D10 -> 109.6 | E9: =+[1]GBA!E10 -> 107.2 | F9: =+[1]GBA!F10 -> 115.9 | G9: =+[1]GBA!G10 -> 103.2 | H9: =+[1]GBA!H10 -> 108.2 | I9: =+[1]GBA!I10 -> 105.1 | ... N9: =+[1]GBA!N10 -> 107.6 | O9: =+[1]GBA!R10 -> 108.5 | P9: =+[1]GBA!S10 -> 107.5 | Q9: =+[1]GBA!T10 -> 113.9 | R9: =+SUMPRODUCT($C$3:$N$3,C9:N9) -> 109.05799 | S9: =+($C$3*$C9+$D$3*$D9+$E$3*$E9+$G$3*$G9+$K$3*$K9+$M$3*$M9+$N$3*$N9)/SUM($C$3:$E$3,$G$3,$K$3,$M$3:$N$3) -> 108.02034 | T9: =+($E$3*$E9+$G$3*$G9+$K$3*$K9+$M$3*$M9+$N$3*$N9)/SUM($E$3,$G$3,$K$3,$M$3:$N$3) -> 107.12396 | U9: =+($E$3*$E9+$G$3*$G9+$K$3*$K9+$N$3*$N9)/SUM($E$3,$G$3,$K$3,$N$3) -> 106.62926 | W9: =($E$3*$E9+SUMPRODUCT($G$3:$L$3,$G9:$L9)+$N$3*$N9)/SUM($E$3,$G$3:$L$3,$N$3) -> 107.74135 | Y9: =+B9/B8-1 -> 0.026340546 | Z9: =+C9/C8-1 -> 0.02247191 | AA9: =+D9/D8-1 -> 0.02334267 | AB9: =+E9/E8-1 -> 0.049951028 | AC9: =+F9/F8-1 -> 0.046028881 | AD9: =+G9/G8-1 -> 0.010773751 | AE9: =+H9/H8-1 -> 0.014058107 | AF9: =+I9/I8-1 -> 0.0047801147 | ... AT9: =+W9/W8-1 -> 0.025166715 | BS9: =+A9 -> 42826 | BT9: =(C9-C8)/$B8*C$3 -> 0.0052921919 | BU9: =(D9-D8)/$B8*D$3 -> 0.00076904986 | BV9: =(E9-E8)/$B8*E$3 -> 0.0040732832 | BW9: =(F9-F8)/$B8*F$3 -> 0.0050184384 | BX9: =(G9-G8)/$B8*G$3 -> 0.00064882408 | BY9: =(H9-H8)/$B8*H$3 -> 0.0012417686 | BZ9: =(I9-I8)/$B8*I$3 -> 0.00054515522 | CA9: =(J9-J8)/$B8*J$3 -> 0.0019825964 | ... CE9: =(N9-N8)/$B8*N$3 -> 0.00066792098 | CF9: =+SUM(BT9:CE9) -> 0.026157197
A10: =+[1]NAC!A11 -> 42856 | B10: =+[1]GBA!B11 -> 110.5 | C10: =+[1]GBA!C11 -> 110.4 | D10: =+[1]GBA!D11 -> 111.6 | E10: =+[1]GBA!E11 -> 107.9 | F10: =+[1]GBA!F11 -> 118 | G10: =+[1]GBA!G11 -> 106.3 | H10: =+[1]GBA!H11 -> 109.8 | I10: =+[1]GBA!I11 -> 106.2 | ... N10: =+[1]GBA!N11 -> 109.1 | O10: =+[1]GBA!R11 -> 108 | P10: =+[1]GBA!S11 -> 109.2 | Q10: =+[1]GBA!T11 -> 115.2 | R10: =+SUMPRODUCT($C$3:$N$3,C10:N10) -> 110.46333 | S10: =+($C$3*$C10+$D$3*$D10+$E$3*$E10+$G$3*$G10+$K$3*$K10+$M$3*$M10+$N$3*$N10)/SUM($C$3:$E$3,$G$3,$K$3,$M$3:$N$3) -> 109.36423 | T10: =+($E$3*$E10+$G$3*$G10+$K$3*$K10+$M$3*$M10+$N$3*$N10)/SUM($E$3,$G$3,$K$3,$M$3:$N$3) -> 108.50137 | U10: =+($E$3*$E10+$G$3*$G10+$K$3*$K10+$N$3*$N10)/SUM($E$3,$G$3,$K$3,$N$3) -> 108.0813 | W10: =($E$3*$E10+SUMPRODUCT($G$3:$L$3,$G10:$L10)+$N$3*$N10)/SUM($E$3,$G$3:$L$3,$N$3) -> 109.10492 | Y10: =+B10/B9-1 -> 0.012832264 | Z10: =+C10/C9-1 -> 0.010989011 | AA10: =+D10/D9-1 -> 0.018248175 | AB10: =+E10/E9-1 -> 0.0065298507 | AC10: =+F10/F9-1 -> 0.018119068 | AD10: =+G10/G9-1 -> 0.03003876 | AE10: =+H10/H9-1 -> 0.014787431 | AF10: =+I10/I9-1 -> 0.010466223 | ... AT10: =+W10/W9-1 -> 0.012655957 | BS10: =+A10 -> 42856 | BT10: =(C10-C9)/$B9*C$3 -> 0.0025781852 | BU10: =(D10-D9)/$B9*D$3 -> 0.00059945005 | BV10: =(E10-E9)/$B9*E$3 -> 0.00054472961 | BW10: =(F10-F9)/$B9*F$3 -> 0.0020133822 | BX10: =(G10-G9)/$B9*G$3 -> 0.0017815765 | BY10: =(H10-H9)/$B9*H$3 -> 0.0012905591 | BZ10: =(I10-I9)/$B9*I$3 -> 0.001168561 | CA10: =(J10-J9)/$B9*J$3 -> 0 | ... CE10: =(N10-N9)/$B9*N$3 -> 0.00048808433 | CF10: =+SUM(BT10:CE10) -> 0.01288121
A11: =+[1]NAC!A12 -> 42887 | B11: =+[1]GBA!B12 -> 112 | C11: =+[1]GBA!C12 -> 111.8 | D11: =+[1]GBA!D12 -> 112.2 | E11: =+[1]GBA!E12 -> 108.6 | F11: =+[1]GBA!F12 -> 120.9 | G11: =+[1]GBA!G12 -> 107.7 | H11: =+[1]GBA!H12 -> 111.2 | I11: =+[1]GBA!I12 -> 106.5 | ... N11: =+[1]GBA!N12 -> 110.2 | O11: =+[1]GBA!R12 -> 109.6 | P11: =+[1]GBA!S12 -> 110.9 | Q11: =+[1]GBA!T12 -> 116.4 | R11: =+SUMPRODUCT($C$3:$N$3,C11:N11) -> 111.98898 | S11: =+($C$3*$C11+$D$3*$D11+$E$3*$E11+$G$3*$G11+$K$3*$K11+$M$3*$M11+$N$3*$N11)/SUM($C$3:$E$3,$G$3,$K$3,$M$3:$N$3) -> 110.90456 | T11: =+($E$3*$E11+$G$3*$G11+$K$3*$K11+$M$3*$M11+$N$3*$N11)/SUM($E$3,$G$3,$K$3,$M$3:$N$3) -> 110.21554 | U11: =+($E$3*$E11+$G$3*$G11+$K$3*$K11+$N$3*$N11)/SUM($E$3,$G$3,$K$3,$N$3) -> 109.75937 | W11: =($E$3*$E11+SUMPRODUCT($G$3:$L$3,$G11:$L11)+$N$3*$N11)/SUM($E$3,$G$3:$L$3,$N$3) -> 110.41173 | Y11: =+B11/B10-1 -> 0.013574661 | Z11: =+C11/C10-1 -> 0.012681159 | AA11: =+D11/D10-1 -> 0.0053763441 | AB11: =+E11/E10-1 -> 0.0064874884 | AC11: =+F11/F10-1 -> 0.024576271 | AD11: =+G11/G10-1 -> 0.013170273 | AE11: =+H11/H10-1 -> 0.012750455 | AF11: =+I11/I10-1 -> 0.0028248588 | ... AT11: =+W11/W10-1 -> 0.011977544 | BS11: =+A11 -> 42887 | BT11: =(C11-C10)/$B10*C$3 -> 0.0029697738 | BU11: =(D11-D10)/$B10*D$3 -> 0.00017755656 | BV11: =(E11-E10)/$B10*E$3 -> 0.00053782805 | BW11: =(F11-F10)/$B10*F$3 -> 0.0027451584 | BX11: =(G11-G10)/$B10*G$3 -> 0.00079438914 | BY11: =(H11-H10)/$B10*H$3 -> 0.0011149321 | BZ11: =(I11-I10)/$B10*I$3 -> 0.00031466063 | CA11: =(J11-J10)/$B10*J$3 -> 0.00055945701 | ... CE11: =(N11-N10)/$B10*N$3 -> 0.00035339367 | CF11: =+SUM(BT11:CE11) -> 0.013806787
A12: =+[1]NAC!A13 -> 42917 | B12: =+[1]GBA!B13 -> 113.9 | C12: =+[1]GBA!C13 -> 113.2 | D12: =+[1]GBA!D13 -> 115.9 | E12: =+[1]GBA!E13 -> 106.6 | F12: =+[1]GBA!F13 -> 123.9 | G12: =+[1]GBA!G13 -> 110.4 | H12: =+[1]GBA!H13 -> 115 | I12: =+[1]GBA!I13 -> 108.1 | ... N12: =+[1]GBA!N13 -> 111.8 | O12: =+[1]GBA!R13 -> 110.1 | P12: =+[1]GBA!S13 -> 112.8 | Q12: =+[1]GBA!T13 -> 118.8 | R12: =+SUMPRODUCT($C$3:$N$3,C12:N12) -> 113.93651 | S12: =+($C$3*$C12+$D$3*$D12+$E$3*$E12+$G$3*$G12+$K$3*$K12+$M$3*$M12+$N$3*$N12)/SUM($C$3:$E$3,$G$3,$K$3,$M$3:$N$3) -> 112.59449 | T12: =+($E$3*$E12+$G$3*$G12+$K$3*$K12+$M$3*$M12+$N$3*$N12)/SUM($E$3,$G$3,$K$3,$M$3:$N$3) -> 111.91155 | U12: =+($E$3*$E12+$G$3*$G12+$K$3*$K12+$N$3*$N12)/SUM($E$3,$G$3,$K$3,$N$3) -> 110.991 | W12: =($E$3*$E12+SUMPRODUCT($G$3:$L$3,$G12:$L12)+$N$3*$N12)/SUM($E$3,$G$3:$L$3,$N$3) -> 112.10641 | Y12: =+B12/B11-1 -> 0.016964286 | Z12: =+C12/C11-1 -> 0.012522361 | AA12: =+D12/D11-1 -> 0.032976827 | AB12: =+E12/E11-1 -> -0.018416206 | AC12: =+F12/F11-1 -> 0.024813896 | AD12: =+G12/G11-1 -> 0.025069638 | AE12: =+H12/H11-1 -> 0.034172662 | AF12: =+I12/I11-1 -> 0.015023474 | ... AT12: =+W12/W11-1 -> 0.015348659 | BS12: =+A12 -> 42917 | BT12: =(C12-C11)/$B11*C$3 -> 0.00293 | BU12: =(D12-D11)/$B11*D$3 -> 0.0010802679 | BV12: =(E12-E11)/$B11*E$3 -> -0.0015160714 | BW12: =(F12-F11)/$B11*F$3 -> 0.0028017857 | BX12: =(G12-G11)/$B11*G$3 -> 0.0015115179 | BY12: =(H12-H11)/$B11*H$3 -> 0.0029857143 | BZ12: =(I12-I11)/$B11*I$3 -> 0.0016557143 | CA12: =(J12-J11)/$B11*J$3 -> 0.000175625 | ... CE12: =(N12-N11)/$B11*N$3 -> 0.00050714286 | CF12: =+SUM(BT12:CE12) -> 0.017388661
A13: =+[1]NAC!A14 -> 42948 | B13: =+[1]GBA!B14 -> 115.6 | C13: =+[1]GBA!C14 -> 115.7 | D13: =+[1]GBA!D14 -> 117.4 | E13: =+[1]GBA!E14 -> 105.6 | F13: =+[1]GBA!F14 -> 127.2 | G13: =+[1]GBA!G14 -> 111.5 | H13: =+[1]GBA!H14 -> 118.3 | I13: =+[1]GBA!I14 -> 109.3 | ... N13: =+[1]GBA!N14 -> 113.5 | O13: =+[1]GBA!R14 -> 111.5 | P13: =+[1]GBA!S14 -> 114.5 | Q13: =+[1]GBA!T14 -> 120.6 | R13: =+SUMPRODUCT($C$3:$N$3,C13:N13) -> 115.61803 | S13: =+($C$3*$C13+$D$3*$D13+$E$3*$E13+$G$3*$G13+$K$3*$K13+$M$3*$M13+$N$3*$N13)/SUM($C$3:$E$3,$G$3,$K$3,$M$3:$N$3) -> 113.83876 | T13: =+($E$3*$E13+$G$3*$G13+$K$3*$K13+$M$3*$M13+$N$3*$N13)/SUM($E$3,$G$3,$K$3,$M$3:$N$3) -> 112.32898 | U13: =+($E$3*$E13+$G$3*$G13+$K$3*$K13+$N$3*$N13)/SUM($E$3,$G$3,$K$3,$N$3) -> 111.16337 | W13: =($E$3*$E13+SUMPRODUCT($G$3:$L$3,$G13:$L13)+$N$3*$N13)/SUM($E$3,$G$3:$L$3,$N$3) -> 113.2468 | Y13: =+B13/B12-1 -> 0.014925373 | Z13: =+C13/C12-1 -> 0.022084806 | AA13: =+D13/D12-1 -> 0.012942192 | AB13: =+E13/E12-1 -> -0.009380863 | AC13: =+F13/F12-1 -> 0.026634383 | AD13: =+G13/G12-1 -> 0.0099637681 | AE13: =+H13/H12-1 -> 0.028695652 | AF13: =+I13/I12-1 -> 0.011100833 | ... AT13: =+W13/W12-1 -> 0.010172411 | BS13: =+A13 -> 42948 | BT13: =(C13-C12)/$B12*C$3 -> 0.0051448639 | BU13: =(D13-D12)/$B12*D$3 -> 0.00043064091 | BV13: =(E13-E12)/$B12*E$3 -> -0.00074539069 | BW13: =(F13-F12)/$B12*F$3 -> 0.0030305531 | BX13: =(G13-G12)/$B12*G$3 -> 0.00060553117 | BY13: =(H13-H12)/$B12*H$3 -> 0.0025496049 | BZ13: =(I13-I12)/$B12*I$3 -> 0.0012210711 | CA13: =(J13-J12)/$B12*J$3 -> 0.00056742757 | ... CE13: =(N13-N12)/$B12*N$3 -> 0.00052985075 | CF13: =+SUM(BT13:CE13) -> 0.014763126
A14: =+[1]NAC!A15 -> 42979 | B14: =+[1]GBA!B15 -> 118 | C14: =+[1]GBA!C15 -> 117.9 | D14: =+[1]GBA!D15 -> 118.3 | E14: =+[1]GBA!E15 -> 111.8 | F14: =+[1]GBA!F15 -> 128.2 | G14: =+[1]GBA!G15 -> 112.6 | H14: =+[1]GBA!H15 -> 121.2 | I14: =+[1]GBA!I15 -> 110.3 | ... N14: =+[1]GBA!N15 -> 115.6 | O14: =+[1]GBA!R15 -> 117.2 | P14: =+[1]GBA!S15 -> 116.5 | Q14: =+[1]GBA!T15 -> 122.5 | R14: =+SUMPRODUCT($C$3:$N$3,C14:N14) -> 117.97261 | S14: =+($C$3*$C14+$D$3*$D14+$E$3*$E14+$G$3*$G14+$K$3*$K14+$M$3*$M14+$N$3*$N14)/SUM($C$3:$E$3,$G$3,$K$3,$M$3:$N$3) -> 116.45674 | T14: =+($E$3*$E14+$G$3*$G14+$K$3*$K14+$M$3*$M14+$N$3*$N14)/SUM($E$3,$G$3,$K$3,$M$3:$N$3) -> 115.36804 | U14: =+($E$3*$E14+$G$3*$G14+$K$3*$K14+$N$3*$N14)/SUM($E$3,$G$3,$K$3,$N$3) -> 114.89189 | W14: =($E$3*$E14+SUMPRODUCT($G$3:$L$3,$G14:$L14)+$N$3*$N14)/SUM($E$3,$G$3:$L$3,$N$3) -> 116.23412 | Y14: =+B14/B13-1 -> 0.020761246 | Z14: =+C14/C13-1 -> 0.019014693 | AA14: =+D14/D13-1 -> 0.0076660988 | AB14: =+E14/E13-1 -> 0.058712121 | AC14: =+F14/F13-1 -> 0.0078616352 | AD14: =+G14/G13-1 -> 0.0098654709 | AE14: =+H14/H13-1 -> 0.024513948 | AF14: =+I14/I13-1 -> 0.0091491308 | ... AT14: =+W14/W13-1 -> 0.026378887 | BS14: =+A14 -> 42979 | BT14: =(C14-C13)/$B13*C$3 -> 0.0044608997 | BU14: =(D14-D13)/$B13*D$3 -> 0.00025458478 | BV14: =(E14-E13)/$B13*E$3 -> 0.0045534602 | BW14: =(F14-F13)/$B13*F$3 -> 0.00090484429 | BX14: =(G14-G13)/$B13*G$3 -> 0.0005966263 | BY14: =(H14-H13)/$B13*H$3 -> 0.0022076125 | BZ14: =(I14-I13)/$B13*I$3 -> 0.0010025952 | CA14: =(J14-J13)/$B13*J$3 -> 0.00026738754 | ... CE14: =(N14-N13)/$B13*N$3 -> 0.00064489619 | CF14: =+SUM(BT14:CE14) -> 0.020368339
A15: =+[1]NAC!A16 -> 43009 | B15: =+[1]GBA!B16 -> 119.5 | C15: =+[1]GBA!C16 -> 119.7 | D15: =+[1]GBA!D16 -> 122.1 | E15: =+[1]GBA!E16 -> 113.6 | F15: =+[1]GBA!F16 -> 128.9 | G15: =+[1]GBA!G16 -> 113.4 | H15: =+[1]GBA!H16 -> 122.1 | I15: =+[1]GBA!I16 -> 111.2 | ... N15: =+[1]GBA!N16 -> 117.3 | O15: =+[1]GBA!R16 -> 119.8 | P15: =+[1]GBA!S16 -> 117.9 | Q15: =+[1]GBA!T16 -> 124.1 | R15: =+SUMPRODUCT($C$3:$N$3,C15:N15) -> 119.49921 | S15: =+($C$3*$C15+$D$3*$D15+$E$3*$E15+$G$3*$G15+$K$3*$K15+$M$3*$M15+$N$3*$N15)/SUM($C$3:$E$3,$G$3,$K$3,$M$3:$N$3) -> 118.14826 | T15: =+($E$3*$E15+$G$3*$G15+$K$3*$K15+$M$3*$M15+$N$3*$N15)/SUM($E$3,$G$3,$K$3,$M$3:$N$3) -> 116.80178 | U15: =+($E$3*$E15+$G$3*$G15+$K$3*$K15+$N$3*$N15)/SUM($E$3,$G$3,$K$3,$N$3) -> 116.08743 | W15: =($E$3*$E15+SUMPRODUCT($G$3:$L$3,$G15:$L15)+$N$3*$N15)/SUM($E$3,$G$3:$L$3,$N$3) -> 117.56207 | Y15: =+B15/B14-1 -> 0.012711864 | Z15: =+C15/C14-1 -> 0.015267176 | AA15: =+D15/D14-1 -> 0.032121724 | AB15: =+E15/E14-1 -> 0.016100179 | AC15: =+F15/F14-1 -> 0.0054602184 | AD15: =+G15/G14-1 -> 0.0071047957 | AE15: =+H15/H14-1 -> 0.0074257426 | AF15: =+I15/I14-1 -> 0.0081595648 | ... AT15: =+W15/W14-1 -> 0.011424766 | BS15: =+A15 -> 43009 | BT15: =(C15-C14)/$B14*C$3 -> 0.0035755932 | BU15: =(D15-D14)/$B14*D$3 -> 0.0010530508 | BV15: =(E15-E14)/$B14*E$3 -> 0.0012950847 | BW15: =(F15-F14)/$B14*F$3 -> 0.00062050847 | BX15: =(G15-G14)/$B14*G$3 -> 0.00042508475 | BY15: =(H15-H14)/$B14*H$3 -> 0.00067118644 | BZ15: =(I15-I14)/$B14*I$3 -> 0.00088398305 | CA15: =(J15-J14)/$B14*J$3 -> 0.0014288136 | ... CE15: =(N15-N14)/$B14*N$3 -> 0.00051144068 | CF15: =+SUM(BT15:CE15) -> 0.012937288
A16: =+[1]NAC!A17 -> 43040 | B16: =+[1]GBA!B17 -> 120.9 | C16: =+[1]GBA!C17 -> 120.9 | D16: =+[1]GBA!D17 -> 123.4 | E16: =+[1]GBA!E17 -> 114.9 | F16: =+[1]GBA!F17 -> 130.2 | G16: =+[1]GBA!G17 -> 114.2 | H16: =+[1]GBA!H17 -> 123.6 | I16: =+[1]GBA!I17 -> 114.1 | ... N16: =+[1]GBA!N17 -> 118.7 | O16: =+[1]GBA!R17 -> 121 | P16: =+[1]GBA!S17 -> 119.4 | Q16: =+[1]GBA!T17 -> 125.2 | R16: =+SUMPRODUCT($C$3:$N$3,C16:N16) -> 120.89635 | S16: =+($C$3*$C16+$D$3*$D16+$E$3*$E16+$G$3*$G16+$K$3*$K16+$M$3*$M16+$N$3*$N16)/SUM($C$3:$E$3,$G$3,$K$3,$M$3:$N$3) -> 119.3458 | T16: =+($E$3*$E16+$G$3*$G16+$K$3*$K16+$M$3*$M16+$N$3*$N16)/SUM($E$3,$G$3,$K$3,$M$3:$N$3) -> 117.98858 | U16: =+($E$3*$E16+$G$3*$G16+$K$3*$K16+$N$3*$N16)/SUM($E$3,$G$3,$K$3,$N$3) -> 116.93217 | W16: =($E$3*$E16+SUMPRODUCT($G$3:$L$3,$G16:$L16)+$N$3*$N16)/SUM($E$3,$G$3:$L$3,$N$3) -> 118.94805 | Y16: =+B16/B15-1 -> 0.011715481 | Z16: =+C16/C15-1 -> 0.010025063 | AA16: =+D16/D15-1 -> 0.010647011 | AB16: =+E16/E15-1 -> 0.011443662 | AC16: =+F16/F15-1 -> 0.010085337 | AD16: =+G16/G15-1 -> 0.0070546737 | AE16: =+H16/H15-1 -> 0.012285012 | AF16: =+I16/I15-1 -> 0.026079137 | ... AT16: =+W16/W15-1 -> 0.01178933 | BS16: =+A16 -> 43040 | BT16: =(C16-C15)/$B15*C$3 -> 0.0023538075 | BU16: =(D16-D15)/$B15*D$3 -> 0.00035573222 | BV16: =(E16-E15)/$B15*E$3 -> 0.00092359833 | BW16: =(F16-F15)/$B15*F$3 -> 0.0011379079 | BX16: =(G16-G15)/$B15*G$3 -> 0.00041974895 | BY16: =(H16-H15)/$B15*H$3 -> 0.0011046025 | BZ16: =(I16-I15)/$B15*I$3 -> 0.002812636 | CA16: =(J16-J15)/$B15*J$3 -> 0.00016460251 | ... CE16: =(N16-N15)/$B15*N$3 -> 0.00041589958 | CF16: =+SUM(BT16:CE16) -> 0.011691548
A17: =+[1]NAC!A18 -> 43070 | B17: =+[1]GBA!B18 -> 125 | C17: =+[1]GBA!C18 -> 121.6 | D17: =+[1]GBA!D18 -> 124.1 | E17: =+[1]GBA!E18 -> 115.7 | F17: =+[1]GBA!F18 -> 154.7 | G17: =+[1]GBA!G18 -> 117.7 | H17: =+[1]GBA!H18 -> 127.2 | I17: =+[1]GBA!I18 -> 117.5 | ... N17: =+[1]GBA!N18 -> 119.7 | O17: =+[1]GBA!R18 -> 121.2 | P17: =+[1]GBA!S18 -> 121.8 | Q17: =+[1]GBA!T18 -> 136.4 | R17: =+SUMPRODUCT($C$3:$N$3,C17:N17) -> 125.05919 | S17: =+($C$3*$C17+$D$3*$D17+$E$3*$E17+$G$3*$G17+$K$3*$K17+$M$3*$M17+$N$3*$N17)/SUM($C$3:$E$3,$G$3,$K$3,$M$3:$N$3) -> 120.62186 | T17: =+($E$3*$E17+$G$3*$G17+$K$3*$K17+$M$3*$M17+$N$3*$N17)/SUM($E$3,$G$3,$K$3,$M$3:$N$3) -> 119.68492 | U17: =+($E$3*$E17+$G$3*$G17+$K$3*$K17+$N$3*$N17)/SUM($E$3,$G$3,$K$3,$N$3) -> 118.41665 | W17: =($E$3*$E17+SUMPRODUCT($G$3:$L$3,$G17:$L17)+$N$3*$N17)/SUM($E$3,$G$3:$L$3,$N$3) -> 121.2075 | Y17: =+B17/B16-1 -> 0.033912324 | Z17: =+C17/C16-1 -> 0.005789909 | AA17: =+D17/D16-1 -> 0.0056726094 | AB17: =+E17/E16-1 -> 0.0069625762 | AC17: =+F17/F16-1 -> 0.18817204 | AD17: =+G17/G16-1 -> 0.030647986 | AE17: =+H17/H16-1 -> 0.029126214 | AF17: =+I17/I16-1 -> 0.029798422 | ... AT17: =+W17/W16-1 -> 0.018995299 | AV17: =+B17/B5-1 -> 0.25 | AW17: =+C17/C5-1 -> 0.216 | AX17: =+D17/D5-1 -> 0.241 | AY17: =+E17/E5-1 -> 0.157 | AZ17: =+F17/F5-1 -> 0.547 | BA17: =+G17/G5-1 -> 0.177 | BB17: =+H17/H5-1 -> 0.272 | BC17: =+I17/I5-1 -> 0.175 | ... BQ17: =+W17/W5-1 -> 0.21207501 | BS17: =+A17 -> 43070 | BT17: =(C17-C16)/$B16*C$3 -> 0.0013571547 | BU17: =(D17-D16)/$B16*D$3 -> 0.00018933002 | BV17: =(E17-E16)/$B16*E$3 -> 0.0005617866 | BW17: =(F17-F16)/$B16*F$3 -> 0.021196857 | BX17: =(G17-G16)/$B16*G$3 -> 0.0018151365 | BY17: =(H17-H16)/$B16*H$3 -> 0.0026203474 | BZ17: =(I17-I16)/$B16*I$3 -> 0.0032593879 | CA17: =(J17-J16)/$B16*J$3 -> 0.00069727047 | ... CE17: =(N17-N16)/$B16*N$3 -> 0.0002936311 | CF17: =+SUM(BT17:CE17) -> 0.034432093
A18: =+[1]NAC!A19 -> 43101 | B18: =+[1]GBA!B19 -> 127 | C18: =+[1]GBA!C19 -> 124.7 | D18: =+[1]GBA!D19 -> 126.7 | E18: =+[1]GBA!E19 -> 113.6 | F18: =+[1]GBA!F19 -> 152.3 | G18: =+[1]GBA!G19 -> 119 | H18: =+[1]GBA!H19 -> 129.5 | I18: =+[1]GBA!I19 -> 120 | ... N18: =+[1]GBA!N19 -> 123.6 | O18: =+[1]GBA!R19 -> 125.2 | P18: =+[1]GBA!S19 -> 123.5 | Q18: =+[1]GBA!T19 -> 138.1 | R18: =+SUMPRODUCT($C$3:$N$3,C18:N18) -> 127.0033 | S18: =+($C$3*$C18+$D$3*$D18+$E$3*$E18+$G$3*$G18+$K$3*$K18+$M$3*$M18+$N$3*$N18)/SUM($C$3:$E$3,$G$3,$K$3,$M$3:$N$3) -> 123.19089 | T18: =+($E$3*$E18+$G$3*$G18+$K$3*$K18+$M$3*$M18+$N$3*$N18)/SUM($E$3,$G$3,$K$3,$M$3:$N$3) -> 121.91123 | U18: =+($E$3*$E18+$G$3*$G18+$K$3*$K18+$N$3*$N18)/SUM($E$3,$G$3,$K$3,$N$3) -> 119.93892 | W18: =($E$3*$E18+SUMPRODUCT($G$3:$L$3,$G18:$L18)+$N$3*$N18)/SUM($E$3,$G$3:$L$3,$N$3) -> 123.05541 | Y18: =+B18/B17-1 -> 0.016 | Z18: =+C18/C17-1 -> 0.025493421 | AA18: =+D18/D17-1 -> 0.020950846 | AB18: =+E18/E17-1 -> -0.018150389 | AC18: =+F18/F17-1 -> -0.015513898 | AD18: =+G18/G17-1 -> 0.01104503 | AE18: =+H18/H17-1 -> 0.018081761 | AF18: =+I18/I17-1 -> 0.021276596 | ... AT18: =+W18/W17-1 -> 0.015245864 | AV18: =+B18/B6-1 -> 0.25370188 | AW18: =+C18/C6-1 -> 0.23099704 | AX18: =+D18/D6-1 -> 0.26069652 | AY18: =+E18/E6-1 -> 0.16036772 | AZ18: =+F18/F6-1 -> 0.523 | BA18: =+G18/G6-1 -> 0.17938553 | BB18: =+H18/H6-1 -> 0.27712032 | BC18: =+I18/I6-1 -> 0.17878193 | ... BQ18: =+W18/W6-1 -> 0.21547214 | BS18: =+A18 -> 43101 | BT18: =(C18-C17)/$B17*C$3 -> 0.00581312 | BU18: =(D18-D17)/$B17*D$3 -> 0.00068016 | BV18: =(E18-E17)/$B17*E$3 -> -0.00142632 | BW18: =(F18-F17)/$B17*F$3 -> -0.00200832 | BX18: =(G18-G17)/$B17*G$3 -> 0.00065208 | BY18: =(H18-H17)/$B17*H$3 -> 0.0016192 | BZ18: =(I18-I17)/$B17*I$3 -> 0.002318 | CA18: =(J18-J17)/$B17*J$3 -> 0.000562 | ... CE18: =(N18-N17)/$B17*N$3 -> 0.0011076 | CF18: =+SUM(BT18:CE18) -> 0.01555288
A19: =+[1]NAC!A20 -> 43132 | B19: =+[1]GBA!B20 -> 130.3 | C19: =+[1]GBA!C20 -> 127.8 | D19: =+[1]GBA!D20 -> 128.9 | E19: =+[1]GBA!E20 -> 113 | F19: =+[1]GBA!F20 -> 159.8 | G19: =+[1]GBA!G20 -> 121.1 | H19: =+[1]GBA!H20 -> 133.1 | I19: =+[1]GBA!I20 -> 125.4 | ... N19: =+[1]GBA!N20 -> 125.4 | O19: =+[1]GBA!R20 -> 124 | P19: =+[1]GBA!S20 -> 126.2 | Q19: =+[1]GBA!T20 -> 145.1 | R19: =+SUMPRODUCT($C$3:$N$3,C19:N19) -> 130.30526 | S19: =+($C$3*$C19+$D$3*$D19+$E$3*$E19+$G$3*$G19+$K$3*$K19+$M$3*$M19+$N$3*$N19)/SUM($C$3:$E$3,$G$3,$K$3,$M$3:$N$3) -> 125.12135 | T19: =+($E$3*$E19+$G$3*$G19+$K$3*$K19+$M$3*$M19+$N$3*$N19)/SUM($E$3,$G$3,$K$3,$M$3:$N$3) -> 123.06881 | U19: =+($E$3*$E19+$G$3*$G19+$K$3*$K19+$N$3*$N19)/SUM($E$3,$G$3,$K$3,$N$3) -> 120.61595 | W19: =($E$3*$E19+SUMPRODUCT($G$3:$L$3,$G19:$L19)+$N$3*$N19)/SUM($E$3,$G$3:$L$3,$N$3) -> 125.88204 | Y19: =+B19/B18-1 -> 0.025984252 | Z19: =+C19/C18-1 -> 0.024859663 | AA19: =+D19/D18-1 -> 0.017363852 | AB19: =+E19/E18-1 -> -0.0052816901 | AC19: =+F19/F18-1 -> 0.049244911 | AD19: =+G19/G18-1 -> 0.017647059 | AE19: =+H19/H18-1 -> 0.027799228 | AF19: =+I19/I18-1 -> 0.045 | ... AT19: =+W19/W18-1 -> 0.022970306 | AV19: =+B19/B7-1 -> 0.25529865 | AW19: =+C19/C7-1 -> 0.23837209 | AX19: =+D19/D7-1 -> 0.22180095 | AY19: =+E19/E7-1 -> 0.16016427 | AZ19: =+F19/F7-1 -> 0.47416974 | BA19: =+G19/G7-1 -> 0.19664032 | BB19: =+H19/H7-1 -> 0.27125119 | BC19: =+I19/I7-1 -> 0.2115942 | ... BQ19: =+W19/W7-1 -> 0.22493358 | BS19: =+A19 -> 43132 | BT19: =(C19-C18)/$B18*C$3 -> 0.0057215748 | BU19: =(D19-D18)/$B18*D$3 -> 0.00056645669 | BV19: =(E19-E18)/$B18*E$3 -> -0.00040110236 | BW19: =(F19-F18)/$B18*F$3 -> 0.0061771654 | BX19: =(G19-G18)/$B18*G$3 -> 0.0010367717 | BY19: =(H19-H18)/$B18*H$3 -> 0.0024944882 | BZ19: =(I19-I18)/$B18*I$3 -> 0.0049280315 | CA19: =(J19-J18)/$B18*J$3 -> 0.0023232283 | ... CE19: =(N19-N18)/$B18*N$3 -> 0.00050314961 | CF19: =+SUM(BT19:CE19) -> 0.025999685
A20: =+[1]NAC!A21 -> 43160 | B20: =+[1]GBA!B21 -> 133.5 | C20: =+[1]GBA!C21 -> 130.3 | D20: =+[1]GBA!D21 -> 129.7 | E20: =+[1]GBA!E21 -> 120.7 | F20: =+[1]GBA!F21 -> 161.4 | G20: =+[1]GBA!G21 -> 127 | H20: =+[1]GBA!H21 -> 134.4 | I20: =+[1]GBA!I21 -> 127.1 | ... N20: =+[1]GBA!N21 -> 128.4 | O20: =+[1]GBA!R21 -> 127.3 | P20: =+[1]GBA!S21 -> 129.3 | Q20: =+[1]GBA!T21 -> 148.5 | R20: =+SUMPRODUCT($C$3:$N$3,C20:N20) -> 133.512 | S20: =+($C$3*$C20+$D$3*$D20+$E$3*$E20+$G$3*$G20+$K$3*$K20+$M$3*$M20+$N$3*$N20)/SUM($C$3:$E$3,$G$3,$K$3,$M$3:$N$3) -> 128.35783 | T20: =+($E$3*$E20+$G$3*$G20+$K$3*$K20+$M$3*$M20+$N$3*$N20)/SUM($E$3,$G$3,$K$3,$M$3:$N$3) -> 126.99446 | U20: =+($E$3*$E20+$G$3*$G20+$K$3*$K20+$N$3*$N20)/SUM($E$3,$G$3,$K$3,$N$3) -> 125.43574 | W20: =($E$3*$E20+SUMPRODUCT($G$3:$L$3,$G20:$L20)+$N$3*$N20)/SUM($E$3,$G$3:$L$3,$N$3) -> 130.17536 | Y20: =+B20/B19-1 -> 0.024558711 | Z20: =+C20/C19-1 -> 0.019561815 | AA20: =+D20/D19-1 -> 0.0062063615 | AB20: =+E20/E19-1 -> 0.068141593 | AC20: =+F20/F19-1 -> 0.010012516 | AD20: =+G20/G19-1 -> 0.048720066 | AE20: =+H20/H19-1 -> 0.0097670924 | AF20: =+I20/I19-1 -> 0.013556619 | ... AT20: =+W20/W19-1 -> 0.034105944 | AV20: =+B20/B8-1 -> 0.25587959 | AW20: =+C20/C8-1 -> 0.22003745 | AX20: =+D20/D8-1 -> 0.21101774 | AY20: =+E20/E8-1 -> 0.18217434 | AZ20: =+F20/F8-1 -> 0.4566787 | BA20: =+G20/G8-1 -> 0.24387855 | BB20: =+H20/H8-1 -> 0.25960637 | BC20: =+I20/I8-1 -> 0.21510516 | ... BQ20: =+W20/W8-1 -> 0.2386279 | BS20: =+A20 -> 43160 | BT20: =(C20-C19)/$B19*C$3 -> 0.0044973139 | BU20: =(D20-D19)/$B19*D$3 -> 0.00020076746 | BV20: =(E20-E19)/$B19*E$3 -> 0.0050171144 | BW20: =(F20-F19)/$B19*F$3 -> 0.0012844206 | BX20: =(G20-G19)/$B19*G$3 -> 0.0028390637 | BY20: =(H20-H19)/$B19*H$3 -> 0.00087797391 | BZ20: =(I20-I19)/$B19*I$3 -> 0.0015121259 | CA20: =(J20-J19)/$B19*J$3 -> 0.00071166539 | ... CE20: =(N20-N19)/$B19*N$3 -> 0.00081734459 | CF20: =+SUM(BT20:CE20) -> 0.024610437
A21: =+[1]NAC!A22 -> 43191 | B21: =+[1]GBA!B22 -> 136.9 | C21: =+[1]GBA!C22 -> 131.3 | D21: =+[1]GBA!D22 -> 131.2 | E21: =+[1]GBA!E22 -> 124.6 | F21: =+[1]GBA!F22 -> 172.2 | G21: =+[1]GBA!G22 -> 128.4 | H21: =+[1]GBA!H22 -> 136.4 | I21: =+[1]GBA!I22 -> 133.8 | ... N21: =+[1]GBA!N22 -> 130.2 | O21: =+[1]GBA!R22 -> 126.8 | P21: =+[1]GBA!S22 -> 132.1 | Q21: =+[1]GBA!T22 -> 155.8 | R21: =+SUMPRODUCT($C$3:$N$3,C21:N21) -> 136.94178 | S21: =+($C$3*$C21+$D$3*$D21+$E$3*$E21+$G$3*$G21+$K$3*$K21+$M$3*$M21+$N$3*$N21)/SUM($C$3:$E$3,$G$3,$K$3,$M$3:$N$3) -> 130.39428 | T21: =+($E$3*$E21+$G$3*$G21+$K$3*$K21+$M$3*$M21+$N$3*$N21)/SUM($E$3,$G$3,$K$3,$M$3:$N$3) -> 129.74242 | U21: =+($E$3*$E21+$G$3*$G21+$K$3*$K21+$N$3*$N21)/SUM($E$3,$G$3,$K$3,$N$3) -> 128.11975 | W21: =($E$3*$E21+SUMPRODUCT($G$3:$L$3,$G21:$L21)+$N$3*$N21)/SUM($E$3,$G$3:$L$3,$N$3) -> 133.44962 | Y21: =+B21/B20-1 -> 0.025468165 | Z21: =+C21/C20-1 -> 0.0076745971 | AA21: =+D21/D20-1 -> 0.01156515 | AB21: =+E21/E20-1 -> 0.032311516 | AC21: =+F21/F20-1 -> 0.066914498 | AD21: =+G21/G20-1 -> 0.011023622 | AE21: =+H21/H20-1 -> 0.014880952 | AF21: =+I21/I20-1 -> 0.052714398 | ... AT21: =+W21/W20-1 -> 0.025152719 | AV21: =+B21/B9-1 -> 0.2548121 | AW21: =+C21/C9-1 -> 0.20238095 | AX21: =+D21/D9-1 -> 0.19708029 | AY21: =+E21/E9-1 -> 0.16231343 | AZ21: =+F21/F9-1 -> 0.48576359 | BA21: =+G21/G9-1 -> 0.24418605 | BB21: =+H21/H9-1 -> 0.26062847 | BC21: =+I21/I9-1 -> 0.27307326 | ... BQ21: =+W21/W9-1 -> 0.23861099 | BS21: =+A21 -> 43191 | BT21: =(C21-C20)/$B20*C$3 -> 0.0017558052 | BU21: =(D21-D20)/$B20*D$3 -> 0.00036741573 | BV21: =(E21-E20)/$B20*E$3 -> 0.0024802247 | BW21: =(F21-F20)/$B20*F$3 -> 0.0084620225 | BX21: =(G21-G20)/$B20*G$3 -> 0.00065752809 | BY21: =(H21-H20)/$B20*H$3 -> 0.0013183521 | BZ21: =(I21-I20)/$B20*I$3 -> 0.0058167041 | CA21: =(J21-J20)/$B20*J$3 -> 0.00023153558 | ... CE21: =(N21-N20)/$B20*N$3 -> 0.00047865169 | CF21: =+SUM(BT21:CE21) -> 0.025691236
A22: =+[1]NAC!A23 -> 43221 | B22: =+[1]GBA!B23 -> 139.6 | C22: =+[1]GBA!C23 -> 136.2 | D22: =+[1]GBA!D23 -> 133 | E22: =+[1]GBA!E23 -> 126.7 | F22: =+[1]GBA!F23 -> 170 | G22: =+[1]GBA!G23 -> 131.4 | H22: =+[1]GBA!H23 -> 139.5 | I22: =+[1]GBA!I23 -> 136.4 | ... N22: =+[1]GBA!N23 -> 132.2 | O22: =+[1]GBA!R23 -> 130.8 | P22: =+[1]GBA!S23 -> 135.4 | Q22: =+[1]GBA!T23 -> 155.7 | R22: =+SUMPRODUCT($C$3:$N$3,C22:N22) -> 139.58445 | S22: =+($C$3*$C22+$D$3*$D22+$E$3*$E22+$G$3*$G22+$K$3*$K22+$M$3*$M22+$N$3*$N22)/SUM($C$3:$E$3,$G$3,$K$3,$M$3:$N$3) -> 133.76578 | T22: =+($E$3*$E22+$G$3*$G22+$K$3*$K22+$M$3*$M22+$N$3*$N22)/SUM($E$3,$G$3,$K$3,$M$3:$N$3) -> 132.27564 | U22: =+($E$3*$E22+$G$3*$G22+$K$3*$K22+$N$3*$N22)/SUM($E$3,$G$3,$K$3,$N$3) -> 130.54075 | W22: =($E$3*$E22+SUMPRODUCT($G$3:$L$3,$G22:$L22)+$N$3*$N22)/SUM($E$3,$G$3:$L$3,$N$3) -> 136.06907 | Y22: =+B22/B21-1 -> 0.019722425 | Z22: =+C22/C21-1 -> 0.037319117 | AA22: =+D22/D21-1 -> 0.013719512 | AB22: =+E22/E21-1 -> 0.016853933 | AC22: =+F22/F21-1 -> -0.012775842 | AD22: =+G22/G21-1 -> 0.023364486 | AE22: =+H22/H21-1 -> 0.022727273 | AF22: =+I22/I21-1 -> 0.019431988 | ... AT22: =+W22/W21-1 -> 0.019628725 | AV22: =+B22/B10-1 -> 0.26334842 | AW22: =+C22/C10-1 -> 0.23369565 | AX22: =+D22/D10-1 -> 0.19175627 | AY22: =+E22/E10-1 -> 0.1742354 | AZ22: =+F22/F10-1 -> 0.44067797 | BA22: =+G22/G10-1 -> 0.23612418 | BB22: =+H22/H10-1 -> 0.2704918 | BC22: =+I22/I10-1 -> 0.28436911 | ... BQ22: =+W22/W10-1 -> 0.2471396 | BS22: =+A22 -> 43221 | BT22: =(C22-C21)/$B21*C$3 -> 0.0083897736 | BU22: =(D22-D21)/$B21*D$3 -> 0.00042994887 | BV22: =(E22-E21)/$B21*E$3 -> 0.0013023375 | BW22: =(F22-F21)/$B21*F$3 -> -0.001680935 | BX22: =(G22-G21)/$B21*G$3 -> 0.0013739956 | BY22: =(H22-H21)/$B21*H$3 -> 0.0019926954 | BZ22: =(I22-I21)/$B21*I$3 -> 0.0022011687 | CA22: =(J22-J21)/$B21*J$3 -> 0.0011084003 | ... CE22: =(N22-N21)/$B21*N$3 -> 0.00051862673 | CF22: =+SUM(BT22:CE22) -> 0.019303652
A23: =+[1]NAC!A24 -> 43252 | B23: =+[1]GBA!B24 -> 145.1 | C23: =+[1]GBA!C24 -> 142.6 | D23: =+[1]GBA!D24 -> 134.5 | E23: =+[1]GBA!E24 -> 129.4 | F23: =+[1]GBA!F24 -> 176.6 | G23: =+[1]GBA!G24 -> 136.5 | H23: =+[1]GBA!H24 -> 146.2 | I23: =+[1]GBA!I24 -> 145.3 | ... N23: =+[1]GBA!N24 -> 135.9 | O23: =+[1]GBA!R24 -> 135 | P23: =+[1]GBA!S24 -> 141.1 | Q23: =+[1]GBA!T24 -> 161.2 | R23: =+SUMPRODUCT($C$3:$N$3,C23:N23) -> 145.04938 | S23: =+($C$3*$C23+$D$3*$D23+$E$3*$E23+$G$3*$G23+$K$3*$K23+$M$3*$M23+$N$3*$N23)/SUM($C$3:$E$3,$G$3,$K$3,$M$3:$N$3) -> 138.61852 | T23: =+($E$3*$E23+$G$3*$G23+$K$3*$K23+$M$3*$M23+$N$3*$N23)/SUM($E$3,$G$3,$K$3,$M$3:$N$3) -> 136.4372 | U23: =+($E$3*$E23+$G$3*$G23+$K$3*$K23+$N$3*$N23)/SUM($E$3,$G$3,$K$3,$N$3) -> 134.68615 | W23: =($E$3*$E23+SUMPRODUCT($G$3:$L$3,$G23:$L23)+$N$3*$N23)/SUM($E$3,$G$3:$L$3,$N$3) -> 141.39717 | Y23: =+B23/B22-1 -> 0.039398281 | Z23: =+C23/C22-1 -> 0.046989721 | AA23: =+D23/D22-1 -> 0.011278195 | AB23: =+E23/E22-1 -> 0.021310182 | AC23: =+F23/F22-1 -> 0.038823529 | AD23: =+G23/G22-1 -> 0.038812785 | AE23: =+H23/H22-1 -> 0.048028674 | AF23: =+I23/I22-1 -> 0.065249267 | ... AT23: =+W23/W22-1 -> 0.03915733 | AV23: =+B23/B11-1 -> 0.29553571 | AW23: =+C23/C11-1 -> 0.27549195 | AX23: =+D23/D11-1 -> 0.19875223 | AY23: =+E23/E11-1 -> 0.19152855 | AZ23: =+F23/F11-1 -> 0.46071133 | BA23: =+G23/G11-1 -> 0.26740947 | BB23: =+H23/H11-1 -> 0.3147482 | BC23: =+I23/I11-1 -> 0.36431925 | ... BQ23: =+W23/W11-1 -> 0.28063539 | BS23: =+A23 -> 43252 | BT23: =(C23-C22)/$B22*C$3 -> 0.010746132 | BU23: =(D23-D22)/$B22*D$3 -> 0.00035136103 | BV23: =(E23-E22)/$B22*E$3 -> 0.0016420487 | BW23: =(F23-F22)/$B22*F$3 -> 0.0049452722 | BX23: =(G23-G22)/$B22*G$3 -> 0.002290616 | BY23: =(H23-H22)/$B22*H$3 -> 0.0042234957 | BZ23: =(I23-I22)/$B22*I$3 -> 0.0073890401 | CA23: =(J23-J22)/$B22*J$3 -> 8.0515759e-05 | ... CE23: =(N23-N22)/$B22*N$3 -> 0.00094090258 | CF23: =+SUM(BT23:CE23) -> 0.039147063
A24: =+[1]NAC!A25 -> 43282 | B24: =+[1]GBA!B25 -> 149.1 | C24: =+[1]GBA!C25 -> 148.3 | D24: =+[1]GBA!D25 -> 138 | E24: =+[1]GBA!E25 -> 128.6 | F24: =+[1]GBA!F25 -> 176.6 | G24: =+[1]GBA!G25 -> 142.4 | H24: =+[1]GBA!H25 -> 149.8 | I24: =+[1]GBA!I25 -> 151.6 | ... N24: =+[1]GBA!N25 -> 141.8 | O24: =+[1]GBA!R25 -> 140.5 | P24: =+[1]GBA!S25 -> 145.2 | Q24: =+[1]GBA!T25 -> 164.5 | R24: =+SUMPRODUCT($C$3:$N$3,C24:N24) -> 149.12552 | S24: =+($C$3*$C24+$D$3*$D24+$E$3*$E24+$G$3*$G24+$K$3*$K24+$M$3*$M24+$N$3*$N24)/SUM($C$3:$E$3,$G$3,$K$3,$M$3:$N$3) -> 143.21364 | T24: =+($E$3*$E24+$G$3*$G24+$K$3*$K24+$M$3*$M24+$N$3*$N24)/SUM($E$3,$G$3,$K$3,$M$3:$N$3) -> 140.42273 | U24: =+($E$3*$E24+$G$3*$G24+$K$3*$K24+$N$3*$N24)/SUM($E$3,$G$3,$K$3,$N$3) -> 138.58145 | W24: =($E$3*$E24+SUMPRODUCT($G$3:$L$3,$G24:$L24)+$N$3*$N24)/SUM($E$3,$G$3:$L$3,$N$3) -> 145.57169 | Y24: =+B24/B23-1 -> 0.027567195 | Z24: =+C24/C23-1 -> 0.03997195 | AA24: =+D24/D23-1 -> 0.026022305 | AB24: =+E24/E23-1 -> -0.0061823802 | AC24: =+F24/F23-1 -> 0 | AD24: =+G24/G23-1 -> 0.043223443 | AE24: =+H24/H23-1 -> 0.024623803 | AF24: =+I24/I23-1 -> 0.043358568 | ... AT24: =+W24/W23-1 -> 0.029523323 | AV24: =+B24/B12-1 -> 0.30904302 | AW24: =+C24/C12-1 -> 0.31007067 | AX24: =+D24/D12-1 -> 0.19068162 | AY24: =+E24/E12-1 -> 0.20637899 | AZ24: =+F24/F12-1 -> 0.42534302 | BA24: =+G24/G12-1 -> 0.28985507 | BB24: =+H24/H12-1 -> 0.3026087 | BC24: =+I24/I12-1 -> 0.40240518 | ... BQ24: =+W24/W12-1 -> 0.29851356 | BS24: =+A24 -> 43282 | BT24: =(C24-C23)/$B23*C$3 -> 0.0092079945 | BU24: =(D24-D23)/$B23*D$3 -> 0.00078876637 | BV24: =(E24-E23)/$B23*E$3 -> -0.00046809097 | BW24: =(F24-F23)/$B23*F$3 -> 0 | BX24: =(G24-G23)/$B23*G$3 -> 0.0025494831 | BY24: =(H24-H23)/$B23*H$3 -> 0.0021833218 | BZ24: =(I24-I23)/$B23*I$3 -> 0.0050321847 | CA24: =(J24-J23)/$B23*J$3 -> 0.00011619573 | ... CE24: =(N24-N23)/$B23*N$3 -> 0.0014434873 | CF24: =+SUM(BT24:CE24) -> 0.028091937
A25: =+[1]NAC!A26 -> 43313 | B25: =+[1]GBA!B26 -> 155.2 | C25: =+[1]GBA!C26 -> 153.4 | D25: =+[1]GBA!D26 -> 139.5 | E25: =+[1]GBA!E26 -> 129.5 | F25: =+[1]GBA!F26 -> 191.8 | G25: =+[1]GBA!G26 -> 146.9 | H25: =+[1]GBA!H26 -> 157.3 | I25: =+[1]GBA!I26 -> 156.6 | ... N25: =+[1]GBA!N26 -> 149.6 | O25: =+[1]GBA!R26 -> 142.6 | P25: =+[1]GBA!S26 -> 149.9 | Q25: =+[1]GBA!T26 -> 176.4 | R25: =+SUMPRODUCT($C$3:$N$3,C25:N25) -> 155.15845 | S25: =+($C$3*$C25+$D$3*$D25+$E$3*$E25+$G$3*$G25+$K$3*$K25+$M$3*$M25+$N$3*$N25)/SUM($C$3:$E$3,$G$3,$K$3,$M$3:$N$3) -> 147.04632 | T25: =+($E$3*$E25+$G$3*$G25+$K$3*$K25+$M$3*$M25+$N$3*$N25)/SUM($E$3,$G$3,$K$3,$M$3:$N$3) -> 143.65234 | U25: =+($E$3*$E25+$G$3*$G25+$K$3*$K25+$N$3*$N25)/SUM($E$3,$G$3,$K$3,$N$3) -> 141.65526 | W25: =($E$3*$E25+SUMPRODUCT($G$3:$L$3,$G25:$L25)+$N$3*$N25)/SUM($E$3,$G$3:$L$3,$N$3) -> 150.97326 | Y25: =+B25/B24-1 -> 0.04091214 | Z25: =+C25/C24-1 -> 0.034389751 | AA25: =+D25/D24-1 -> 0.010869565 | AB25: =+E25/E24-1 -> 0.0069984448 | AC25: =+F25/F24-1 -> 0.086070215 | AD25: =+G25/G24-1 -> 0.031601124 | AE25: =+H25/H24-1 -> 0.050066756 | AF25: =+I25/I24-1 -> 0.03298153 | ... AT25: =+W25/W24-1 -> 0.03710596 | AV25: =+B25/B13-1 -> 0.34256055 | AW25: =+C25/C13-1 -> 0.3258427 | AX25: =+D25/D13-1 -> 0.18824532 | AY25: =+E25/E13-1 -> 0.22632576 | AZ25: =+F25/F13-1 -> 0.50786164 | BA25: =+G25/G13-1 -> 0.31748879 | BB25: =+H25/H13-1 -> 0.32967033 | BC25: =+I25/I13-1 -> 0.43275389 | ... BQ25: =+W25/W13-1 -> 0.33313495 | BS25: =+A25 -> 43313 | BT25: =(C25-C24)/$B24*C$3 -> 0.0080177062 | BU25: =(D25-D24)/$B24*D$3 -> 0.00032897384 | BV25: =(E25-E24)/$B24*E$3 -> 0.00051247485 | BW25: =(F25-F24)/$B24*F$3 -> 0.010663447 | BX25: =(G25-G24)/$B24*G$3 -> 0.0018923541 | BY25: =(H25-H24)/$B24*H$3 -> 0.0044265594 | BZ25: =(I25-I24)/$B24*I$3 -> 0.0038866533 | CA25: =(J25-J24)/$B24*J$3 -> 0.0045608317 | ... CE25: =(N25-N24)/$B24*N$3 -> 0.0018571429 | CF25: =+SUM(BT25:CE25) -> 0.040462307
A26: =+[1]NAC!A27 -> 43344 | B26: =+[1]GBA!B27 -> 165.5 | C26: =+[1]GBA!C27 -> 164.6 | D26: =+[1]GBA!D27 -> 145.6 | E26: =+[1]GBA!E27 -> 146.6 | F26: =+[1]GBA!F27 -> 193.2 | G26: =+[1]GBA!G27 -> 161.6 | H26: =+[1]GBA!H27 -> 164.1 | I26: =+[1]GBA!I27 -> 173.3 | ... N26: =+[1]GBA!N27 -> 160.8 | O26: =+[1]GBA!R27 -> 150.8 | P26: =+[1]GBA!S27 -> 161.6 | Q26: =+[1]GBA!T27 -> 183.6 | R26: =+SUMPRODUCT($C$3:$N$3,C26:N26) -> 165.50202 | S26: =+($C$3*$C26+$D$3*$D26+$E$3*$E26+$G$3*$G26+$K$3*$K26+$M$3*$M26+$N$3*$N26)/SUM($C$3:$E$3,$G$3,$K$3,$M$3:$N$3) -> 158.86601 | T26: =+($E$3*$E26+$G$3*$G26+$K$3*$K26+$M$3*$M26+$N$3*$N26)/SUM($E$3,$G$3,$K$3,$M$3:$N$3) -> 156.37968 | U26: =+($E$3*$E26+$G$3*$G26+$K$3*$K26+$N$3*$N26)/SUM($E$3,$G$3,$K$3,$N$3) -> 155.82429 | W26: =($E$3*$E26+SUMPRODUCT($G$3:$L$3,$G26:$L26)+$N$3*$N26)/SUM($E$3,$G$3:$L$3,$N$3) -> 163.21458 | Y26: =+B26/B25-1 -> 0.066365979 | Z26: =+C26/C25-1 -> 0.073011734 | AA26: =+D26/D25-1 -> 0.043727599 | AB26: =+E26/E25-1 -> 0.13204633 | AC26: =+F26/F25-1 -> 0.0072992701 | AD26: =+G26/G25-1 -> 0.10006807 | AE26: =+H26/H25-1 -> 0.043229498 | AF26: =+I26/I25-1 -> 0.10664112 | ... AT26: =+W26/W25-1 -> 0.081082672 | AV26: =+B26/B14-1 -> 0.40254237 | AW26: =+C26/C14-1 -> 0.39609839 | AX26: =+D26/D14-1 -> 0.23076923 | AY26: =+E26/E14-1 -> 0.31127013 | AZ26: =+F26/F14-1 -> 0.50702028 | BA26: =+G26/G14-1 -> 0.43516874 | BB26: =+H26/H14-1 -> 0.3539604 | BC26: =+I26/I14-1 -> 0.57116954 | ... BQ26: =+W26/W14-1 -> 0.40418818 | BS26: =+A26 -> 43344 | BT26: =(C26-C25)/$B25*C$3 -> 0.016915464 | BU26: =(D26-D25)/$B25*D$3 -> 0.0012852448 | BV26: =(E26-E25)/$B25*E$3 -> 0.009354317 | BW26: =(F26-F25)/$B25*F$3 -> 0.0009435567 | BX26: =(G26-G25)/$B25*G$3 -> 0.0059387242 | BY26: =(H26-H25)/$B25*H$3 -> 0.0038556701 | BZ26: =(I26-I25)/$B25*I$3 -> 0.012471198 | CA26: =(J26-J25)/$B25*J$3 -> 0.00045264175 | ... CE26: =(N26-N25)/$B25*N$3 -> 0.0025618557 | CF26: =+SUM(BT26:CE26) -> 0.066646714
A27: =+[1]NAC!A28 -> 43374 | B27: =+[1]GBA!B28 -> 173.9 | C27: =+[1]GBA!C28 -> 174.6 | D27: =+[1]GBA!D28 -> 149.2 | E27: =+[1]GBA!E28 -> 153.7 | F27: =+[1]GBA!F28 -> 206.9 | G27: =+[1]GBA!G28 -> 167.9 | H27: =+[1]GBA!H28 -> 173.7 | I27: =+[1]GBA!I28 -> 185.6 | ... N27: =+[1]GBA!N28 -> 170.4 | O27: =+[1]GBA!R28 -> 160.2 | P27: =+[1]GBA!S28 -> 168.5 | Q27: =+[1]GBA!T28 -> 195.9 | R27: =+SUMPRODUCT($C$3:$N$3,C27:N27) -> 173.85663 | S27: =+($C$3*$C27+$D$3*$D27+$E$3*$E27+$G$3*$G27+$K$3*$K27+$M$3*$M27+$N$3*$N27)/SUM($C$3:$E$3,$G$3,$K$3,$M$3:$N$3) -> 165.96491 | T27: =+($E$3*$E27+$G$3*$G27+$K$3*$K27+$M$3*$M27+$N$3*$N27)/SUM($E$3,$G$3,$K$3,$M$3:$N$3) -> 161.93362 | U27: =+($E$3*$E27+$G$3*$G27+$K$3*$K27+$N$3*$N27)/SUM($E$3,$G$3,$K$3,$N$3) -> 162.0319 | W27: =($E$3*$E27+SUMPRODUCT($G$3:$L$3,$G27:$L27)+$N$3*$N27)/SUM($E$3,$G$3:$L$3,$N$3) -> 170.9589 | Y27: =+B27/B26-1 -> 0.050755287 | Z27: =+C27/C26-1 -> 0.060753341 | AA27: =+D27/D26-1 -> 0.024725275 | AB27: =+E27/E26-1 -> 0.048431105 | AC27: =+F27/F26-1 -> 0.070910973 | AD27: =+G27/G26-1 -> 0.038985149 | AE27: =+H27/H26-1 -> 0.058500914 | AF27: =+I27/I26-1 -> 0.070975188 | ... AT27: =+W27/W26-1 -> 0.047448679 | AV27: =+B27/B15-1 -> 0.45523013 | AW27: =+C27/C15-1 -> 0.45864662 | AX27: =+D27/D15-1 -> 0.22194922 | AY27: =+E27/E15-1 -> 0.35299296 | AZ27: =+F27/F15-1 -> 0.60512025 | BA27: =+G27/G15-1 -> 0.48059965 | BB27: =+H27/H15-1 -> 0.42260442 | BC27: =+I27/I15-1 -> 0.66906475 | ... BQ27: =+W27/W15-1 -> 0.45420114 | BS27: =+A27 -> 43374 | BT27: =(C27-C26)/$B26*C$3 -> 0.014163142 | BU27: =(D27-D26)/$B26*D$3 -> 0.00071129909 | BV27: =(E27-E26)/$B26*E$3 -> 0.0036422356 | BW27: =(F27-F26)/$B26*F$3 -> 0.0086587311 | BX27: =(G27-G26)/$B26*G$3 -> 0.0023867674 | BY27: =(H27-H26)/$B26*H$3 -> 0.0051045317 | BZ27: =(I27-I26)/$B26*I$3 -> 0.008613716 | CA27: =(J27-J26)/$B26*J$3 -> 6.7915408e-05 | ... CE27: =(N27-N26)/$B26*N$3 -> 0.0020592145 | CF27: =+SUM(BT27:CE27) -> 0.050481027
A28: =+[1]NAC!A29 -> 43405 | B28: =+[1]GBA!B29 -> 178.9 | C28: =+[1]GBA!C29 -> 180.1 | D28: =+[1]GBA!D29 -> 156.6 | E28: =+[1]GBA!E29 -> 156.3 | F28: =+[1]GBA!F29 -> 209 | G28: =+[1]GBA!G29 -> 174 | H28: =+[1]GBA!H29 -> 179.7 | I28: =+[1]GBA!I29 -> 191.1 | ... N28: =+[1]GBA!N29 -> 176.4 | O28: =+[1]GBA!R29 -> 162.6 | P28: =+[1]GBA!S29 -> 173.8 | Q28: =+[1]GBA!T29 -> 201.1 | R28: =+SUMPRODUCT($C$3:$N$3,C28:N28) -> 178.89572 | S28: =+($C$3*$C28+$D$3*$D28+$E$3*$E28+$G$3*$G28+$K$3*$K28+$M$3*$M28+$N$3*$N28)/SUM($C$3:$E$3,$G$3,$K$3,$M$3:$N$3) -> 171.2725 | T28: =+($E$3*$E28+$G$3*$G28+$K$3*$K28+$M$3*$M28+$N$3*$N28)/SUM($E$3,$G$3,$K$3,$M$3:$N$3) -> 166.93114 | U28: =+($E$3*$E28+$G$3*$G28+$K$3*$K28+$N$3*$N28)/SUM($E$3,$G$3,$K$3,$N$3) -> 167.19662 | W28: =($E$3*$E28+SUMPRODUCT($G$3:$L$3,$G28:$L28)+$N$3*$N28)/SUM($E$3,$G$3:$L$3,$N$3) -> 176.32456 | Y28: =+B28/B27-1 -> 0.028752156 | Z28: =+C28/C27-1 -> 0.031500573 | AA28: =+D28/D27-1 -> 0.049597855 | AB28: =+E28/E27-1 -> 0.01691607 | AC28: =+F28/F27-1 -> 0.010149831 | AD28: =+G28/G27-1 -> 0.036331149 | AE28: =+H28/H27-1 -> 0.034542314 | AF28: =+I28/I27-1 -> 0.029633621 | ... AT28: =+W28/W27-1 -> 0.031385711 | AV28: =+B28/B16-1 -> 0.47973532 | AW28: =+C28/C16-1 -> 0.48966088 | AX28: =+D28/D16-1 -> 0.26904376 | AY28: =+E28/E16-1 -> 0.36031332 | AZ28: =+F28/F16-1 -> 0.60522273 | BA28: =+G28/G16-1 -> 0.52364273 | BB28: =+H28/H16-1 -> 0.4538835 | BC28: =+I28/I16-1 -> 0.67484663 | ... BQ28: =+W28/W16-1 -> 0.48236617 | BS28: =+A28 -> 43405 | BT28: =(C28-C27)/$B27*C$3 -> 0.007413456 | BU28: =(D28-D27)/$B27*D$3 -> 0.0013914894 | BV28: =(E28-E27)/$B27*E$3 -> 0.0012693502 | BW28: =(F28-F27)/$B27*F$3 -> 0.0012631397 | BX28: =(G28-G27)/$B27*G$3 -> 0.0021993675 | BY28: =(H28-H27)/$B27*H$3 -> 0.0030362277 | BZ28: =(I28-I27)/$B27*I$3 -> 0.0036656124 | CA28: =(J28-J27)/$B27*J$3 -> 0.0013734905 | ... CE28: =(N28-N27)/$B27*N$3 -> 0.0012248419 | CF28: =+SUM(BT28:CE28) -> 0.028976941
... A118: =+[1]NAC!A119 -> 46143 | B118: =+[1]GBA!B119 -> 11594.5 | C118: =+[1]GBA!C119 -> 12553.2 | D118: =+[1]GBA!D119 -> 8109.7 | E118: =+[1]GBA!E119 -> 8711.1 | F118: =+[1]GBA!F119 -> 11811.4 | G118: =+[1]GBA!G119 -> 9312.4 | H118: =+[1]GBA!H119 -> 12243.5 | I118: =+[1]GBA!I119 -> 11804.6 | ... N118: =+[1]GBA!N119 -> 11472.7 | O118: =+[1]GBA!R119 -> 9620.9 | P118: =+[1]GBA!S119 -> 11832 | Q118: =+[1]GBA!T119 -> 11785.1 | R118: =+SUMPRODUCT($C$3:$N$3,C118:N118) -> 11594.472 | S118: =+($C$3*$C118+$D$3*$D118+$E$3*$E118+$G$3*$G118+$K$3*$K118+$M$3*$M118+$N$3*$N118)/SUM($C$3:$E$3,$G$3,$K$3,$M$3:$N$3) -> 11449.083 | T118: =+($E$3*$E118+$G$3*$G118+$K$3*$K118+$M$3*$M118+$N$3*$N118)/SUM($E$3,$G$3,$K$3,$M$3:$N$3) -> 11040.433 | U118: =+($E$3*$E118+$G$3*$G118+$K$3*$K118+$N$3*$N118)/SUM($E$3,$G$3,$K$3,$N$3) -> 9740.8661 | W118: =($E$3*$E118+SUMPRODUCT($G$3:$L$3,$G118:$L118)+$N$3*$N118)/SUM($E$3,$G$3:$L$3,$N$3) -> 10809.12 | Y118: =+B118/B117-1 -> 0.022749325 | Z118: =+C118/C117-1 -> 0.028057589 | AA118: =+D118/D117-1 -> 0.010667863 | AB118: =+E118/E117-1 -> -0.0033066362 | AC118: =+F118/F117-1 -> 0.017522398 | AD118: =+G118/G117-1 -> 0.01106346 | AE118: =+H118/H117-1 -> 0.027449565 | AF118: =+I118/I117-1 -> 0.024349184 | ... AT118: =+W118/W117-1 -> 0.02225283 | AV118: =+B118/B106-1 -> 0.33644935 | AW118: =+C118/C106-1 -> 0.33463751 | AX118: =+D118/D106-1 -> 0.24360921 | AY118: =+E118/E106-1 -> 0.12690651 | AZ118: =+F118/F106-1 -> 0.43885295 | BA118: =+G118/G106-1 -> 0.25082606 | BB118: =+H118/H106-1 -> 0.29759949 | BC118: =+I118/I106-1 -> 0.4344598 | ... BQ118: =+W118/W106-1 -> 0.3139208 | BS118: =+A118 -> 46143 | BT118: =(C118-C117)/$B117*C$3 -> 0.0070837323 | BU118: =(D118-D117)/$B117*D$3 -> 0.00024691001 | BV118: =(E118-E117)/$B117*E$3 -> -0.00021643262 | BW118: =(F118-F117)/$B117*F$3 -> 0.0018767214 | BX118: =(G118-G117)/$B117*G$3 -> 0.00056358432 | BY118: =(H118-H117)/$B117*H$3 -> 0.0025391034 | BZ118: =(I118-I117)/$B117*I$3 -> 0.0028687208 | CA118: =(J118-J117)/$B117*J$3 -> 0.0010075905 | ... CE118: =(N118-N117)/$B117*N$3 -> 0.00084862304 | CF118: =+SUM(BT118:CE118) -> 0.022756801

Sheet PAM
B1: Índices | Y1: Tasas de inflación mensual | AV1: Tasas de inflación interanual | BS1: Incidencia mensual | CH1: Incidencia Feb 21 - Jun 24
R2: =+SUM(C3:N3) -> 1 | S2: =+SUM($C$3:$E$3,$G$3,$K$3,$M$3:$N$3) -> 0.6829 | T2: =+SUM($E$3,$G$3,$K$3,$M$3:$N$3) -> 0.3584 | U2: =+SUM($E$3,$G$3,$K$3,$N$3) -> 0.2774 | W2: =+SUM(E3,G3:L3,N3) -> 0.5078 | AT2: =+SUM(AB3,AD3:AI3,AK3) -> 0.5078 | BL2: =+SUM(AW3:BH3) -> 1 | BQ2: =+SUM(AY3,BA3:BF3,BH3) -> 0.5078
C3: =+[1]PAM!C3 -> 0.2865 | D3: =+[1]PAM!D3 -> 0.038 | E3: =+[1]PAM!E3 -> 0.1043 | F3: =+[1]PAM!F3 -> 0.0867 | G3: =+[1]PAM!G3 -> 0.0634 | H3: =+[1]PAM!H3 -> 0.0816 | I3: =+[1]PAM!I3 -> 0.1041 | J3: =+[1]PAM!J3 -> 0.0286 | ... N3: =+[1]PAM!N3 -> 0.0358 | R3: headline | V3: no food & energy | W3: no food & energy & shelter | Z3: =+C3 -> 0.2865 | AA3: =+D3 -> 0.038 | AB3: =+E3 -> 0.1043 | AC3: =+F3 -> 0.0867 | AD3: =+G3 -> 0.0634 | AE3: =+H3 -> 0.0816 | AF3: =+I3 -> 0.1041 | AG3: =+J3 -> 0.0286 | ... AK3: =+N3 -> 0.0358 | AO3: headline | AS3: no food & energy | AT3: no food & energy & shelter | AW3: =+Z3 -> 0.2865 | AX3: =+AA3 -> 0.038 | AY3: =+AB3 -> 0.1043 | AZ3: =+AC3 -> 0.0867 | BA3: =+AD3 -> 0.0634 | BB3: =+AE3 -> 0.0816 | BC3: =+AF3 -> 0.1041 | BD3: =+AG3 -> 0.0286 | ... BH3: =+AK3 -> 0.0358 | BL3: headline | BP3: no food & energy | BQ3: no food & energy & shelter | BT3: =+AW3 -> 0.2865 | BU3: =+AX3 -> 0.038 | BV3: =+AY3 -> 0.1043 | BW3: =+AZ3 -> 0.0867 | BX3: =+BA3 -> 0.0634 | BY3: =+BB3 -> 0.0816 | BZ3: =+BC3 -> 0.1041 | CA3: =+BD3 -> 0.0286 | ... CE3: =+BH3 -> 0.0358 | CH3: 1 | CI3: =+BT3 -> 0.2865 | CJ3: =+BU3 -> 0.038 | CK3: =+BV3 -> 0.1043 | CL3: =+BW3 -> 0.0867 | CM3: =+BX3 -> 0.0634 | CN3: =+BY3 -> 0.0816 | CO3: =+BZ3 -> 0.1041 | CP3: =+CA3 -> 0.0286 | ... CT3: =+CE3 -> 0.0358
A4: Fecha | B4: Nivel general | C4: Alimentos y bebidas no alcohólicas | D4: Bebidas alcohólicas y tabaco | E4: Prendas de vestir y calzado | F4: Vivienda, agua, electricidad, gas y otros combustibles | G4: Equipamiento y mantenimiento del hogar | H4: Salud | I4: Transporte | J4: Comunicación | K4: Recreación y cultura | L4: Educación | M4: Restaurantes y hoteles | N4: Bienes y servicios varios | O4: Estacional | P4: Núcleo | Q4: Regulados | R4: Nivel General | S4: Subyacente | T4: Subyacente-AyB | U4: Subyacente-Food | V4: Core | W4: Supercore | Y4: Nivel general | Z4: Alimentos y bebidas no alcohólicas | AA4: Bebidas alcohólicas y tabaco | AB4: Prendas de vestir y calzado | AC4: Vivienda, agua, electricidad, gas y otros combustibles | AD4: Equipamiento y mantenimiento del hogar | AE4: Salud | AF4: Transporte | AG4: Comunicación | AH4: Recreación y cultura | AI4: Educación | AJ4: Restaurantes y hoteles | AK4: Bienes y servicios varios | AL4: Estacional | AM4: Núcleo | AN4: Regulados | AO4: =+R4 -> Nivel General | AP4: =+S4 -> Subyacente | AQ4: =+T4 -> Subyacente-AyB | AR4: =+U4 -> Subyacente-Food | AS4: Core | AT4: Supercore | AV4: Nivel general | AW4: Alimentos y bebidas no alcohólicas | AX4: Bebidas alcohólicas y tabaco | AY4: Prendas de vestir y calzado | AZ4: Vivienda, agua, electricidad, gas y otros combustibles | BA4: Equipamiento y mantenimiento del hogar | BB4: Salud | BC4: Transporte | BD4: Comunicación | BE4: Recreación y cultura | BF4: Educación | BG4: Restaurantes y hoteles | BH4: Bienes y servicios varios | BI4: Estacional | BJ4: Núcleo | BK4: Regulados | BL4: =+AO4 -> Nivel General | BM4: =+AP4 -> Subyacente | BN4: =+AQ4 -> Subyacente-AyB | BO4: =+AR4 -> Subyacente-Food | BP4: Core | BQ4: Supercore | BS4: Fecha | BT4: Alimentos y bebidas no alcohólicas | BU4: Bebidas alcohólicas y tabaco | BV4: Prendas de vestir y calzado | BW4: Vivienda, agua, electricidad, gas y otros combustibles | BX4: Equipamiento y mantenimiento del hogar | BY4: Salud | BZ4: Transporte | CA4: Comunicación | CB4: Recreación y cultura | CC4: Educación | CD4: Restaurantes y hoteles | CE4: Bienes y servicios varios | CF4: Nivel general | CH4: Fecha | CI4: Alimentos y bebidas no alcohólicas | CJ4: Bebidas alcohólicas y tabaco | CK4: Prendas de vestir y calzado | CL4: Vivienda, agua, electricidad, gas y otros combustibles | CM4: Equipamiento y mantenimiento del hogar | CN4: Salud | CO4: Transporte | CP4: Comunicación | CQ4: Recreación y cultura | CR4: Educación | CS4: Restaurantes y hoteles | CT4: Bienes y servicios varios | CU4: Nivel general
A5: =+[1]PAM!A6 -> 42705 | B5: =+[1]PAM!B6 -> 100 | C5: =+[1]PAM!C6 -> 100 | D5: =+[1]PAM!D6 -> 100 | E5: =+[1]PAM!E6 -> 100 | F5: =+[1]PAM!F6 -> 100 | G5: =+[1]PAM!G6 -> 100 | H5: =+[1]PAM!H6 -> 100 | ... N5: =+[1]PAM!N6 -> 100 | O5: =+[1]PAM!R6 -> 100 | P5: =+[1]PAM!S6 -> 100 | Q5: =+[1]PAM!T6 -> 100 | R5: =+SUMPRODUCT($C$3:$N$3,C5:N5) -> 100 | S5: =+($C$3*$C5+$D$3*$D5+$E$3*$E5+$G$3*$G5+$K$3*$K5+$M$3*$M5+$N$3*$N5)/SUM($C$3:$E$3,$G$3,$K$3,$M$3:$N$3) -> 100 | T5: =+($E$3*$E5+$G$3*$G5+$K$3*$K5+$M$3*$M5+$N$3*$N5)/SUM($E$3,$G$3,$K$3,$M$3:$N$3) -> 100 | U5: =+($E$3*$E5+$G$3*$G5+$K$3*$K5+$N$3*$N5)/SUM($E$3,$G$3,$K$3,$N$3) -> 100 | W5: =($E$3*$E5+SUMPRODUCT($G$3:$L$3,$G5:$L5)+$N$3*$N5)/SUM($E$3,$G$3:$L$3,$N$3) -> 100 | BS5: =+A5 -> 42705
A6: =+[1]PAM!A7 -> 42736 | B6: =+[1]PAM!B7 -> 101.8 | C6: =+[1]PAM!C7 -> 101.3 | D6: =+[1]PAM!D7 -> 101.3 | E6: =+[1]PAM!E7 -> 99.6 | F6: =+[1]PAM!F7 -> 102.2 | G6: =+[1]PAM!G7 -> 100.8 | H6: =+[1]PAM!H7 -> 103.2 | ... N6: =+[1]PAM!N7 -> 101.6 | O6: =+[1]PAM!R7 -> 102.1 | P6: =+[1]PAM!S7 -> 101.6 | Q6: =+[1]PAM!T7 -> 102.2 | R6: =+SUMPRODUCT($C$3:$N$3,C6:N6) -> 101.77347 | S6: =+($C$3*$C6+$D$3*$D6+$E$3*$E6+$G$3*$G6+$K$3*$K6+$M$3*$M6+$N$3*$N6)/SUM($C$3:$E$3,$G$3,$K$3,$M$3:$N$3) -> 101.47206 | T6: =+($E$3*$E6+$G$3*$G6+$K$3*$K6+$M$3*$M6+$N$3*$N6)/SUM($E$3,$G$3,$K$3,$M$3:$N$3) -> 101.62785 | U6: =+($E$3*$E6+$G$3*$G6+$K$3*$K6+$N$3*$N6)/SUM($E$3,$G$3,$K$3,$N$3) -> 101.19798 | W6: =($E$3*$E6+SUMPRODUCT($G$3:$L$3,$G6:$L6)+$N$3*$N6)/SUM($E$3,$G$3:$L$3,$N$3) -> 101.79161 | Y6: =+B6/B5-1 -> 0.018 | Z6: =+C6/C5-1 -> 0.013 | AA6: =+D6/D5-1 -> 0.013 | AB6: =+E6/E5-1 -> -0.004 | AC6: =+F6/F5-1 -> 0.022 | AD6: =+G6/G5-1 -> 0.008 | AE6: =+H6/H5-1 -> 0.032 | AF6: =+I6/I5-1 -> 0.024 | ... AT6: =+W6/W5-1 -> 0.017916109 | BS6: =+A6 -> 42736 | BT6: =(C6-C5)/$B5*C$3 -> 0.0037245 | BU6: =(D6-D5)/$B5*D$3 -> 0.000494 | BV6: =(E6-E5)/$B5*E$3 -> -0.0004172 | BW6: =(F6-F5)/$B5*F$3 -> 0.0019074 | BX6: =(G6-G5)/$B5*G$3 -> 0.0005072 | BY6: =(H6-H5)/$B5*H$3 -> 0.0026112 | BZ6: =(I6-I5)/$B5*I$3 -> 0.0024984 | CA6: =(J6-J5)/$B5*J$3 -> 0.0006006 | ... CE6: =(N6-N5)/$B5*N$3 -> 0.0005728 | CF6: =+SUM(BT6:CE6) -> 0.0177347 | CH6: =+CH$3*(B$95-B$55)/$B$55 -> 14.104383 | CI6: =+CI$3*(C$95-C$55)/$B$55 -> 4.5208809 | CJ6: =+CJ$3*(D$95-D$55)/$B$55 -> 0.41264562 | CK6: =+CK$3*(E$95-E$55)/$B$55 -> 1.3206828 | CL6: =+CL$3*(F$95-F$55)/$B$55 -> 0.91586579 | CM6: =+CM$3*(G$95-G$55)/$B$55 -> 0.84708615 | CN6: =+CN$3*(H$95-H$55)/$B$55 -> 1.3410933 | CO6: =+CO$3*(I$95-I$55)/$B$55 -> 1.6603999 | ... CT6: =+CT$3*(N$95-N$55)/$B$55 -> 0.50378968
A7: =+[1]PAM!A8 -> 42767 | B7: =+[1]PAM!B8 -> 103.5 | C7: =+[1]PAM!C8 -> 103.1 | D7: =+[1]PAM!D8 -> 105.2 | E7: =+[1]PAM!E8 -> 99.9 | F7: =+[1]PAM!F8 -> 104.6 | G7: =+[1]PAM!G8 -> 101.5 | H7: =+[1]PAM!H8 -> 105.5 | ... N7: =+[1]PAM!N8 -> 103.5 | O7: =+[1]PAM!R8 -> 102.6 | P7: =+[1]PAM!S8 -> 103.2 | Q7: =+[1]PAM!T8 -> 105.3 | R7: =+SUMPRODUCT($C$3:$N$3,C7:N7) -> 103.52511 | S7: =+($C$3*$C7+$D$3*$D7+$E$3*$E7+$G$3*$G7+$K$3*$K7+$M$3*$M7+$N$3*$N7)/SUM($C$3:$E$3,$G$3,$K$3,$M$3:$N$3) -> 102.9181 | T7: =+($E$3*$E7+$G$3*$G7+$K$3*$K7+$M$3*$M7+$N$3*$N7)/SUM($E$3,$G$3,$K$3,$M$3:$N$3) -> 102.53075 | U7: =+($E$3*$E7+$G$3*$G7+$K$3*$K7+$N$3*$N7)/SUM($E$3,$G$3,$K$3,$N$3) -> 101.95573 | W7: =($E$3*$E7+SUMPRODUCT($G$3:$L$3,$G7:$L7)+$N$3*$N7)/SUM($E$3,$G$3:$L$3,$N$3) -> 103.30059 | Y7: =+B7/B6-1 -> 0.016699411 | Z7: =+C7/C6-1 -> 0.017769003 | AA7: =+D7/D6-1 -> 0.038499506 | AB7: =+E7/E6-1 -> 0.0030120482 | AC7: =+F7/F6-1 -> 0.023483366 | AD7: =+G7/G6-1 -> 0.0069444444 | AE7: =+H7/H6-1 -> 0.022286822 | AF7: =+I7/I6-1 -> 0.01953125 | ... AT7: =+W7/W6-1 -> 0.014824207 | BS7: =+A7 -> 42767 | BT7: =(C7-C6)/$B6*C$3 -> 0.0050658153 | BU7: =(D7-D6)/$B6*D$3 -> 0.0014557957 | BV7: =(E7-E6)/$B6*E$3 -> 0.00030736739 | BW7: =(F7-F6)/$B6*F$3 -> 0.0020440079 | BX7: =(G7-G6)/$B6*G$3 -> 0.00043595285 | BY7: =(H7-H6)/$B6*H$3 -> 0.0018436149 | BZ7: =(I7-I6)/$B6*I$3 -> 0.0020451866 | CA7: =(J7-J6)/$B6*J$3 -> 0.0013204322 | ... CE7: =(N7-N6)/$B6*N$3 -> 0.00066817289 | CF7: =+SUM(BT7:CE7) -> 0.01720668
A8: =+[1]PAM!A9 -> 42795 | B8: =+[1]PAM!B9 -> 105.8 | C8: =+[1]PAM!C9 -> 105.5 | D8: =+[1]PAM!D9 -> 107.7 | E8: =+[1]PAM!E9 -> 102.4 | F8: =+[1]PAM!F9 -> 107.7 | G8: =+[1]PAM!G9 -> 102.1 | H8: =+[1]PAM!H9 -> 107.5 | ... N8: =+[1]PAM!N9 -> 105.8 | O8: =+[1]PAM!R9 -> 104.2 | P8: =+[1]PAM!S9 -> 105.3 | Q8: =+[1]PAM!T9 -> 108.6 | R8: =+SUMPRODUCT($C$3:$N$3,C8:N8) -> 105.81924 | S8: =+($C$3*$C8+$D$3*$D8+$E$3*$E8+$G$3*$G8+$K$3*$K8+$M$3*$M8+$N$3*$N8)/SUM($C$3:$E$3,$G$3,$K$3,$M$3:$N$3) -> 104.9691 | T8: =+($E$3*$E8+$G$3*$G8+$K$3*$K8+$M$3*$M8+$N$3*$N8)/SUM($E$3,$G$3,$K$3,$M$3:$N$3) -> 104.25516 | U8: =+($E$3*$E8+$G$3*$G8+$K$3*$K8+$N$3*$N8)/SUM($E$3,$G$3,$K$3,$N$3) -> 103.86247 | W8: =($E$3*$E8+SUMPRODUCT($G$3:$L$3,$G8:$L8)+$N$3*$N8)/SUM($E$3,$G$3:$L$3,$N$3) -> 105.57247 | Y8: =+B8/B7-1 -> 0.022222222 | Z8: =+C8/C7-1 -> 0.023278371 | AA8: =+D8/D7-1 -> 0.023764259 | AB8: =+E8/E7-1 -> 0.025025025 | AC8: =+F8/F7-1 -> 0.029636711 | AD8: =+G8/G7-1 -> 0.00591133 | AE8: =+H8/H7-1 -> 0.018957346 | AF8: =+I8/I7-1 -> 0.012452107 | ... AT8: =+W8/W7-1 -> 0.021992892 | BS8: =+A8 -> 42795 | BT8: =(C8-C7)/$B7*C$3 -> 0.0066434783 | BU8: =(D8-D7)/$B7*D$3 -> 0.0009178744 | BV8: =(E8-E7)/$B7*E$3 -> 0.0025193237 | BW8: =(F8-F7)/$B7*F$3 -> 0.0025968116 | BX8: =(G8-G7)/$B7*G$3 -> 0.00036753623 | BY8: =(H8-H7)/$B7*H$3 -> 0.0015768116 | BZ8: =(I8-I7)/$B7*I$3 -> 0.0013075362 | CA8: =(J8-J7)/$B7*J$3 -> 0.0011605797 | ... CE8: =(N8-N7)/$B7*N$3 -> 0.00079555556 | CF8: =+SUM(BT8:CE8) -> 0.022165507
A9: =+[1]PAM!A10 -> 42826 | B9: =+[1]PAM!B10 -> 108.7 | C9: =+[1]PAM!C10 -> 107.6 | D9: =+[1]PAM!D10 -> 110.3 | E9: =+[1]PAM!E10 -> 107.8 | F9: =+[1]PAM!F10 -> 115.8 | G9: =+[1]PAM!G10 -> 103.2 | H9: =+[1]PAM!H10 -> 109.7 | ... N9: =+[1]PAM!N10 -> 107.5 | O9: =+[1]PAM!R10 -> 108.6 | P9: =+[1]PAM!S10 -> 107.3 | Q9: =+[1]PAM!T10 -> 113.6 | R9: =+SUMPRODUCT($C$3:$N$3,C9:N9) -> 108.69498 | S9: =+($C$3*$C9+$D$3*$D9+$E$3*$E9+$G$3*$G9+$K$3*$K9+$M$3*$M9+$N$3*$N9)/SUM($C$3:$E$3,$G$3,$K$3,$M$3:$N$3) -> 107.42012 | T9: =+($E$3*$E9+$G$3*$G9+$K$3*$K9+$M$3*$M9+$N$3*$N9)/SUM($E$3,$G$3,$K$3,$M$3:$N$3) -> 106.97098 | U9: =+($E$3*$E9+$G$3*$G9+$K$3*$K9+$N$3*$N9)/SUM($E$3,$G$3,$K$3,$N$3) -> 106.81651 | W9: =($E$3*$E9+SUMPRODUCT($G$3:$L$3,$G9:$L9)+$N$3*$N9)/SUM($E$3,$G$3:$L$3,$N$3) -> 108.17019 | Y9: =+B9/B8-1 -> 0.027410208 | Z9: =+C9/C8-1 -> 0.019905213 | AA9: =+D9/D8-1 -> 0.024141133 | AB9: =+E9/E8-1 -> 0.052734375 | AC9: =+F9/F8-1 -> 0.075208914 | AD9: =+G9/G8-1 -> 0.010773751 | AE9: =+H9/H8-1 -> 0.020465116 | AF9: =+I9/I8-1 -> 0.0075685904 | ... AT9: =+W9/W8-1 -> 0.024605995 | BS9: =+A9 -> 42826 | BT9: =(C9-C8)/$B8*C$3 -> 0.005686673 | BU9: =(D9-D8)/$B8*D$3 -> 0.00093383743 | BV9: =(E9-E8)/$B8*E$3 -> 0.0053234405 | BW9: =(F9-F8)/$B8*F$3 -> 0.0066377127 | BX9: =(G9-G8)/$B8*G$3 -> 0.00065916824 | BY9: =(H9-H8)/$B8*H$3 -> 0.0016967864 | BZ9: =(I9-I8)/$B8*I$3 -> 0.00078714556 | CA9: =(J9-J8)/$B8*J$3 -> 0.0019192817 | ... CE9: =(N9-N8)/$B8*N$3 -> 0.00057523629 | CF9: =+SUM(BT9:CE9) -> 0.027180907
A10: =+[1]PAM!A11 -> 42856 | B10: =+[1]PAM!B11 -> 110.3 | C10: =+[1]PAM!C11 -> 109.2 | D10: =+[1]PAM!D11 -> 111.9 | E10: =+[1]PAM!E11 -> 110.9 | F10: =+[1]PAM!F11 -> 117.2 | G10: =+[1]PAM!G11 -> 106 | H10: =+[1]PAM!H11 -> 111.3 | ... N10: =+[1]PAM!N11 -> 108.6 | O10: =+[1]PAM!R11 -> 110.4 | P10: =+[1]PAM!S11 -> 109.1 | Q10: =+[1]PAM!T11 -> 114.6 | R10: =+SUMPRODUCT($C$3:$N$3,C10:N10) -> 110.30142 | S10: =+($C$3*$C10+$D$3*$D10+$E$3*$E10+$G$3*$G10+$K$3*$K10+$M$3*$M10+$N$3*$N10)/SUM($C$3:$E$3,$G$3,$K$3,$M$3:$N$3) -> 109.19893 | T10: =+($E$3*$E10+$G$3*$G10+$K$3*$K10+$M$3*$M10+$N$3*$N10)/SUM($E$3,$G$3,$K$3,$M$3:$N$3) -> 108.91169 | U10: =+($E$3*$E10+$G$3*$G10+$K$3*$K10+$N$3*$N10)/SUM($E$3,$G$3,$K$3,$N$3) -> 108.71071 | W10: =($E$3*$E10+SUMPRODUCT($G$3:$L$3,$G10:$L10)+$N$3*$N10)/SUM($E$3,$G$3:$L$3,$N$3) -> 109.73726 | Y10: =+B10/B9-1 -> 0.014719411 | Z10: =+C10/C9-1 -> 0.014869888 | AA10: =+D10/D9-1 -> 0.014505893 | AB10: =+E10/E9-1 -> 0.028756957 | AC10: =+F10/F9-1 -> 0.01208981 | AD10: =+G10/G9-1 -> 0.027131783 | AE10: =+H10/H9-1 -> 0.014585232 | AF10: =+I10/I9-1 -> 0.00657277 | ... AT10: =+W10/W9-1 -> 0.014487113 | BS10: =+A10 -> 42856 | BT10: =(C10-C9)/$B9*C$3 -> 0.0042171113 | BU10: =(D10-D9)/$B9*D$3 -> 0.00055933763 | BV10: =(E10-E9)/$B9*E$3 -> 0.002974517 | BW10: =(F10-F9)/$B9*F$3 -> 0.0011166513 | BX10: =(G10-G9)/$B9*G$3 -> 0.0016331187 | BY10: =(H10-H9)/$B9*H$3 -> 0.001201104 | BZ10: =(I10-I9)/$B9*I$3 -> 0.00067037718 | CA10: =(J10-J9)/$B9*J$3 -> 0.00028942042 | ... CE10: =(N10-N9)/$B9*N$3 -> 0.00036228151 | CF10: =+SUM(BT10:CE10) -> 0.014778657
A11: =+[1]PAM!A12 -> 42887 | B11: =+[1]PAM!B12 -> 111.4 | C11: =+[1]PAM!C12 -> 109.7 | D11: =+[1]PAM!D12 -> 112.8 | E11: =+[1]PAM!E12 -> 112 | F11: =+[1]PAM!F12 -> 118.6 | G11: =+[1]PAM!G12 -> 107.3 | H11: =+[1]PAM!H12 -> 113.1 | ... N11: =+[1]PAM!N12 -> 110.5 | O11: =+[1]PAM!R12 -> 111.2 | P11: =+[1]PAM!S12 -> 110.3 | Q11: =+[1]PAM!T12 -> 115.4 | R11: =+SUMPRODUCT($C$3:$N$3,C11:N11) -> 111.39721 | S11: =+($C$3*$C11+$D$3*$D11+$E$3*$E11+$G$3*$G11+$K$3*$K11+$M$3*$M11+$N$3*$N11)/SUM($C$3:$E$3,$G$3,$K$3,$M$3:$N$3) -> 110.19502 | T11: =+($E$3*$E11+$G$3*$G11+$K$3*$K11+$M$3*$M11+$N$3*$N11)/SUM($E$3,$G$3,$K$3,$M$3:$N$3) -> 110.31454 | U11: =+($E$3*$E11+$G$3*$G11+$K$3*$K11+$N$3*$N11)/SUM($E$3,$G$3,$K$3,$N$3) -> 110.17278 | W11: =($E$3*$E11+SUMPRODUCT($G$3:$L$3,$G11:$L11)+$N$3*$N11)/SUM($E$3,$G$3:$L$3,$N$3) -> 111.11528 | Y11: =+B11/B10-1 -> 0.0099728015 | Z11: =+C11/C10-1 -> 0.0045787546 | AA11: =+D11/D10-1 -> 0.0080428954 | AB11: =+E11/E10-1 -> 0.0099188458 | AC11: =+F11/F10-1 -> 0.011945392 | AD11: =+G11/G10-1 -> 0.012264151 | AE11: =+H11/H10-1 -> 0.016172507 | AF11: =+I11/I10-1 -> 0.0074626866 | ... AT11: =+W11/W10-1 -> 0.012557475 | BS11: =+A11 -> 42887 | BT11: =(C11-C10)/$B10*C$3 -> 0.0012987307 | BU11: =(D11-D10)/$B10*D$3 -> 0.00031006346 | BV11: =(E11-E10)/$B10*E$3 -> 0.0010401632 | BW11: =(F11-F10)/$B10*F$3 -> 0.0011004533 | BX11: =(G11-G10)/$B10*G$3 -> 0.00074723481 | BY11: =(H11-H10)/$B10*H$3 -> 0.001331641 | BZ11: =(I11-I10)/$B10*I$3 -> 0.00075503173 | CA11: =(J11-J10)/$B10*J$3 -> 0.00025929284 | ... CE11: =(N11-N10)/$B10*N$3 -> 0.00061668178 | CF11: =+SUM(BT11:CE11) -> 0.0099346328
A12: =+[1]PAM!A13 -> 42917 | B12: =+[1]PAM!B13 -> 113.6 | C12: =+[1]PAM!C13 -> 111 | D12: =+[1]PAM!D13 -> 116 | E12: =+[1]PAM!E13 -> 110.9 | F12: =+[1]PAM!F13 -> 120.5 | G12: =+[1]PAM!G13 -> 110 | H12: =+[1]PAM!H13 -> 117.2 | ... N12: =+[1]PAM!N13 -> 112 | O12: =+[1]PAM!R13 -> 112.3 | P12: =+[1]PAM!S13 -> 112.4 | Q12: =+[1]PAM!T13 -> 118.4 | R12: =+SUMPRODUCT($C$3:$N$3,C12:N12) -> 113.58451 | S12: =+($C$3*$C12+$D$3*$D12+$E$3*$E12+$G$3*$G12+$K$3*$K12+$M$3*$M12+$N$3*$N12)/SUM($C$3:$E$3,$G$3,$K$3,$M$3:$N$3) -> 112.09114 | T12: =+($E$3*$E12+$G$3*$G12+$K$3*$K12+$M$3*$M12+$N$3*$N12)/SUM($E$3,$G$3,$K$3,$M$3:$N$3) -> 112.54894 | U12: =+($E$3*$E12+$G$3*$G12+$K$3*$K12+$N$3*$N12)/SUM($E$3,$G$3,$K$3,$N$3) -> 112.00844 | W12: =($E$3*$E12+SUMPRODUCT($G$3:$L$3,$G12:$L12)+$N$3*$N12)/SUM($E$3,$G$3:$L$3,$N$3) -> 113.55112 | Y12: =+B12/B11-1 -> 0.019748654 | Z12: =+C12/C11-1 -> 0.011850501 | AA12: =+D12/D11-1 -> 0.028368794 | AB12: =+E12/E11-1 -> -0.0098214286 | AC12: =+F12/F11-1 -> 0.016020236 | AD12: =+G12/G11-1 -> 0.025163094 | AE12: =+H12/H11-1 -> 0.036251105 | AF12: =+I12/I11-1 -> 0.028703704 | ... AT12: =+W12/W11-1 -> 0.021921745 | BS12: =+A12 -> 42917 | BT12: =(C12-C11)/$B11*C$3 -> 0.0033433573 | BU12: =(D12-D11)/$B11*D$3 -> 0.0010915619 | BV12: =(E12-E11)/$B11*E$3 -> -0.0010298923 | BW12: =(F12-F11)/$B11*F$3 -> 0.0014787253 | BX12: =(G12-G11)/$B11*G$3 -> 0.0015366248 | BY12: =(H12-H11)/$B11*H$3 -> 0.0030032316 | BZ12: =(I12-I11)/$B11*I$3 -> 0.0028968582 | CA12: =(J12-J11)/$B11*J$3 -> 0.00048779174 | ... CE12: =(N12-N11)/$B11*N$3 -> 0.00048204668 | CF12: =+SUM(BT12:CE12) -> 0.01963465
A13: =+[1]PAM!A14 -> 42948 | B13: =+[1]PAM!B14 -> 115.1 | C13: =+[1]PAM!C14 -> 113.5 | D13: =+[1]PAM!D14 -> 117.2 | E13: =+[1]PAM!E14 -> 110.2 | F13: =+[1]PAM!F14 -> 122.5 | G13: =+[1]PAM!G14 -> 111.2 | H13: =+[1]PAM!H14 -> 119.9 | ... N13: =+[1]PAM!N14 -> 113.6 | O13: =+[1]PAM!R14 -> 113.3 | P13: =+[1]PAM!S14 -> 114 | Q13: =+[1]PAM!T14 -> 120 | R13: =+SUMPRODUCT($C$3:$N$3,C13:N13) -> 115.10087 | S13: =+($C$3*$C13+$D$3*$D13+$E$3*$E13+$G$3*$G13+$K$3*$K13+$M$3*$M13+$N$3*$N13)/SUM($C$3:$E$3,$G$3,$K$3,$M$3:$N$3) -> 113.41832 | T13: =+($E$3*$E13+$G$3*$G13+$K$3*$K13+$M$3*$M13+$N$3*$N13)/SUM($E$3,$G$3,$K$3,$M$3:$N$3) -> 112.95206 | U13: =+($E$3*$E13+$G$3*$G13+$K$3*$K13+$N$3*$N13)/SUM($E$3,$G$3,$K$3,$N$3) -> 112.41247 | W13: =($E$3*$E13+SUMPRODUCT($G$3:$L$3,$G13:$L13)+$N$3*$N13)/SUM($E$3,$G$3:$L$3,$N$3) -> 114.63169 | Y13: =+B13/B12-1 -> 0.013204225 | Z13: =+C13/C12-1 -> 0.022522523 | AA13: =+D13/D12-1 -> 0.010344828 | AB13: =+E13/E12-1 -> -0.0063119928 | AC13: =+F13/F12-1 -> 0.01659751 | AD13: =+G13/G12-1 -> 0.010909091 | AE13: =+H13/H12-1 -> 0.023037543 | AF13: =+I13/I12-1 -> 0.01080108 | ... AT13: =+W13/W12-1 -> 0.0095160945 | BS13: =+A13 -> 42948 | BT13: =(C13-C12)/$B12*C$3 -> 0.0063050176 | BU13: =(D13-D12)/$B12*D$3 -> 0.00040140845 | BV13: =(E13-E12)/$B12*E$3 -> -0.00064269366 | BW13: =(F13-F12)/$B12*F$3 -> 0.0015264085 | BX13: =(G13-G12)/$B12*G$3 -> 0.00066971831 | BY13: =(H13-H12)/$B12*H$3 -> 0.0019394366 | BZ13: =(I13-I12)/$B12*I$3 -> 0.0010996479 | CA13: =(J13-J12)/$B12*J$3 -> 0.00025176056 | ... CE13: =(N13-N12)/$B12*N$3 -> 0.00050422535 | CF13: =+SUM(BT13:CE13) -> 0.013348239
A14: =+[1]PAM!A15 -> 42979 | B14: =+[1]PAM!B15 -> 117.3 | C14: =+[1]PAM!C15 -> 115.2 | D14: =+[1]PAM!D15 -> 118 | E14: =+[1]PAM!E15 -> 113 | F14: =+[1]PAM!F15 -> 127.7 | G14: =+[1]PAM!G15 -> 112.5 | H14: =+[1]PAM!H15 -> 122.7 | ... N14: =+[1]PAM!N15 -> 115.5 | O14: =+[1]PAM!R15 -> 116.7 | P14: =+[1]PAM!S15 -> 115.8 | Q14: =+[1]PAM!T15 -> 123.1 | R14: =+SUMPRODUCT($C$3:$N$3,C14:N14) -> 117.3003 | S14: =+($C$3*$C14+$D$3*$D14+$E$3*$E14+$G$3*$G14+$K$3*$K14+$M$3*$M14+$N$3*$N14)/SUM($C$3:$E$3,$G$3,$K$3,$M$3:$N$3) -> 115.36317 | T14: =+($E$3*$E14+$G$3*$G14+$K$3*$K14+$M$3*$M14+$N$3*$N14)/SUM($E$3,$G$3,$K$3,$M$3:$N$3) -> 115.21403 | U14: =+($E$3*$E14+$G$3*$G14+$K$3*$K14+$N$3*$N14)/SUM($E$3,$G$3,$K$3,$N$3) -> 114.78014 | W14: =($E$3*$E14+SUMPRODUCT($G$3:$L$3,$G14:$L14)+$N$3*$N14)/SUM($E$3,$G$3:$L$3,$N$3) -> 116.75307 | Y14: =+B14/B13-1 -> 0.019113814 | Z14: =+C14/C13-1 -> 0.014977974 | AA14: =+D14/D13-1 -> 0.0068259386 | AB14: =+E14/E13-1 -> 0.025408348 | AC14: =+F14/F13-1 -> 0.04244898 | AD14: =+G14/G13-1 -> 0.011690647 | AE14: =+H14/H13-1 -> 0.023352794 | AF14: =+I14/I13-1 -> 0.0062333037 | ... AT14: =+W14/W13-1 -> 0.018506108 | BS14: =+A14 -> 42979 | BT14: =(C14-C13)/$B13*C$3 -> 0.0042315378 | BU14: =(D14-D13)/$B13*D$3 -> 0.00026411816 | BV14: =(E14-E13)/$B13*E$3 -> 0.0025372719 | BW14: =(F14-F13)/$B13*F$3 -> 0.0039169418 | BX14: =(G14-G13)/$B13*G$3 -> 0.00071607298 | BY14: =(H14-H13)/$B13*H$3 -> 0.0019850565 | BZ14: =(I14-I13)/$B13*I$3 -> 0.00063310165 | CA14: =(J14-J13)/$B13*J$3 -> 0.00044726325 | ... CE14: =(N14-N13)/$B13*N$3 -> 0.00059096438 | CF14: =+SUM(BT14:CE14) -> 0.019108862
A15: =+[1]PAM!A16 -> 43009 | B15: =+[1]PAM!B16 -> 119.3 | C15: =+[1]PAM!C16 -> 116.7 | D15: =+[1]PAM!D16 -> 121.5 | E15: =+[1]PAM!E16 -> 116.3 | F15: =+[1]PAM!F16 -> 129.1 | G15: =+[1]PAM!G16 -> 113.2 | H15: =+[1]PAM!H16 -> 124.3 | ... N15: =+[1]PAM!N16 -> 117 | O15: =+[1]PAM!R16 -> 119.7 | P15: =+[1]PAM!S16 -> 117.5 | Q15: =+[1]PAM!T16 -> 125.4 | R15: =+SUMPRODUCT($C$3:$N$3,C15:N15) -> 119.27587 | S15: =+($C$3*$C15+$D$3*$D15+$E$3*$E15+$G$3*$G15+$K$3*$K15+$M$3*$M15+$N$3*$N15)/SUM($C$3:$E$3,$G$3,$K$3,$M$3:$N$3) -> 117.26168 | T15: =+($E$3*$E15+$G$3*$G15+$K$3*$K15+$M$3*$M15+$N$3*$N15)/SUM($E$3,$G$3,$K$3,$M$3:$N$3) -> 117.2613 | U15: =+($E$3*$E15+$G$3*$G15+$K$3*$K15+$N$3*$N15)/SUM($E$3,$G$3,$K$3,$N$3) -> 116.9872 | W15: =($E$3*$E15+SUMPRODUCT($G$3:$L$3,$G15:$L15)+$N$3*$N15)/SUM($E$3,$G$3:$L$3,$N$3) -> 119.05701 | Y15: =+B15/B14-1 -> 0.017050298 | Z15: =+C15/C14-1 -> 0.013020833 | AA15: =+D15/D14-1 -> 0.029661017 | AB15: =+E15/E14-1 -> 0.02920354 | AC15: =+F15/F14-1 -> 0.010963195 | AD15: =+G15/G14-1 -> 0.0062222222 | AE15: =+H15/H14-1 -> 0.013039935 | AF15: =+I15/I14-1 -> 0.016814159 | ... AT15: =+W15/W14-1 -> 0.01973343 | BS15: =+A15 -> 43009 | BT15: =(C15-C14)/$B14*C$3 -> 0.0036636829 | BU15: =(D15-D14)/$B14*D$3 -> 0.0011338448 | BV15: =(E15-E14)/$B14*E$3 -> 0.0029342711 | BW15: =(F15-F14)/$B14*F$3 -> 0.0010347826 | BX15: =(G15-G14)/$B14*G$3 -> 0.00037834612 | BY15: =(H15-H14)/$B14*H$3 -> 0.0011130435 | BZ15: =(I15-I14)/$B14*I$3 -> 0.0016861893 | CA15: =(J15-J14)/$B14*J$3 -> 0.0018042626 | ... CE15: =(N15-N14)/$B14*N$3 -> 0.00045780051 | CF15: =+SUM(BT15:CE15) -> 0.016842029
A16: =+[1]PAM!A17 -> 43040 | B16: =+[1]PAM!B17 -> 121.2 | C16: =+[1]PAM!C17 -> 118.3 | D16: =+[1]PAM!D17 -> 122.9 | E16: =+[1]PAM!E17 -> 118.2 | F16: =+[1]PAM!F17 -> 130.9 | G16: =+[1]PAM!G17 -> 114.5 | H16: =+[1]PAM!H17 -> 126.1 | ... N16: =+[1]PAM!N17 -> 118.7 | O16: =+[1]PAM!R17 -> 122.8 | P16: =+[1]PAM!S17 -> 119 | Q16: =+[1]PAM!T17 -> 128 | R16: =+SUMPRODUCT($C$3:$N$3,C16:N16) -> 121.18855 | S16: =+($C$3*$C16+$D$3*$D16+$E$3*$E16+$G$3*$G16+$K$3*$K16+$M$3*$M16+$N$3*$N16)/SUM($C$3:$E$3,$G$3,$K$3,$M$3:$N$3) -> 118.95783 | T16: =+($E$3*$E16+$G$3*$G16+$K$3*$K16+$M$3*$M16+$N$3*$N16)/SUM($E$3,$G$3,$K$3,$M$3:$N$3) -> 119.06571 | U16: =+($E$3*$E16+$G$3*$G16+$K$3*$K16+$N$3*$N16)/SUM($E$3,$G$3,$K$3,$N$3) -> 118.6177 | W16: =($E$3*$E16+SUMPRODUCT($G$3:$L$3,$G16:$L16)+$N$3*$N16)/SUM($E$3,$G$3:$L$3,$N$3) -> 121.12597 | Y16: =+B16/B15-1 -> 0.015926236 | Z16: =+C16/C15-1 -> 0.013710368 | AA16: =+D16/D15-1 -> 0.011522634 | AB16: =+E16/E15-1 -> 0.016337059 | AC16: =+F16/F15-1 -> 0.01394268 | AD16: =+G16/G15-1 -> 0.011484099 | AE16: =+H16/H15-1 -> 0.014481094 | AF16: =+I16/I15-1 -> 0.034812881 | ... AT16: =+W16/W15-1 -> 0.017377928 | BS16: =+A16 -> 43040 | BT16: =(C16-C15)/$B15*C$3 -> 0.0038424141 | BU16: =(D16-D15)/$B15*D$3 -> 0.00044593462 | BV16: =(E16-E15)/$B15*E$3 -> 0.0016611065 | BW16: =(F16-F15)/$B15*F$3 -> 0.0013081308 | BX16: =(G16-G15)/$B15*G$3 -> 0.00069086337 | BY16: =(H16-H15)/$B15*H$3 -> 0.0012311819 | BZ16: =(I16-I15)/$B15*I$3 -> 0.0034903604 | CA16: =(J16-J15)/$B15*J$3 -> 0.00023973177 | ... CE16: =(N16-N15)/$B15*N$3 -> 0.0005101425 | CF16: =+SUM(BT16:CE16) -> 0.016032523
A17: =+[1]PAM!A18 -> 43070 | B17: =+[1]PAM!B18 -> 125 | C17: =+[1]PAM!C18 -> 119.1 | D17: =+[1]PAM!D18 -> 123.7 | E17: =+[1]PAM!E18 -> 119.1 | F17: =+[1]PAM!F18 -> 156.4 | G17: =+[1]PAM!G18 -> 118 | H17: =+[1]PAM!H18 -> 129 | ... N17: =+[1]PAM!N18 -> 120.2 | O17: =+[1]PAM!R18 -> 123.1 | P17: =+[1]PAM!S18 -> 120.8 | Q17: =+[1]PAM!T18 -> 141.1 | R17: =+SUMPRODUCT($C$3:$N$3,C17:N17) -> 124.99152 | S17: =+($C$3*$C17+$D$3*$D17+$E$3*$E17+$G$3*$G17+$K$3*$K17+$M$3*$M17+$N$3*$N17)/SUM($C$3:$E$3,$G$3,$K$3,$M$3:$N$3) -> 120.2492 | T17: =+($E$3*$E17+$G$3*$G17+$K$3*$K17+$M$3*$M17+$N$3*$N17)/SUM($E$3,$G$3,$K$3,$M$3:$N$3) -> 120.80198 | U17: =+($E$3*$E17+$G$3*$G17+$K$3*$K17+$N$3*$N17)/SUM($E$3,$G$3,$K$3,$N$3) -> 120.18937 | W17: =($E$3*$E17+SUMPRODUCT($G$3:$L$3,$G17:$L17)+$N$3*$N17)/SUM($E$3,$G$3:$L$3,$N$3) -> 123.3832 | Y17: =+B17/B16-1 -> 0.031353135 | Z17: =+C17/C16-1 -> 0.0067624683 | AA17: =+D17/D16-1 -> 0.0065093572 | AB17: =+E17/E16-1 -> 0.0076142132 | AC17: =+F17/F16-1 -> 0.19480519 | AD17: =+G17/G16-1 -> 0.030567686 | AE17: =+H17/H16-1 -> 0.022997621 | AF17: =+I17/I16-1 -> 0.033641716 | ... AT17: =+W17/W16-1 -> 0.018635369 | AV17: =+B17/B5-1 -> 0.25 | AW17: =+C17/C5-1 -> 0.191 | AX17: =+D17/D5-1 -> 0.237 | AY17: =+E17/E5-1 -> 0.191 | AZ17: =+F17/F5-1 -> 0.564 | BA17: =+G17/G5-1 -> 0.18 | BB17: =+H17/H5-1 -> 0.29 | BC17: =+I17/I5-1 -> 0.229 | ... BQ17: =+W17/W5-1 -> 0.23383202 | BS17: =+A17 -> 43070 | BT17: =(C17-C16)/$B16*C$3 -> 0.0018910891 | BU17: =(D17-D16)/$B16*D$3 -> 0.00025082508 | BV17: =(E17-E16)/$B16*E$3 -> 0.00077450495 | BW17: =(F17-F16)/$B16*F$3 -> 0.018241337 | BX17: =(G17-G16)/$B16*G$3 -> 0.0018308581 | BY17: =(H17-H16)/$B16*H$3 -> 0.0019524752 | BZ17: =(I17-I16)/$B16*I$3 -> 0.0034356436 | CA17: =(J17-J16)/$B16*J$3 -> 0.00047194719 | ... CE17: =(N17-N16)/$B16*N$3 -> 0.00044306931 | CF17: =+SUM(BT17:CE17) -> 0.03137764
A18: =+[1]PAM!A19 -> 43101 | B18: =+[1]PAM!B19 -> 127.3 | C18: =+[1]PAM!C19 -> 121.3 | D18: =+[1]PAM!D19 -> 126.9 | E18: =+[1]PAM!E19 -> 119.3 | F18: =+[1]PAM!F19 -> 160 | G18: =+[1]PAM!G19 -> 119.1 | H18: =+[1]PAM!H19 -> 131.2 | ... N18: =+[1]PAM!N19 -> 122.4 | O18: =+[1]PAM!R19 -> 126.5 | P18: =+[1]PAM!S19 -> 122.7 | Q18: =+[1]PAM!T19 -> 144.4 | R18: =+SUMPRODUCT($C$3:$N$3,C18:N18) -> 127.29932 | S18: =+($C$3*$C18+$D$3*$D18+$E$3*$E18+$G$3*$G18+$K$3*$K18+$M$3*$M18+$N$3*$N18)/SUM($C$3:$E$3,$G$3,$K$3,$M$3:$N$3) -> 122.42252 | T18: =+($E$3*$E18+$G$3*$G18+$K$3*$K18+$M$3*$M18+$N$3*$N18)/SUM($E$3,$G$3,$K$3,$M$3:$N$3) -> 122.84512 | U18: =+($E$3*$E18+$G$3*$G18+$K$3*$K18+$N$3*$N18)/SUM($E$3,$G$3,$K$3,$N$3) -> 121.8655 | W18: =($E$3*$E18+SUMPRODUCT($G$3:$L$3,$G18:$L18)+$N$3*$N18)/SUM($E$3,$G$3:$L$3,$N$3) -> 125.30616 | Y18: =+B18/B17-1 -> 0.0184 | Z18: =+C18/C17-1 -> 0.018471872 | AA18: =+D18/D17-1 -> 0.025869038 | AB18: =+E18/E17-1 -> 0.0016792611 | AC18: =+F18/F17-1 -> 0.023017903 | AD18: =+G18/G17-1 -> 0.0093220339 | AE18: =+H18/H17-1 -> 0.017054264 | AF18: =+I18/I17-1 -> 0.017900732 | ... AT18: =+W18/W17-1 -> 0.01558528 | AV18: =+B18/B6-1 -> 0.25049116 | AW18: =+C18/C6-1 -> 0.19743337 | AX18: =+D18/D6-1 -> 0.25271471 | AY18: =+E18/E6-1 -> 0.19779116 | AZ18: =+F18/F6-1 -> 0.56555773 | BA18: =+G18/G6-1 -> 0.18154762 | BB18: =+H18/H6-1 -> 0.27131783 | BC18: =+I18/I6-1 -> 0.22167969 | ... BQ18: =+W18/W6-1 -> 0.23100679 | BS18: =+A18 -> 43101 | BT18: =(C18-C17)/$B17*C$3 -> 0.0050424 | BU18: =(D18-D17)/$B17*D$3 -> 0.0009728 | BV18: =(E18-E17)/$B17*E$3 -> 0.00016688 | BW18: =(F18-F17)/$B17*F$3 -> 0.00249696 | BX18: =(G18-G17)/$B17*G$3 -> 0.00055792 | BY18: =(H18-H17)/$B17*H$3 -> 0.00143616 | BZ18: =(I18-I17)/$B17*I$3 -> 0.00183216 | CA18: =(J18-J17)/$B17*J$3 -> 0.00061776 | ... CE18: =(N18-N17)/$B17*N$3 -> 0.00063008 | CF18: =+SUM(BT18:CE18) -> 0.0184624
A19: =+[1]PAM!A20 -> 43132 | B19: =+[1]PAM!B20 -> 130.3 | C19: =+[1]PAM!C20 -> 123.7 | D19: =+[1]PAM!D20 -> 129 | E19: =+[1]PAM!E20 -> 118 | F19: =+[1]PAM!F20 -> 165.3 | G19: =+[1]PAM!G20 -> 121.2 | H19: =+[1]PAM!H20 -> 134 | ... N19: =+[1]PAM!N20 -> 125.2 | O19: =+[1]PAM!R20 -> 125.3 | P19: =+[1]PAM!S20 -> 125.2 | Q19: =+[1]PAM!T20 -> 151.6 | R19: =+SUMPRODUCT($C$3:$N$3,C19:N19) -> 130.2957 | S19: =+($C$3*$C19+$D$3*$D19+$E$3*$E19+$G$3*$G19+$K$3*$K19+$M$3*$M19+$N$3*$N19)/SUM($C$3:$E$3,$G$3,$K$3,$M$3:$N$3) -> 124.20034 | T19: =+($E$3*$E19+$G$3*$G19+$K$3*$K19+$M$3*$M19+$N$3*$N19)/SUM($E$3,$G$3,$K$3,$M$3:$N$3) -> 124.09141 | U19: =+($E$3*$E19+$G$3*$G19+$K$3*$K19+$N$3*$N19)/SUM($E$3,$G$3,$K$3,$N$3) -> 122.80411 | W19: =($E$3*$E19+SUMPRODUCT($G$3:$L$3,$G19:$L19)+$N$3*$N19)/SUM($E$3,$G$3:$L$3,$N$3) -> 128.42387 | Y19: =+B19/B18-1 -> 0.023566379 | Z19: =+C19/C18-1 -> 0.019785655 | AA19: =+D19/D18-1 -> 0.016548463 | AB19: =+E19/E18-1 -> -0.010896899 | AC19: =+F19/F18-1 -> 0.033125 | AD19: =+G19/G18-1 -> 0.017632242 | AE19: =+H19/H18-1 -> 0.021341463 | AF19: =+I19/I18-1 -> 0.04636291 | ... AT19: =+W19/W18-1 -> 0.02488069 | AV19: =+B19/B7-1 -> 0.2589372 | AW19: =+C19/C7-1 -> 0.19980601 | AX19: =+D19/D7-1 -> 0.22623574 | AY19: =+E19/E7-1 -> 0.18118118 | AZ19: =+F19/F7-1 -> 0.58030593 | BA19: =+G19/G7-1 -> 0.19408867 | BB19: =+H19/H7-1 -> 0.27014218 | BC19: =+I19/I7-1 -> 0.25383142 | ... BQ19: =+W19/W7-1 -> 0.24320555 | BS19: =+A19 -> 43132 | BT19: =(C19-C18)/$B18*C$3 -> 0.005401414 | BU19: =(D19-D18)/$B18*D$3 -> 0.00062686567 | BV19: =(E19-E18)/$B18*E$3 -> -0.0010651218 | BW19: =(F19-F18)/$B18*F$3 -> 0.0036096622 | BX19: =(G19-G18)/$B18*G$3 -> 0.0010458759 | BY19: =(H19-H18)/$B18*H$3 -> 0.0017948154 | BZ19: =(I19-I18)/$B18*I$3 -> 0.0047429694 | CA19: =(J19-J18)/$B18*J$3 -> 0.0033475255 | ... CE19: =(N19-N18)/$B18*N$3 -> 0.00078743126 | CF19: =+SUM(BT19:CE19) -> 0.023537942
A20: =+[1]PAM!A21 -> 43160 | B20: =+[1]PAM!B21 -> 132.8 | C20: =+[1]PAM!C21 -> 126.9 | D20: =+[1]PAM!D21 -> 129.9 | E20: =+[1]PAM!E21 -> 121.5 | F20: =+[1]PAM!F21 -> 163.5 | G20: =+[1]PAM!G21 -> 126.6 | H20: =+[1]PAM!H21 -> 135.8 | ... N20: =+[1]PAM!N21 -> 127 | O20: =+[1]PAM!R21 -> 126.4 | P20: =+[1]PAM!S21 -> 128.4 | Q20: =+[1]PAM!T21 -> 152.6 | R20: =+SUMPRODUCT($C$3:$N$3,C20:N20) -> 132.83396 | S20: =+($C$3*$C20+$D$3*$D20+$E$3*$E20+$G$3*$G20+$K$3*$K20+$M$3*$M20+$N$3*$N20)/SUM($C$3:$E$3,$G$3,$K$3,$M$3:$N$3) -> 127.02429 | T20: =+($E$3*$E20+$G$3*$G20+$K$3*$K20+$M$3*$M20+$N$3*$N20)/SUM($E$3,$G$3,$K$3,$M$3:$N$3) -> 126.81875 | U20: =+($E$3*$E20+$G$3*$G20+$K$3*$K20+$N$3*$N20)/SUM($E$3,$G$3,$K$3,$N$3) -> 125.77304 | W20: =($E$3*$E20+SUMPRODUCT($G$3:$L$3,$G20:$L20)+$N$3*$N20)/SUM($E$3,$G$3:$L$3,$N$3) -> 131.55388 | Y20: =+B20/B19-1 -> 0.019186493 | Z20: =+C20/C19-1 -> 0.025869038 | AA20: =+D20/D19-1 -> 0.0069767442 | AB20: =+E20/E19-1 -> 0.029661017 | AC20: =+F20/F19-1 -> -0.010889292 | AD20: =+G20/G19-1 -> 0.044554455 | AE20: =+H20/H19-1 -> 0.013432836 | AF20: =+I20/I19-1 -> 0.018334607 | ... AT20: =+W20/W19-1 -> 0.024372509 | AV20: =+B20/B8-1 -> 0.25519849 | AW20: =+C20/C8-1 -> 0.2028436 | AX20: =+D20/D8-1 -> 0.20612813 | AY20: =+E20/E8-1 -> 0.18652344 | AZ20: =+F20/F8-1 -> 0.51810585 | BA20: =+G20/G8-1 -> 0.23996082 | BB20: =+H20/H8-1 -> 0.26325581 | BC20: =+I20/I8-1 -> 0.26111637 | ... BQ20: =+W20/W8-1 -> 0.24610024 | BS20: =+A20 -> 43160 | BT20: =(C20-C19)/$B19*C$3 -> 0.0070360706 | BU20: =(D20-D19)/$B19*D$3 -> 0.00026247122 | BV20: =(E20-E19)/$B19*E$3 -> 0.0028016117 | BW20: =(F20-F19)/$B19*F$3 -> -0.0011976976 | BX20: =(G20-G19)/$B19*G$3 -> 0.0026274751 | BY20: =(H20-H19)/$B19*H$3 -> 0.0011272448 | BZ20: =(I20-I19)/$B19*I$3 -> 0.0019174213 | CA20: =(J20-J19)/$B19*J$3 -> 0.0010535687 | ... CE20: =(N20-N19)/$B19*N$3 -> 0.00049455104 | CF20: =+SUM(BT20:CE20) -> 0.019480123
A21: =+[1]PAM!A22 -> 43191 | B21: =+[1]PAM!B22 -> 136.6 | C21: =+[1]PAM!C22 -> 128.5 | D21: =+[1]PAM!D22 -> 131.8 | E21: =+[1]PAM!E22 -> 127.9 | F21: =+[1]PAM!F22 -> 177.6 | G21: =+[1]PAM!G22 -> 128.2 | H21: =+[1]PAM!H22 -> 138.5 | ... N21: =+[1]PAM!N22 -> 129.6 | O21: =+[1]PAM!R22 -> 129.2 | P21: =+[1]PAM!S22 -> 131.1 | Q21: =+[1]PAM!T22 -> 160.8 | R21: =+SUMPRODUCT($C$3:$N$3,C21:N21) -> 136.62675 | S21: =+($C$3*$C21+$D$3*$D21+$E$3*$E21+$G$3*$G21+$K$3*$K21+$M$3*$M21+$N$3*$N21)/SUM($C$3:$E$3,$G$3,$K$3,$M$3:$N$3) -> 129.72971 | T21: =+($E$3*$E21+$G$3*$G21+$K$3*$K21+$M$3*$M21+$N$3*$N21)/SUM($E$3,$G$3,$K$3,$M$3:$N$3) -> 130.49322 | U21: =+($E$3*$E21+$G$3*$G21+$K$3*$K21+$N$3*$N21)/SUM($E$3,$G$3,$K$3,$N$3) -> 129.44005 | W21: =($E$3*$E21+SUMPRODUCT($G$3:$L$3,$G21:$L21)+$N$3*$N21)/SUM($E$3,$G$3:$L$3,$N$3) -> 134.98046 | Y21: =+B21/B20-1 -> 0.028614458 | Z21: =+C21/C20-1 -> 0.012608353 | AA21: =+D21/D20-1 -> 0.014626636 | AB21: =+E21/E20-1 -> 0.052674897 | AC21: =+F21/F20-1 -> 0.086238532 | AD21: =+G21/G20-1 -> 0.012638231 | AE21: =+H21/H20-1 -> 0.01988218 | AF21: =+I21/I20-1 -> 0.031507877 | ... AT21: =+W21/W20-1 -> 0.02604701 | AV21: =+B21/B9-1 -> 0.25666973 | AW21: =+C21/C9-1 -> 0.19423792 | AX21: =+D21/D9-1 -> 0.19492294 | AY21: =+E21/E9-1 -> 0.1864564 | AZ21: =+F21/F9-1 -> 0.53367876 | BA21: =+G21/G9-1 -> 0.24224806 | BB21: =+H21/H9-1 -> 0.26253418 | BC21: =+I21/I9-1 -> 0.29107981 | ... BQ21: =+W21/W9-1 -> 0.24785277 | BS21: =+A21 -> 43191 | BT21: =(C21-C20)/$B20*C$3 -> 0.0034518072 | BU21: =(D21-D20)/$B20*D$3 -> 0.0005436747 | BV21: =(E21-E20)/$B20*E$3 -> 0.005026506 | BW21: =(F21-F20)/$B20*F$3 -> 0.0092053464 | BX21: =(G21-G20)/$B20*G$3 -> 0.00076385542 | BY21: =(H21-H20)/$B20*H$3 -> 0.0016590361 | BZ21: =(I21-I20)/$B20*I$3 -> 0.0032923193 | CA21: =(J21-J20)/$B20*J$3 -> 0.00043072289 | ... CE21: =(N21-N20)/$B20*N$3 -> 0.00070090361 | CF21: =+SUM(BT21:CE21) -> 0.028560166
A22: =+[1]PAM!A23 -> 43221 | B22: =+[1]PAM!B23 -> 139.7 | C22: =+[1]PAM!C23 -> 132.3 | D22: =+[1]PAM!D23 -> 133.9 | E22: =+[1]PAM!E23 -> 130.9 | F22: =+[1]PAM!F23 -> 176 | G22: =+[1]PAM!G23 -> 130.8 | H22: =+[1]PAM!H23 -> 141.2 | ... N22: =+[1]PAM!N23 -> 132.7 | O22: =+[1]PAM!R23 -> 132 | P22: =+[1]PAM!S23 -> 134.9 | Q22: =+[1]PAM!T23 -> 161.4 | R22: =+SUMPRODUCT($C$3:$N$3,C22:N22) -> 139.66446 | S22: =+($C$3*$C22+$D$3*$D22+$E$3*$E22+$G$3*$G22+$K$3*$K22+$M$3*$M22+$N$3*$N22)/SUM($C$3:$E$3,$G$3,$K$3,$M$3:$N$3) -> 133.32153 | T22: =+($E$3*$E22+$G$3*$G22+$K$3*$K22+$M$3*$M22+$N$3*$N22)/SUM($E$3,$G$3,$K$3,$M$3:$N$3) -> 134.07679 | U22: =+($E$3*$E22+$G$3*$G22+$K$3*$K22+$N$3*$N22)/SUM($E$3,$G$3,$K$3,$N$3) -> 132.81442 | W22: =($E$3*$E22+SUMPRODUCT($G$3:$L$3,$G22:$L22)+$N$3*$N22)/SUM($E$3,$G$3:$L$3,$N$3) -> 138.24874 | Y22: =+B22/B21-1 -> 0.022693997 | Z22: =+C22/C21-1 -> 0.029571984 | AA22: =+D22/D21-1 -> 0.015933232 | AB22: =+E22/E21-1 -> 0.023455825 | AC22: =+F22/F21-1 -> -0.009009009 | AD22: =+G22/G21-1 -> 0.020280811 | AE22: =+H22/H21-1 -> 0.019494585 | AF22: =+I22/I21-1 -> 0.016 | ... AT22: =+W22/W21-1 -> 0.024212948 | AV22: =+B22/B10-1 -> 0.26654578 | AW22: =+C22/C10-1 -> 0.21153846 | AX22: =+D22/D10-1 -> 0.19660411 | AY22: =+E22/E10-1 -> 0.18034265 | AZ22: =+F22/F10-1 -> 0.50170648 | BA22: =+G22/G10-1 -> 0.23396226 | BB22: =+H22/H10-1 -> 0.26864331 | BC22: =+I22/I10-1 -> 0.30317164 | ... BQ22: =+W22/W10-1 -> 0.25981587 | BS22: =+A22 -> 43221 | BT22: =(C22-C21)/$B21*C$3 -> 0.0079699854 | BU22: =(D22-D21)/$B21*D$3 -> 0.00058418741 | BV22: =(E22-E21)/$B21*E$3 -> 0.0022906296 | BW22: =(F22-F21)/$B21*F$3 -> -0.0010155198 | BX22: =(G22-G21)/$B21*G$3 -> 0.001206735 | BY22: =(H22-H21)/$B21*H$3 -> 0.0016128843 | BZ22: =(I22-I21)/$B21*I$3 -> 0.0016765739 | CA22: =(J22-J21)/$B21*J$3 -> 0.0016540264 | ... CE22: =(N22-N21)/$B21*N$3 -> 0.0008124451 | CF22: =+SUM(BT22:CE22) -> 0.022237994
A23: =+[1]PAM!A24 -> 43252 | B23: =+[1]PAM!B24 -> 144.8 | C23: =+[1]PAM!C24 -> 140 | D23: =+[1]PAM!D24 -> 134.8 | E23: =+[1]PAM!E24 -> 133.5 | F23: =+[1]PAM!F24 -> 179 | G23: =+[1]PAM!G24 -> 136.3 | H23: =+[1]PAM!H24 -> 146.6 | ... N23: =+[1]PAM!N24 -> 137.1 | O23: =+[1]PAM!R24 -> 136.8 | P23: =+[1]PAM!S24 -> 140.3 | Q23: =+[1]PAM!T24 -> 165.8 | R23: =+SUMPRODUCT($C$3:$N$3,C23:N23) -> 144.83594 | S23: =+($C$3*$C23+$D$3*$D23+$E$3*$E23+$G$3*$G23+$K$3*$K23+$M$3*$M23+$N$3*$N23)/SUM($C$3:$E$3,$G$3,$K$3,$M$3:$N$3) -> 138.53888 | T23: =+($E$3*$E23+$G$3*$G23+$K$3*$K23+$M$3*$M23+$N$3*$N23)/SUM($E$3,$G$3,$K$3,$M$3:$N$3) -> 137.7673 | U23: =+($E$3*$E23+$G$3*$G23+$K$3*$K23+$N$3*$N23)/SUM($E$3,$G$3,$K$3,$N$3) -> 136.73576 | W23: =($E$3*$E23+SUMPRODUCT($G$3:$L$3,$G23:$L23)+$N$3*$N23)/SUM($E$3,$G$3:$L$3,$N$3) -> 143.04636 | Y23: =+B23/B22-1 -> 0.0365068 | Z23: =+C23/C22-1 -> 0.058201058 | AA23: =+D23/D22-1 -> 0.0067214339 | AB23: =+E23/E22-1 -> 0.01986249 | AC23: =+F23/F22-1 -> 0.017045455 | AD23: =+G23/G22-1 -> 0.04204893 | AE23: =+H23/H22-1 -> 0.038243626 | AF23: =+I23/I22-1 -> 0.058697208 | ... AT23: =+W23/W22-1 -> 0.034702791 | AV23: =+B23/B11-1 -> 0.29982047 | AW23: =+C23/C11-1 -> 0.27620784 | AX23: =+D23/D11-1 -> 0.19503546 | AY23: =+E23/E11-1 -> 0.19196429 | AZ23: =+F23/F11-1 -> 0.50927487 | BA23: =+G23/G11-1 -> 0.27027027 | BB23: =+H23/H11-1 -> 0.29619805 | BC23: =+I23/I11-1 -> 0.36944444 | ... BQ23: =+W23/W11-1 -> 0.28736889 | BS23: =+A23 -> 43252 | BT23: =(C23-C22)/$B22*C$3 -> 0.015791339 | BU23: =(D23-D22)/$B22*D$3 -> 0.00024481031 | BV23: =(E23-E22)/$B22*E$3 -> 0.0019411596 | BW23: =(F23-F22)/$B22*F$3 -> 0.0018618468 | BX23: =(G23-G22)/$B22*G$3 -> 0.002496063 | BY23: =(H23-H22)/$B22*H$3 -> 0.0031541875 | BZ23: =(I23-I22)/$B22*I$3 -> 0.0061103794 | CA23: =(J23-J22)/$B22*J$3 -> 0.00012283465 | ... CE23: =(N23-N22)/$B22*N$3 -> 0.0011275591 | CF23: =+SUM(BT23:CE23) -> 0.037018468
A24: =+[1]PAM!A25 -> 43282 | B24: =+[1]PAM!B25 -> 149.6 | C24: =+[1]PAM!C25 -> 145.6 | D24: =+[1]PAM!D25 -> 138.1 | E24: =+[1]PAM!E25 -> 133 | F24: =+[1]PAM!F25 -> 182.8 | G24: =+[1]PAM!G25 -> 141.9 | H24: =+[1]PAM!H25 -> 151.4 | ... N24: =+[1]PAM!N25 -> 142.3 | O24: =+[1]PAM!R25 -> 141.1 | P24: =+[1]PAM!S25 -> 145.1 | Q24: =+[1]PAM!T25 -> 171 | R24: =+SUMPRODUCT($C$3:$N$3,C24:N24) -> 149.62398 | S24: =+($C$3*$C24+$D$3*$D24+$E$3*$E24+$G$3*$G24+$K$3*$K24+$M$3*$M24+$N$3*$N24)/SUM($C$3:$E$3,$G$3,$K$3,$M$3:$N$3) -> 143.0895 | T24: =+($E$3*$E24+$G$3*$G24+$K$3*$K24+$M$3*$M24+$N$3*$N24)/SUM($E$3,$G$3,$K$3,$M$3:$N$3) -> 141.61166 | U24: =+($E$3*$E24+$G$3*$G24+$K$3*$K24+$N$3*$N24)/SUM($E$3,$G$3,$K$3,$N$3) -> 140.70988 | W24: =($E$3*$E24+SUMPRODUCT($G$3:$L$3,$G24:$L24)+$N$3*$N24)/SUM($E$3,$G$3:$L$3,$N$3) -> 147.87775 | Y24: =+B24/B23-1 -> 0.033149171 | Z24: =+C24/C23-1 -> 0.04 | AA24: =+D24/D23-1 -> 0.024480712 | AB24: =+E24/E23-1 -> -0.0037453184 | AC24: =+F24/F23-1 -> 0.02122905 | AD24: =+G24/G23-1 -> 0.04108584 | AE24: =+H24/H23-1 -> 0.032742156 | AF24: =+I24/I23-1 -> 0.058147397 | ... AT24: =+W24/W23-1 -> 0.033774997 | AV24: =+B24/B12-1 -> 0.31690141 | AW24: =+C24/C12-1 -> 0.31171171 | AX24: =+D24/D12-1 -> 0.19051724 | AY24: =+E24/E12-1 -> 0.19927863 | AZ24: =+F24/F12-1 -> 0.51701245 | BA24: =+G24/G12-1 -> 0.29 | BB24: =+H24/H12-1 -> 0.29180887 | BC24: =+I24/I12-1 -> 0.40864086 | ... BQ24: =+W24/W12-1 -> 0.30230106 | BS24: =+A24 -> 43282 | BT24: =(C24-C23)/$B23*C$3 -> 0.01108011 | BU24: =(D24-D23)/$B23*D$3 -> 0.0008660221 | BV24: =(E24-E23)/$B23*E$3 -> -0.00036015193 | BW24: =(F24-F23)/$B23*F$3 -> 0.0022752762 | BX24: =(G24-G23)/$B23*G$3 -> 0.0024519337 | BY24: =(H24-H23)/$B23*H$3 -> 0.0027049724 | BZ24: =(I24-I23)/$B23*I$3 -> 0.0061827348 | CA24: =(J24-J23)/$B23*J$3 -> 0.00019751381 | ... CE24: =(N24-N23)/$B23*N$3 -> 0.0012856354 | CF24: =+SUM(BT24:CE24) -> 0.033066575
A25: =+[1]PAM!A26 -> 43313 | B25: =+[1]PAM!B26 -> 155.2 | C25: =+[1]PAM!C26 -> 151.8 | D25: =+[1]PAM!D26 -> 140.4 | E25: =+[1]PAM!E26 -> 132.7 | F25: =+[1]PAM!F26 -> 188.7 | G25: =+[1]PAM!G26 -> 146.1 | H25: =+[1]PAM!H26 -> 156.6 | ... N25: =+[1]PAM!N26 -> 148.9 | O25: =+[1]PAM!R26 -> 143.4 | P25: =+[1]PAM!S26 -> 150.3 | Q25: =+[1]PAM!T26 -> 179.9 | R25: =+SUMPRODUCT($C$3:$N$3,C25:N25) -> 155.2363 | S25: =+($C$3*$C25+$D$3*$D25+$E$3*$E25+$G$3*$G25+$K$3*$K25+$M$3*$M25+$N$3*$N25)/SUM($C$3:$E$3,$G$3,$K$3,$M$3:$N$3) -> 147.94106 | T25: =+($E$3*$E25+$G$3*$G25+$K$3*$K25+$M$3*$M25+$N$3*$N25)/SUM($E$3,$G$3,$K$3,$M$3:$N$3) -> 145.65583 | U25: =+($E$3*$E25+$G$3*$G25+$K$3*$K25+$N$3*$N25)/SUM($E$3,$G$3,$K$3,$N$3) -> 144.91294 | W25: =($E$3*$E25+SUMPRODUCT($G$3:$L$3,$G25:$L25)+$N$3*$N25)/SUM($E$3,$G$3:$L$3,$N$3) -> 153.69419 | Y25: =+B25/B24-1 -> 0.037433155 | Z25: =+C25/C24-1 -> 0.042582418 | AA25: =+D25/D24-1 -> 0.016654598 | AB25: =+E25/E24-1 -> -0.0022556391 | AC25: =+F25/F24-1 -> 0.032275711 | AD25: =+G25/G24-1 -> 0.029598309 | AE25: =+H25/H24-1 -> 0.034346103 | AF25: =+I25/I24-1 -> 0.047923323 | ... AT25: =+W25/W24-1 -> 0.039332784 | AV25: =+B25/B13-1 -> 0.3483927 | AW25: =+C25/C13-1 -> 0.33744493 | AX25: =+D25/D13-1 -> 0.19795222 | AY25: =+E25/E13-1 -> 0.20417423 | AZ25: =+F25/F13-1 -> 0.54040816 | BA25: =+G25/G13-1 -> 0.31384892 | BB25: =+H25/H13-1 -> 0.30608841 | BC25: =+I25/I13-1 -> 0.460374 | ... BQ25: =+W25/W13-1 -> 0.34076534 | BS25: =+A25 -> 43313 | BT25: =(C25-C24)/$B24*C$3 -> 0.011873663 | BU25: =(D25-D24)/$B24*D$3 -> 0.0005842246 | BV25: =(E25-E24)/$B24*E$3 -> -0.00020915775 | BW25: =(F25-F24)/$B24*F$3 -> 0.0034193182 | BX25: =(G25-G24)/$B24*G$3 -> 0.0017799465 | BY25: =(H25-H24)/$B24*H$3 -> 0.0028363636 | BZ25: =(I25-I24)/$B24*I$3 -> 0.0052189171 | CA25: =(J25-J24)/$B24*J$3 -> 0.0035176471 | ... CE25: =(N25-N24)/$B24*N$3 -> 0.0015794118 | CF25: =+SUM(BT25:CE25) -> 0.037515508
A26: =+[1]PAM!A27 -> 43344 | B26: =+[1]PAM!B27 -> 165.1 | C26: =+[1]PAM!C27 -> 161.9 | D26: =+[1]PAM!D27 -> 146.7 | E26: =+[1]PAM!E27 -> 142.3 | F26: =+[1]PAM!F27 -> 195.2 | G26: =+[1]PAM!G27 -> 160.2 | H26: =+[1]PAM!H27 -> 163.7 | ... N26: =+[1]PAM!N27 -> 161.4 | O26: =+[1]PAM!R27 -> 147.1 | P26: =+[1]PAM!S27 -> 161.4 | Q26: =+[1]PAM!T27 -> 189.1 | R26: =+SUMPRODUCT($C$3:$N$3,C26:N26) -> 165.05789 | S26: =+($C$3*$C26+$D$3*$D26+$E$3*$E26+$G$3*$G26+$K$3*$K26+$M$3*$M26+$N$3*$N26)/SUM($C$3:$E$3,$G$3,$K$3,$M$3:$N$3) -> 157.69772 | T26: =+($E$3*$E26+$G$3*$G26+$K$3*$K26+$M$3*$M26+$N$3*$N26)/SUM($E$3,$G$3,$K$3,$M$3:$N$3) -> 155.50452 | U26: =+($E$3*$E26+$G$3*$G26+$K$3*$K26+$N$3*$N26)/SUM($E$3,$G$3,$K$3,$N$3) -> 155.62264 | W26: =($E$3*$E26+SUMPRODUCT($G$3:$L$3,$G26:$L26)+$N$3*$N26)/SUM($E$3,$G$3:$L$3,$N$3) -> 164.65538 | Y26: =+B26/B25-1 -> 0.06378866 | Z26: =+C26/C25-1 -> 0.066534914 | AA26: =+D26/D25-1 -> 0.044871795 | AB26: =+E26/E25-1 -> 0.072343632 | AC26: =+F26/F25-1 -> 0.034446211 | AD26: =+G26/G25-1 -> 0.09650924 | AE26: =+H26/H25-1 -> 0.045338442 | AF26: =+I26/I25-1 -> 0.10609756 | ... AT26: =+W26/W25-1 -> 0.071318151 | AV26: =+B26/B14-1 -> 0.40750213 | AW26: =+C26/C14-1 -> 0.40538194 | AX26: =+D26/D14-1 -> 0.24322034 | AY26: =+E26/E14-1 -> 0.25929204 | AZ26: =+F26/F14-1 -> 0.52858262 | BA26: =+G26/G14-1 -> 0.424 | BB26: =+H26/H14-1 -> 0.33414833 | BC26: =+I26/I14-1 -> 0.60530973 | ... BQ26: =+W26/W14-1 -> 0.41028731 | BS26: =+A26 -> 43344 | BT26: =(C26-C25)/$B25*C$3 -> 0.018644652 | BU26: =(D26-D25)/$B25*D$3 -> 0.0015425258 | BV26: =(E26-E25)/$B25*E$3 -> 0.0064515464 | BW26: =(F26-F25)/$B25*F$3 -> 0.0036311211 | BX26: =(G26-G25)/$B25*G$3 -> 0.0057599227 | BY26: =(H26-H25)/$B25*H$3 -> 0.0037329897 | BZ26: =(I26-I25)/$B25*I$3 -> 0.011671005 | CA26: =(J26-J25)/$B25*J$3 -> 0.0010688144 | ... CE26: =(N26-N25)/$B25*N$3 -> 0.0028833763 | CF26: =+SUM(BT26:CE26) -> 0.063283441
A27: =+[1]PAM!A28 -> 43374 | B27: =+[1]PAM!B28 -> 174.6 | C27: =+[1]PAM!C28 -> 171.3 | D27: =+[1]PAM!D28 -> 150 | E27: =+[1]PAM!E28 -> 149.9 | F27: =+[1]PAM!F28 -> 218 | G27: =+[1]PAM!G28 -> 167 | H27: =+[1]PAM!H28 -> 172.7 | ... N27: =+[1]PAM!N28 -> 172 | O27: =+[1]PAM!R28 -> 156.7 | P27: =+[1]PAM!S28 -> 168.9 | Q27: =+[1]PAM!T28 -> 206 | R27: =+SUMPRODUCT($C$3:$N$3,C27:N27) -> 174.63668 | S27: =+($C$3*$C27+$D$3*$D27+$E$3*$E27+$G$3*$G27+$K$3*$K27+$M$3*$M27+$N$3*$N27)/SUM($C$3:$E$3,$G$3,$K$3,$M$3:$N$3) -> 165.36054 | T27: =+($E$3*$E27+$G$3*$G27+$K$3*$K27+$M$3*$M27+$N$3*$N27)/SUM($E$3,$G$3,$K$3,$M$3:$N$3) -> 162.24124 | U27: =+($E$3*$E27+$G$3*$G27+$K$3*$K27+$N$3*$N27)/SUM($E$3,$G$3,$K$3,$N$3) -> 162.57448 | W27: =($E$3*$E27+SUMPRODUCT($G$3:$L$3,$G27:$L27)+$N$3*$N27)/SUM($E$3,$G$3:$L$3,$N$3) -> 173.11841 | Y27: =+B27/B26-1 -> 0.057540884 | Z27: =+C27/C26-1 -> 0.058060531 | AA27: =+D27/D26-1 -> 0.022494888 | AB27: =+E27/E26-1 -> 0.053408292 | AC27: =+F27/F26-1 -> 0.11680328 | AD27: =+G27/G26-1 -> 0.042446941 | AE27: =+H27/H26-1 -> 0.054978619 | AF27: =+I27/I26-1 -> 0.081036384 | ... AT27: =+W27/W26-1 -> 0.051398483 | AV27: =+B27/B15-1 -> 0.4635373 | AW27: =+C27/C15-1 -> 0.46786632 | AX27: =+D27/D15-1 -> 0.2345679 | AY27: =+E27/E15-1 -> 0.288908 | AZ27: =+F27/F15-1 -> 0.68861348 | BA27: =+G27/G15-1 -> 0.47526502 | BB27: =+H27/H15-1 -> 0.38938053 | BC27: =+I27/I15-1 -> 0.70670148 | ... BQ27: =+W27/W15-1 -> 0.45407996 | BS27: =+A27 -> 43374 | BT27: =(C27-C26)/$B26*C$3 -> 0.016311932 | BU27: =(D27-D26)/$B26*D$3 -> 0.00075953967 | BV27: =(E27-E26)/$B26*E$3 -> 0.0048012114 | BW27: =(F27-F26)/$B26*F$3 -> 0.011973107 | BX27: =(G27-G26)/$B26*G$3 -> 0.0026112659 | BY27: =(H27-H26)/$B26*H$3 -> 0.0044482132 | BZ27: =(I27-I26)/$B26*I$3 -> 0.0092687462 | CA27: =(J27-J26)/$B26*J$3 -> 0.0003984252 | ... CE27: =(N27-N26)/$B26*N$3 -> 0.0022984858 | CF27: =+SUM(BT27:CE27) -> 0.05801811
A28: =+[1]PAM!A29 -> 43405 | B28: =+[1]PAM!B29 -> 180.4 | C28: =+[1]PAM!C29 -> 177.6 | D28: =+[1]PAM!D29 -> 156.3 | E28: =+[1]PAM!E29 -> 153.9 | F28: =+[1]PAM!F29 -> 224.9 | G28: =+[1]PAM!G29 -> 172.4 | H28: =+[1]PAM!H29 -> 184.6 | ... N28: =+[1]PAM!N29 -> 180 | O28: =+[1]PAM!R29 -> 164.2 | P28: =+[1]PAM!S29 -> 174.3 | Q28: =+[1]PAM!T29 -> 211.8 | R28: =+SUMPRODUCT($C$3:$N$3,C28:N28) -> 180.34785 | S28: =+($C$3*$C28+$D$3*$D28+$E$3*$E28+$G$3*$G28+$K$3*$K28+$M$3*$M28+$N$3*$N28)/SUM($C$3:$E$3,$G$3,$K$3,$M$3:$N$3) -> 170.55608 | T28: =+($E$3*$E28+$G$3*$G28+$K$3*$K28+$M$3*$M28+$N$3*$N28)/SUM($E$3,$G$3,$K$3,$M$3:$N$3) -> 166.4368 | U28: =+($E$3*$E28+$G$3*$G28+$K$3*$K28+$N$3*$N28)/SUM($E$3,$G$3,$K$3,$N$3) -> 166.79795 | W28: =($E$3*$E28+SUMPRODUCT($G$3:$L$3,$G28:$L28)+$N$3*$N28)/SUM($E$3,$G$3:$L$3,$N$3) -> 178.50733 | Y28: =+B28/B27-1 -> 0.033218786 | Z28: =+C28/C27-1 -> 0.036777583 | AA28: =+D28/D27-1 -> 0.042 | AB28: =+E28/E27-1 -> 0.026684456 | AC28: =+F28/F27-1 -> 0.031651376 | AD28: =+G28/G27-1 -> 0.032335329 | AE28: =+H28/H27-1 -> 0.068905617 | AF28: =+I28/I27-1 -> 0.023967364 | ... AT28: =+W28/W27-1 -> 0.031128479 | AV28: =+B28/B16-1 -> 0.48844884 | AW28: =+C28/C16-1 -> 0.50126796 | AX28: =+D28/D16-1 -> 0.27176566 | AY28: =+E28/E16-1 -> 0.30203046 | AZ28: =+F28/F16-1 -> 0.71810542 | BA28: =+G28/G16-1 -> 0.50567686 | BB28: =+H28/H16-1 -> 0.46391753 | BC28: =+I28/I16-1 -> 0.68881413 | ... BQ28: =+W28/W16-1 -> 0.47373283 | BS28: =+A28 -> 43405 | BT28: =(C28-C27)/$B27*C$3 -> 0.010337629 | BU28: =(D28-D27)/$B27*D$3 -> 0.001371134 | BV28: =(E28-E27)/$B27*E$3 -> 0.0023894616 | BW28: =(F28-F27)/$B27*F$3 -> 0.0034262887 | BX28: =(G28-G27)/$B27*G$3 -> 0.0019608247 | BY28: =(H28-H27)/$B27*H$3 -> 0.005561512 | BZ28: =(I28-I27)/$B27*I$3 -> 0.0028022337 | CA28: =(J28-J27)/$B27*J$3 -> 0.00044226804 | ... CE28: =(N28-N27)/$B27*N$3 -> 0.0016403207 | CF28: =+SUM(BT28:CE28) -> 0.032710023
... A118: =+[1]PAM!A119 -> 46143 | B118: =+[1]PAM!B119 -> 11556.9 | C118: =+[1]PAM!C119 -> 12553.9 | D118: =+[1]PAM!D119 -> 8047.9 | E118: =+[1]PAM!E119 -> 8204 | F118: =+[1]PAM!F119 -> 12040 | G118: =+[1]PAM!G119 -> 9358.3 | H118: =+[1]PAM!H119 -> 13344.2 | ... N118: =+[1]PAM!N119 -> 10804.5 | O118: =+[1]PAM!R119 -> 9404.7 | P118: =+[1]PAM!S119 -> 11938.7 | Q118: =+[1]PAM!T119 -> 11533.2 | R118: =+SUMPRODUCT($C$3:$N$3,C118:N118) -> 11556.663 | S118: =+($C$3*$C118+$D$3*$D118+$E$3*$E118+$G$3*$G118+$K$3*$K118+$M$3*$M118+$N$3*$N118)/SUM($C$3:$E$3,$G$3,$K$3,$M$3:$N$3) -> 11201.853 | T118: =+($E$3*$E118+$G$3*$G118+$K$3*$K118+$M$3*$M118+$N$3*$N118)/SUM($E$3,$G$3,$K$3,$M$3:$N$3) -> 10455.45 | U118: =+($E$3*$E118+$G$3*$G118+$K$3*$K118+$N$3*$N118)/SUM($E$3,$G$3,$K$3,$N$3) -> 9312.1203 | W118: =($E$3*$E118+SUMPRODUCT($G$3:$L$3,$G118:$L118)+$N$3*$N118)/SUM($E$3,$G$3:$L$3,$N$3) -> 10725.151 | Y118: =+B118/B117-1 -> 0.01999947 | Z118: =+C118/C117-1 -> 0.022754306 | AA118: =+D118/D117-1 -> 0.0075744297 | AB118: =+E118/E117-1 -> 0.007565337 | AC118: =+F118/F117-1 -> 0.024131742 | AD118: =+G118/G117-1 -> 0.016344838 | AE118: =+H118/H117-1 -> 0.024719136 | AF118: =+I118/I117-1 -> 0.017895433 | ... AT118: =+W118/W117-1 -> 0.019516046 | AV118: =+B118/B106-1 -> 0.32443645 | AW118: =+C118/C106-1 -> 0.33377602 | AX118: =+D118/D106-1 -> 0.23690156 | AY118: =+E118/E106-1 -> 0.10329617 | AZ118: =+F118/F106-1 -> 0.48693375 | BA118: =+G118/G106-1 -> 0.22765614 | BB118: =+H118/H106-1 -> 0.29916078 | BC118: =+I118/I106-1 -> 0.39726907 | ... BQ118: =+W118/W106-1 -> 0.28339168 | BS118: =+A118 -> 46143 | BT118: =(C118-C117)/$B117*C$3 -> 0.0070624299 | BU118: =(D118-D117)/$B117*D$3 -> 0.00020290725 | BV118: =(E118-E117)/$B117*E$3 -> 0.00056705295 | BW118: =(F118-F117)/$B117*F$3 -> 0.002170886 | BX118: =(G118-G117)/$B117*G$3 -> 0.0008421401 | BY118: =(H118-H117)/$B117*H$3 -> 0.0023183005 | BZ118: =(I118-I117)/$B117*I$3 -> 0.0020396812 | CA118: =(J118-J117)/$B117*J$3 -> 0.000746155 | ... CE118: =(N118-N117)/$B117*N$3 -> 0.00075200127 | CF118: =+SUM(BT118:CE118) -> 0.019996612

Sheet NOA
B1: Índices | Y1: Tasas de inflación mensual | AV1: Tasas de inflación interanual | BS1: Incidencia mensual | CH1: Incidencia Feb 21 - Jun 24
R2: =+SUM(C3:N3) -> 1 | S2: =+SUM($C$3:$E$3,$G$3,$K$3,$M$3:$N$3) -> 0.7363 | T2: =+SUM($E$3,$G$3,$K$3,$M$3:$N$3) -> 0.3583 | U2: =+SUM($E$3,$G$3,$K$3,$N$3) -> 0.2784 | W2: =+SUM(E3,G3:L3,N3) -> 0.4721 | AT2: =+SUM(AB3,AD3:AI3,AK3) -> 0.4721 | BL2: =+SUM(AW3:BH3) -> 1 | BQ2: =+SUM(AY3,BA3:BF3,BH3) -> 0.4721
C3: =+[1]NOA!C3 -> 0.3467 | D3: =+[1]NOA!D3 -> 0.0313 | E3: =+[1]NOA!E3 -> 0.1237 | F3: =+[1]NOA!F3 -> 0.07 | G3: =+[1]NOA!G3 -> 0.0612 | H3: =+[1]NOA!H3 -> 0.0633 | I3: =+[1]NOA!I3 -> 0.0841 | J3: =+[1]NOA!J3 -> 0.0259 | ... N3: =+[1]NOA!N3 -> 0.034 | R3: headline | V3: no food & energy | W3: no food & energy & shelter | Z3: =+C3 -> 0.3467 | AA3: =+D3 -> 0.0313 | AB3: =+E3 -> 0.1237 | AC3: =+F3 -> 0.07 | AD3: =+G3 -> 0.0612 | AE3: =+H3 -> 0.0633 | AF3: =+I3 -> 0.0841 | AG3: =+J3 -> 0.0259 | ... AK3: =+N3 -> 0.034 | AO3: headline | AS3: no food & energy | AT3: no food & energy & shelter | AW3: =+Z3 -> 0.3467 | AX3: =+AA3 -> 0.0313 | AY3: =+AB3 -> 0.1237 | AZ3: =+AC3 -> 0.07 | BA3: =+AD3 -> 0.0612 | BB3: =+AE3 -> 0.0633 | BC3: =+AF3 -> 0.0841 | BD3: =+AG3 -> 0.0259 | ... BH3: =+AK3 -> 0.034 | BL3: headline | BP3: no food & energy | BQ3: no food & energy & shelter | BT3: =+AW3 -> 0.3467 | BU3: =+AX3 -> 0.0313 | BV3: =+AY3 -> 0.1237 | BW3: =+AZ3 -> 0.07 | BX3: =+BA3 -> 0.0612 | BY3: =+BB3 -> 0.0633 | BZ3: =+BC3 -> 0.0841 | CA3: =+BD3 -> 0.0259 | ... CE3: =+BH3 -> 0.034 | CH3: 1 | CI3: =+BT3 -> 0.3467 | CJ3: =+BU3 -> 0.0313 | CK3: =+BV3 -> 0.1237 | CL3: =+BW3 -> 0.07 | CM3: =+BX3 -> 0.0612 | CN3: =+BY3 -> 0.0633 | CO3: =+BZ3 -> 0.0841 | CP3: =+CA3 -> 0.0259 | ... CT3: =+CE3 -> 0.034
A4: Fecha | B4: Nivel general | C4: Alimentos y bebidas no alcohólicas | D4: Bebidas alcohólicas y tabaco | E4: Prendas de vestir y calzado | F4: Vivienda, agua, electricidad, gas y otros combustibles | G4: EquiNOAiento y mantenimiento del hogar | H4: Salud | I4: Transporte | J4: Comunicación | K4: Recreación y cultura | L4: Educación | M4: Restaurantes y hoteles | N4: Bienes y servicios varios | O4: Estacional | P4: Núcleo | Q4: Regulados | R4: Nivel General | S4: Subyacente | T4: Subyacente-AyB | U4: Subyacente-Food | V4: Core | W4: Supercore | Y4: Nivel general | Z4: Alimentos y bebidas no alcohólicas | AA4: Bebidas alcohólicas y tabaco | AB4: Prendas de vestir y calzado | AC4: Vivienda, agua, electricidad, gas y otros combustibles | AD4: EquiNOAiento y mantenimiento del hogar | AE4: Salud | AF4: Transporte | AG4: Comunicación | AH4: Recreación y cultura | AI4: Educación | AJ4: Restaurantes y hoteles | AK4: Bienes y servicios varios | AL4: Estacional | AM4: Núcleo | AN4: Regulados | AO4: =+R4 -> Nivel General | AP4: =+S4 -> Subyacente | AQ4: =+T4 -> Subyacente-AyB | AR4: =+U4 -> Subyacente-Food | AS4: Core | AT4: Supercore | AV4: Nivel general | AW4: Alimentos y bebidas no alcohólicas | AX4: Bebidas alcohólicas y tabaco | AY4: Prendas de vestir y calzado | AZ4: Vivienda, agua, electricidad, gas y otros combustibles | BA4: EquiNOAiento y mantenimiento del hogar | BB4: Salud | BC4: Transporte | BD4: Comunicación | BE4: Recreación y cultura | BF4: Educación | BG4: Restaurantes y hoteles | BH4: Bienes y servicios varios | BI4: Estacional | BJ4: Núcleo | BK4: Regulados | BL4: =+AO4 -> Nivel General | BM4: =+AP4 -> Subyacente | BN4: =+AQ4 -> Subyacente-AyB | BO4: =+AR4 -> Subyacente-Food | BP4: Core | BQ4: Supercore | BS4: Fecha | BT4: Alimentos y bebidas no alcohólicas | BU4: Bebidas alcohólicas y tabaco | BV4: Prendas de vestir y calzado | BW4: Vivienda, agua, electricidad, gas y otros combustibles | BX4: Equipamiento y mantenimiento del hogar | BY4: Salud | BZ4: Transporte | CA4: Comunicación | CB4: Recreación y cultura | CC4: Educación | CD4: Restaurantes y hoteles | CE4: Bienes y servicios varios | CF4: Nivel general | CH4: Fecha | CI4: Alimentos y bebidas no alcohólicas | CJ4: Bebidas alcohólicas y tabaco | CK4: Prendas de vestir y calzado | CL4: Vivienda, agua, electricidad, gas y otros combustibles | CM4: Equipamiento y mantenimiento del hogar | CN4: Salud | CO4: Transporte | CP4: Comunicación | CQ4: Recreación y cultura | CR4: Educación | CS4: Restaurantes y hoteles | CT4: Bienes y servicios varios | CU4: Nivel general
A5: =+[1]NOA!A6 -> 42705 | B5: =+[1]NOA!B6 -> 100 | C5: =+[1]NOA!C6 -> 100 | D5: =+[1]NOA!D6 -> 100 | E5: =+[1]NOA!E6 -> 100 | F5: =+[1]NOA!F6 -> 100 | G5: =+[1]NOA!G6 -> 100 | H5: =+[1]NOA!H6 -> 100 | ... N5: =+[1]NOA!N6 -> 100 | O5: =+[1]NOA!R6 -> 100 | P5: =+[1]NOA!S6 -> 100 | Q5: =+[1]NOA!T6 -> 100 | R5: =+SUMPRODUCT($C$3:$N$3,C5:N5) -> 100 | S5: =+($C$3*$C5+$D$3*$D5+$E$3*$E5+$G$3*$G5+$K$3*$K5+$M$3*$M5+$N$3*$N5)/SUM($C$3:$E$3,$G$3,$K$3,$M$3:$N$3) -> 100 | T5: =+($E$3*$E5+$G$3*$G5+$K$3*$K5+$M$3*$M5+$N$3*$N5)/SUM($E$3,$G$3,$K$3,$M$3:$N$3) -> 100 | U5: =+($E$3*$E5+$G$3*$G5+$K$3*$K5+$N$3*$N5)/SUM($E$3,$G$3,$K$3,$N$3) -> 100 | W5: =($E$3*$E5+SUMPRODUCT($G$3:$L$3,$G5:$L5)+$N$3*$N5)/SUM($E$3,$G$3:$L$3,$N$3) -> 100 | BS5: =+A5 -> 42705
A6: =+[1]NOA!A7 -> 42736 | B6: =+[1]NOA!B7 -> 101.6 | C6: =+[1]NOA!C7 -> 101 | D6: =+[1]NOA!D7 -> 101.3 | E6: =+[1]NOA!E7 -> 100.5 | F6: =+[1]NOA!F7 -> 101.6 | G6: =+[1]NOA!G7 -> 100.4 | H6: =+[1]NOA!H7 -> 102.7 | ... N6: =+[1]NOA!N7 -> 102 | O6: =+[1]NOA!R7 -> 101.6 | P6: =+[1]NOA!S7 -> 101.4 | Q6: =+[1]NOA!T7 -> 102.3 | R6: =+SUMPRODUCT($C$3:$N$3,C6:N6) -> 101.58696 | S6: =+($C$3*$C6+$D$3*$D6+$E$3*$E6+$G$3*$G6+$K$3*$K6+$M$3*$M6+$N$3*$N6)/SUM($C$3:$E$3,$G$3,$K$3,$M$3:$N$3) -> 101.28177 | T6: =+($E$3*$E6+$G$3*$G6+$K$3*$K6+$M$3*$M6+$N$3*$N6)/SUM($E$3,$G$3,$K$3,$M$3:$N$3) -> 101.55283 | U6: =+($E$3*$E6+$G$3*$G6+$K$3*$K6+$N$3*$N6)/SUM($E$3,$G$3,$K$3,$N$3) -> 101.281 | W6: =($E$3*$E6+SUMPRODUCT($G$3:$L$3,$G6:$L6)+$N$3*$N6)/SUM($E$3,$G$3:$L$3,$N$3) -> 101.88058 | Y6: =+B6/B5-1 -> 0.016 | Z6: =+C6/C5-1 -> 0.01 | AA6: =+D6/D5-1 -> 0.013 | AB6: =+E6/E5-1 -> 0.005 | AC6: =+F6/F5-1 -> 0.016 | AD6: =+G6/G5-1 -> 0.004 | AE6: =+H6/H5-1 -> 0.027 | AF6: =+I6/I5-1 -> 0.029 | ... AT6: =+W6/W5-1 -> 0.018805761 | BS6: =+A6 -> 42736 | BT6: =(C6-C5)/$B5*C$3 -> 0.003467 | BU6: =(D6-D5)/$B5*D$3 -> 0.0004069 | BV6: =(E6-E5)/$B5*E$3 -> 0.0006185 | BW6: =(F6-F5)/$B5*F$3 -> 0.00112 | BX6: =(G6-G5)/$B5*G$3 -> 0.0002448 | BY6: =(H6-H5)/$B5*H$3 -> 0.0017091 | BZ6: =(I6-I5)/$B5*I$3 -> 0.0024389 | CA6: =(J6-J5)/$B5*J$3 -> 0.0010619 | ... CE6: =(N6-N5)/$B5*N$3 -> 0.00068 | CF6: =+SUM(BT6:CE6) -> 0.0158696 | CH6: =+CH$3*(B$95-B$55)/$B$55 -> 13.8495 | CI6: =+CI$3*(C$95-C$55)/$B$55 -> 5.2391298 | CJ6: =+CJ$3*(D$95-D$55)/$B$55 -> 0.32339693 | CK6: =+CK$3*(E$95-E$55)/$B$55 -> 1.3710587 | CL6: =+CL$3*(F$95-F$55)/$B$55 -> 0.96140498 | CM6: =+CM$3*(G$95-G$55)/$B$55 -> 0.79137195 | CN6: =+CN$3*(H$95-H$55)/$B$55 -> 1.0322361 | CO6: =+CO$3*(I$95-I$55)/$B$55 -> 1.2381617 | ... CT6: =+CT$3*(N$95-N$55)/$B$55 -> 0.4834422
A7: =+[1]NOA!A8 -> 42767 | B7: =+[1]NOA!B8 -> 103.7 | C7: =+[1]NOA!C8 -> 103.9 | D7: =+[1]NOA!D8 -> 105.5 | E7: =+[1]NOA!E8 -> 100.4 | F7: =+[1]NOA!F8 -> 107.7 | G7: =+[1]NOA!G8 -> 100.7 | H7: =+[1]NOA!H8 -> 104.1 | ... N7: =+[1]NOA!N8 -> 103.5 | O7: =+[1]NOA!R8 -> 103.6 | P7: =+[1]NOA!S8 -> 103 | Q7: =+[1]NOA!T8 -> 106.7 | R7: =+SUMPRODUCT($C$3:$N$3,C7:N7) -> 103.72805 | S7: =+($C$3*$C7+$D$3*$D7+$E$3*$E7+$G$3*$G7+$K$3*$K7+$M$3*$M7+$N$3*$N7)/SUM($C$3:$E$3,$G$3,$K$3,$M$3:$N$3) -> 103.00898 | T7: =+($E$3*$E7+$G$3*$G7+$K$3*$K7+$M$3*$M7+$N$3*$N7)/SUM($E$3,$G$3,$K$3,$M$3:$N$3) -> 101.92919 | U7: =+($E$3*$E7+$G$3*$G7+$K$3*$K7+$N$3*$N7)/SUM($E$3,$G$3,$K$3,$N$3) -> 101.50708 | W7: =($E$3*$E7+SUMPRODUCT($G$3:$L$3,$G7:$L7)+$N$3*$N7)/SUM($E$3,$G$3:$L$3,$N$3) -> 102.95088 | Y7: =+B7/B6-1 -> 0.020669291 | Z7: =+C7/C6-1 -> 0.028712871 | AA7: =+D7/D6-1 -> 0.041461007 | AB7: =+E7/E6-1 -> -0.00099502488 | AC7: =+F7/F6-1 -> 0.06003937 | AD7: =+G7/G6-1 -> 0.0029880478 | AE7: =+H7/H6-1 -> 0.013631938 | AF7: =+I7/I6-1 -> 0.026239067 | ... AT7: =+W7/W6-1 -> 0.010505466 | BS7: =+A7 -> 42767 | BT7: =(C7-C6)/$B6*C$3 -> 0.0098959646 | BU7: =(D7-D6)/$B6*D$3 -> 0.0012938976 | BV7: =(E7-E6)/$B6*E$3 -> -0.00012175197 | BW7: =(F7-F6)/$B6*F$3 -> 0.0042027559 | BX7: =(G7-G6)/$B6*G$3 -> 0.00018070866 | BY7: =(H7-H6)/$B6*H$3 -> 0.00087224409 | BZ7: =(I7-I6)/$B6*I$3 -> 0.0022349409 | CA7: =(J7-J6)/$B6*J$3 -> 0.00076476378 | ... CE7: =(N7-N6)/$B6*N$3 -> 0.0005019685 | CF7: =+SUM(BT7:CE7) -> 0.02107372
A8: =+[1]NOA!A9 -> 42795 | B8: =+[1]NOA!B9 -> 107.1 | C8: =+[1]NOA!C9 -> 106 | D8: =+[1]NOA!D9 -> 107.1 | E8: =+[1]NOA!E9 -> 102.2 | F8: =+[1]NOA!F9 -> 121.4 | G8: =+[1]NOA!G9 -> 102 | H8: =+[1]NOA!H9 -> 107 | ... N8: =+[1]NOA!N9 -> 105.7 | O8: =+[1]NOA!R9 -> 104.3 | P8: =+[1]NOA!S9 -> 105.3 | Q8: =+[1]NOA!T9 -> 116 | R8: =+SUMPRODUCT($C$3:$N$3,C8:N8) -> 107.04326 | S8: =+($C$3*$C8+$D$3*$D8+$E$3*$E8+$G$3*$G8+$K$3*$K8+$M$3*$M8+$N$3*$N8)/SUM($C$3:$E$3,$G$3,$K$3,$M$3:$N$3) -> 104.88078 | T8: =+($E$3*$E8+$G$3*$G8+$K$3*$K8+$M$3*$M8+$N$3*$N8)/SUM($E$3,$G$3,$K$3,$M$3:$N$3) -> 103.60394 | U8: =+($E$3*$E8+$G$3*$G8+$K$3*$K8+$N$3*$N8)/SUM($E$3,$G$3,$K$3,$N$3) -> 103.20327 | W8: =($E$3*$E8+SUMPRODUCT($G$3:$L$3,$G8:$L8)+$N$3*$N8)/SUM($E$3,$G$3:$L$3,$N$3) -> 106.02273 | Y8: =+B8/B7-1 -> 0.032786885 | Z8: =+C8/C7-1 -> 0.020211742 | AA8: =+D8/D7-1 -> 0.015165877 | AB8: =+E8/E7-1 -> 0.017928287 | AC8: =+F8/F7-1 -> 0.1272052 | AD8: =+G8/G7-1 -> 0.012909633 | AE8: =+H8/H7-1 -> 0.027857829 | AF8: =+I8/I7-1 -> 0.0075757576 | ... AT8: =+W8/W7-1 -> 0.029838008 | BS8: =+A8 -> 42795 | BT8: =(C8-C7)/$B7*C$3 -> 0.0070209257 | BU8: =(D8-D7)/$B7*D$3 -> 0.00048293153 | BV8: =(E8-E7)/$B7*E$3 -> 0.0021471553 | BW8: =(F8-F7)/$B7*F$3 -> 0.0092478303 | BX8: =(G8-G7)/$B7*G$3 -> 0.00076721311 | BY8: =(H8-H7)/$B7*H$3 -> 0.0017702025 | BZ8: =(I8-I7)/$B7*I$3 -> 0.0006487946 | CA8: =(J8-J7)/$B7*J$3 -> 0.0015235294 | ... CE8: =(N8-N7)/$B7*N$3 -> 0.00072131148 | CF8: =+SUM(BT8:CE8) -> 0.031969238
A9: =+[1]NOA!A10 -> 42826 | B9: =+[1]NOA!B10 -> 110 | C9: =+[1]NOA!C10 -> 108.4 | D9: =+[1]NOA!D10 -> 109.3 | E9: =+[1]NOA!E10 -> 105.9 | F9: =+[1]NOA!F10 -> 131.8 | G9: =+[1]NOA!G10 -> 103.1 | H9: =+[1]NOA!H10 -> 109.2 | ... N9: =+[1]NOA!N10 -> 106.9 | O9: =+[1]NOA!R10 -> 107.8 | P9: =+[1]NOA!S10 -> 107.5 | Q9: =+[1]NOA!T10 -> 121.2 | R9: =+SUMPRODUCT($C$3:$N$3,C9:N9) -> 109.97286 | S9: =+($C$3*$C9+$D$3*$D9+$E$3*$E9+$G$3*$G9+$K$3*$K9+$M$3*$M9+$N$3*$N9)/SUM($C$3:$E$3,$G$3,$K$3,$M$3:$N$3) -> 107.32168 | T9: =+($E$3*$E9+$G$3*$G9+$K$3*$K9+$M$3*$M9+$N$3*$N9)/SUM($E$3,$G$3,$K$3,$M$3:$N$3) -> 106.10544 | U9: =+($E$3*$E9+$G$3*$G9+$K$3*$K9+$N$3*$N9)/SUM($E$3,$G$3,$K$3,$N$3) -> 105.79131 | W9: =($E$3*$E9+SUMPRODUCT($G$3:$L$3,$G9:$L9)+$N$3*$N9)/SUM($E$3,$G$3:$L$3,$N$3) -> 108.40544 | Y9: =+B9/B8-1 -> 0.027077498 | Z9: =+C9/C8-1 -> 0.022641509 | AA9: =+D9/D8-1 -> 0.02054155 | AB9: =+E9/E8-1 -> 0.036203523 | AC9: =+F9/F8-1 -> 0.085667216 | AD9: =+G9/G8-1 -> 0.010784314 | AE9: =+H9/H8-1 -> 0.020560748 | AF9: =+I9/I8-1 -> 0.0056390977 | ... AT9: =+W9/W8-1 -> 0.02247363 | BS9: =+A9 -> 42826 | BT9: =(C9-C8)/$B8*C$3 -> 0.0077691877 | BU9: =(D9-D8)/$B8*D$3 -> 0.00064295051 | BV9: =(E9-E8)/$B8*E$3 -> 0.0042734827 | BW9: =(F9-F8)/$B8*F$3 -> 0.0067973856 | BX9: =(G9-G8)/$B8*G$3 -> 0.00062857143 | BY9: =(H9-H8)/$B8*H$3 -> 0.0013002801 | BZ9: =(I9-I8)/$B8*I$3 -> 0.00047114846 | CA9: =(J9-J8)/$B8*J$3 -> 0.0018137255 | ... CE9: =(N9-N8)/$B8*N$3 -> 0.00038095238 | CF9: =+SUM(BT9:CE9) -> 0.027353875
A10: =+[1]NOA!A11 -> 42856 | B10: =+[1]NOA!B11 -> 111.6 | C10: =+[1]NOA!C11 -> 109.6 | D10: =+[1]NOA!D11 -> 111.3 | E10: =+[1]NOA!E11 -> 107.8 | F10: =+[1]NOA!F11 -> 135.6 | G10: =+[1]NOA!G11 -> 106.1 | H10: =+[1]NOA!H11 -> 110.9 | ... N10: =+[1]NOA!N11 -> 108.2 | O10: =+[1]NOA!R11 -> 109.2 | P10: =+[1]NOA!S11 -> 109.1 | Q10: =+[1]NOA!T11 -> 123.2 | R10: =+SUMPRODUCT($C$3:$N$3,C10:N10) -> 111.63374 | S10: =+($C$3*$C10+$D$3*$D10+$E$3*$E10+$G$3*$G10+$K$3*$K10+$M$3*$M10+$N$3*$N10)/SUM($C$3:$E$3,$G$3,$K$3,$M$3:$N$3) -> 108.89263 | T10: =+($E$3*$E10+$G$3*$G10+$K$3*$K10+$M$3*$M10+$N$3*$N10)/SUM($E$3,$G$3,$K$3,$M$3:$N$3) -> 107.99785 | U10: =+($E$3*$E10+$G$3*$G10+$K$3*$K10+$N$3*$N10)/SUM($E$3,$G$3,$K$3,$N$3) -> 107.71024 | W10: =($E$3*$E10+SUMPRODUCT($G$3:$L$3,$G10:$L10)+$N$3*$N10)/SUM($E$3,$G$3:$L$3,$N$3) -> 110.04158 | Y10: =+B10/B9-1 -> 0.014545455 | Z10: =+C10/C9-1 -> 0.011070111 | AA10: =+D10/D9-1 -> 0.018298262 | AB10: =+E10/E9-1 -> 0.017941454 | AC10: =+F10/F9-1 -> 0.028831563 | AD10: =+G10/G9-1 -> 0.029097963 | AE10: =+H10/H9-1 -> 0.015567766 | AF10: =+I10/I9-1 -> 0.011214953 | ... AT10: =+W10/W9-1 -> 0.015092751 | BS10: =+A10 -> 42856 | BT10: =(C10-C9)/$B9*C$3 -> 0.0037821818 | BU10: =(D10-D9)/$B9*D$3 -> 0.00056909091 | BV10: =(E10-E9)/$B9*E$3 -> 0.0021366364 | BW10: =(F10-F9)/$B9*F$3 -> 0.0024181818 | BX10: =(G10-G9)/$B9*G$3 -> 0.0016690909 | BY10: =(H10-H9)/$B9*H$3 -> 0.00097827273 | BZ10: =(I10-I9)/$B9*I$3 -> 0.00091745455 | CA10: =(J10-J9)/$B9*J$3 -> 4.7090909e-05 | ... CE10: =(N10-N9)/$B9*N$3 -> 0.00040181818 | CF10: =+SUM(BT10:CE10) -> 0.015098909
A11: =+[1]NOA!A12 -> 42887 | B11: =+[1]NOA!B12 -> 112.7 | C11: =+[1]NOA!C12 -> 110.2 | D11: =+[1]NOA!D12 -> 111.6 | E11: =+[1]NOA!E12 -> 110.9 | F11: =+[1]NOA!F12 -> 136.4 | G11: =+[1]NOA!G12 -> 106.5 | H11: =+[1]NOA!H12 -> 112.7 | ... N11: =+[1]NOA!N12 -> 108.5 | O11: =+[1]NOA!R12 -> 110.7 | P11: =+[1]NOA!S12 -> 110.2 | Q11: =+[1]NOA!T12 -> 123.9 | R11: =+SUMPRODUCT($C$3:$N$3,C11:N11) -> 112.67007 | S11: =+($C$3*$C11+$D$3*$D11+$E$3*$E11+$G$3*$G11+$K$3*$K11+$M$3*$M11+$N$3*$N11)/SUM($C$3:$E$3,$G$3,$K$3,$M$3:$N$3) -> 109.91235 | T11: =+($E$3*$E11+$G$3*$G11+$K$3*$K11+$M$3*$M11+$N$3*$N11)/SUM($E$3,$G$3,$K$3,$M$3:$N$3) -> 109.48658 | U11: =+($E$3*$E11+$G$3*$G11+$K$3*$K11+$N$3*$N11)/SUM($E$3,$G$3,$K$3,$N$3) -> 109.51142 | W11: =($E$3*$E11+SUMPRODUCT($G$3:$L$3,$G11:$L11)+$N$3*$N11)/SUM($E$3,$G$3:$L$3,$N$3) -> 111.5899 | Y11: =+B11/B10-1 -> 0.0098566308 | Z11: =+C11/C10-1 -> 0.0054744526 | AA11: =+D11/D10-1 -> 0.0026954178 | AB11: =+E11/E10-1 -> 0.028756957 | AC11: =+F11/F10-1 -> 0.005899705 | AD11: =+G11/G10-1 -> 0.0037700283 | AE11: =+H11/H10-1 -> 0.016230839 | AF11: =+I11/I10-1 -> 0.0092421442 | ... AT11: =+W11/W10-1 -> 0.014070282 | BS11: =+A11 -> 42887 | BT11: =(C11-C10)/$B10*C$3 -> 0.0018639785 | BU11: =(D11-D10)/$B10*D$3 -> 8.4139785e-05 | BV11: =(E11-E10)/$B10*E$3 -> 0.0034361111 | BW11: =(F11-F10)/$B10*F$3 -> 0.00050179211 | BX11: =(G11-G10)/$B10*G$3 -> 0.00021935484 | BY11: =(H11-H10)/$B10*H$3 -> 0.0010209677 | BZ11: =(I11-I10)/$B10*I$3 -> 0.00075358423 | CA11: =(J11-J10)/$B10*J$3 -> 0.00020887097 | ... CE11: =(N11-N10)/$B10*N$3 -> 9.1397849e-05 | CF11: =+SUM(BT11:CE11) -> 0.0092861111
A12: =+[1]NOA!A13 -> 42917 | B12: =+[1]NOA!B13 -> 114.3 | C12: =+[1]NOA!C13 -> 111.3 | D12: =+[1]NOA!D13 -> 113.9 | E12: =+[1]NOA!E13 -> 110.6 | F12: =+[1]NOA!F13 -> 138.6 | G12: =+[1]NOA!G13 -> 109.4 | H12: =+[1]NOA!H13 -> 116.1 | ... N12: =+[1]NOA!N13 -> 109.4 | O12: =+[1]NOA!R13 -> 110 | P12: =+[1]NOA!S13 -> 111.9 | Q12: =+[1]NOA!T13 -> 126.5 | R12: =+SUMPRODUCT($C$3:$N$3,C12:N12) -> 114.27933 | S12: =+($C$3*$C12+$D$3*$D12+$E$3*$E12+$G$3*$G12+$K$3*$K12+$M$3*$M12+$N$3*$N12)/SUM($C$3:$E$3,$G$3,$K$3,$M$3:$N$3) -> 111.18187 | T12: =+($E$3*$E12+$G$3*$G12+$K$3*$K12+$M$3*$M12+$N$3*$N12)/SUM($E$3,$G$3,$K$3,$M$3:$N$3) -> 110.83011 | U12: =+($E$3*$E12+$G$3*$G12+$K$3*$K12+$N$3*$N12)/SUM($E$3,$G$3,$K$3,$N$3) -> 110.72396 | W12: =($E$3*$E12+SUMPRODUCT($G$3:$L$3,$G12:$L12)+$N$3*$N12)/SUM($E$3,$G$3:$L$3,$N$3) -> 113.40748 | Y12: =+B12/B11-1 -> 0.014196983 | Z12: =+C12/C11-1 -> 0.0099818512 | AA12: =+D12/D11-1 -> 0.020609319 | AB12: =+E12/E11-1 -> -0.0027051398 | AC12: =+F12/F11-1 -> 0.016129032 | AD12: =+G12/G11-1 -> 0.027230047 | AE12: =+H12/H11-1 -> 0.030168589 | AF12: =+I12/I11-1 -> 0.029304029 | ... AT12: =+W12/W11-1 -> 0.016288043 | BS12: =+A12 -> 42917 | BT12: =(C12-C11)/$B11*C$3 -> 0.0033839397 | BU12: =(D12-D11)/$B11*D$3 -> 0.00063877551 | BV12: =(E12-E11)/$B11*E$3 -> -0.00032928128 | BW12: =(F12-F11)/$B11*F$3 -> 0.0013664596 | BX12: =(G12-G11)/$B11*G$3 -> 0.0015748004 | BY12: =(H12-H11)/$B11*H$3 -> 0.0019096717 | BZ12: =(I12-I11)/$B11*I$3 -> 0.0023879326 | CA12: =(J12-J11)/$B11*J$3 -> -2.2981366e-05 | ... CE12: =(N12-N11)/$B11*N$3 -> 0.0002715173 | CF12: =+SUM(BT12:CE12) -> 0.014279148
A13: =+[1]NOA!A14 -> 42948 | B13: =+[1]NOA!B14 -> 115.7 | C13: =+[1]NOA!C14 -> 112.8 | D13: =+[1]NOA!D14 -> 116 | E13: =+[1]NOA!E14 -> 110.3 | F13: =+[1]NOA!F14 -> 139.7 | G13: =+[1]NOA!G14 -> 110.1 | H13: =+[1]NOA!H14 -> 118.5 | ... N13: =+[1]NOA!N14 -> 111.4 | O13: =+[1]NOA!R14 -> 111.5 | P13: =+[1]NOA!S14 -> 113.3 | Q13: =+[1]NOA!T14 -> 128.2 | R13: =+SUMPRODUCT($C$3:$N$3,C13:N13) -> 115.73653 | S13: =+($C$3*$C13+$D$3*$D13+$E$3*$E13+$G$3*$G13+$K$3*$K13+$M$3*$M13+$N$3*$N13)/SUM($C$3:$E$3,$G$3,$K$3,$M$3:$N$3) -> 112.54489 | T13: =+($E$3*$E13+$G$3*$G13+$K$3*$K13+$M$3*$M13+$N$3*$N13)/SUM($E$3,$G$3,$K$3,$M$3:$N$3) -> 111.9962 | U13: =+($E$3*$E13+$G$3*$G13+$K$3*$K13+$N$3*$N13)/SUM($E$3,$G$3,$K$3,$N$3) -> 111.73682 | W13: =($E$3*$E13+SUMPRODUCT($G$3:$L$3,$G13:$L13)+$N$3*$N13)/SUM($E$3,$G$3:$L$3,$N$3) -> 114.8025 | Y13: =+B13/B12-1 -> 0.012248469 | Z13: =+C13/C12-1 -> 0.013477089 | AA13: =+D13/D12-1 -> 0.018437226 | AB13: =+E13/E12-1 -> -0.0027124774 | AC13: =+F13/F12-1 -> 0.0079365079 | AD13: =+G13/G12-1 -> 0.0063985375 | AE13: =+H13/H12-1 -> 0.020671835 | AF13: =+I13/I12-1 -> 0.011565836 | ... AT13: =+W13/W12-1 -> 0.012300972 | BS13: =+A13 -> 42948 | BT13: =(C13-C12)/$B12*C$3 -> 0.0045498688 | BU13: =(D13-D12)/$B12*D$3 -> 0.00057506562 | BV13: =(E13-E12)/$B12*E$3 -> -0.00032467192 | BW13: =(F13-F12)/$B12*F$3 -> 0.00067366579 | BX13: =(G13-G12)/$B12*G$3 -> 0.00037480315 | BY13: =(H13-H12)/$B12*H$3 -> 0.0013291339 | BZ13: =(I13-I12)/$B12*I$3 -> 0.00095651794 | CA13: =(J13-J12)/$B12*J$3 -> 0.00063447069 | ... CE13: =(N13-N12)/$B12*N$3 -> 0.00059492563 | CF13: =+SUM(BT13:CE13) -> 0.012748906
A14: =+[1]NOA!A15 -> 42979 | B14: =+[1]NOA!B15 -> 117.8 | C14: =+[1]NOA!C15 -> 115.9 | D14: =+[1]NOA!D15 -> 116.8 | E14: =+[1]NOA!E15 -> 111.7 | F14: =+[1]NOA!F15 -> 141.2 | G14: =+[1]NOA!G15 -> 111.4 | H14: =+[1]NOA!H15 -> 120.8 | ... N14: =+[1]NOA!N15 -> 113.2 | O14: =+[1]NOA!R15 -> 115.3 | P14: =+[1]NOA!S15 -> 115.3 | Q14: =+[1]NOA!T15 -> 129.2 | R14: =+SUMPRODUCT($C$3:$N$3,C14:N14) -> 117.79073 | S14: =+($C$3*$C14+$D$3*$D14+$E$3*$E14+$G$3*$G14+$K$3*$K14+$M$3*$M14+$N$3*$N14)/SUM($C$3:$E$3,$G$3,$K$3,$M$3:$N$3) -> 114.80043 | T14: =+($E$3*$E14+$G$3*$G14+$K$3*$K14+$M$3*$M14+$N$3*$N14)/SUM($E$3,$G$3,$K$3,$M$3:$N$3) -> 113.56179 | U14: =+($E$3*$E14+$G$3*$G14+$K$3*$K14+$N$3*$N14)/SUM($E$3,$G$3,$K$3,$N$3) -> 113.20643 | W14: =($E$3*$E14+SUMPRODUCT($G$3:$L$3,$G14:$L14)+$N$3*$N14)/SUM($E$3,$G$3:$L$3,$N$3) -> 116.28011 | Y14: =+B14/B13-1 -> 0.018150389 | Z14: =+C14/C13-1 -> 0.02748227 | AA14: =+D14/D13-1 -> 0.0068965517 | AB14: =+E14/E13-1 -> 0.012692656 | AC14: =+F14/F13-1 -> 0.010737294 | AD14: =+G14/G13-1 -> 0.011807448 | AE14: =+H14/H13-1 -> 0.019409283 | AF14: =+I14/I13-1 -> 0.0070360598 | ... AT14: =+W14/W13-1 -> 0.012870893 | BS14: =+A14 -> 42979 | BT14: =(C14-C13)/$B13*C$3 -> 0.0092892826 | BU14: =(D14-D13)/$B13*D$3 -> 0.00021642178 | BV14: =(E14-E13)/$B13*E$3 -> 0.0014968021 | BW14: =(F14-F13)/$B13*F$3 -> 0.00090751945 | BX14: =(G14-G13)/$B13*G$3 -> 0.00068764045 | BY14: =(H14-H13)/$B13*H$3 -> 0.0012583405 | BZ14: =(I14-I13)/$B13*I$3 -> 0.00058150389 | CA14: =(J14-J13)/$B13*J$3 -> 0.0003357822 | ... CE14: =(N14-N13)/$B13*N$3 -> 0.00052895419 | CF14: =+SUM(BT14:CE14) -> 0.017754538
A15: =+[1]NOA!A16 -> 43009 | B15: =+[1]NOA!B16 -> 120 | C15: =+[1]NOA!C16 -> 118.1 | D15: =+[1]NOA!D16 -> 120 | E15: =+[1]NOA!E16 -> 115.2 | F15: =+[1]NOA!F16 -> 142.5 | G15: =+[1]NOA!G16 -> 112.5 | H15: =+[1]NOA!H16 -> 122.4 | ... N15: =+[1]NOA!N16 -> 114.7 | O15: =+[1]NOA!R16 -> 119.7 | P15: =+[1]NOA!S16 -> 117.1 | Q15: =+[1]NOA!T16 -> 131.5 | R15: =+SUMPRODUCT($C$3:$N$3,C15:N15) -> 120.02322 | S15: =+($C$3*$C15+$D$3*$D15+$E$3*$E15+$G$3*$G15+$K$3*$K15+$M$3*$M15+$N$3*$N15)/SUM($C$3:$E$3,$G$3,$K$3,$M$3:$N$3) -> 117.15399 | T15: =+($E$3*$E15+$G$3*$G15+$K$3*$K15+$M$3*$M15+$N$3*$N15)/SUM($E$3,$G$3,$K$3,$M$3:$N$3) -> 115.98998 | U15: =+($E$3*$E15+$G$3*$G15+$K$3*$K15+$N$3*$N15)/SUM($E$3,$G$3,$K$3,$N$3) -> 115.61401 | W15: =($E$3*$E15+SUMPRODUCT($G$3:$L$3,$G15:$L15)+$N$3*$N15)/SUM($E$3,$G$3:$L$3,$N$3) -> 118.5653 | Y15: =+B15/B14-1 -> 0.018675722 | Z15: =+C15/C14-1 -> 0.018981881 | AA15: =+D15/D14-1 -> 0.02739726 | AB15: =+E15/E14-1 -> 0.03133393 | AC15: =+F15/F14-1 -> 0.0092067989 | AD15: =+G15/G14-1 -> 0.0098743268 | AE15: =+H15/H14-1 -> 0.013245033 | AF15: =+I15/I14-1 -> 0.013100437 | ... AT15: =+W15/W14-1 -> 0.019652491 | BS15: =+A15 -> 43009 | BT15: =(C15-C14)/$B14*C$3 -> 0.0064748727 | BU15: =(D15-D14)/$B14*D$3 -> 0.00085025467 | BV15: =(E15-E14)/$B14*E$3 -> 0.0036752971 | BW15: =(F15-F14)/$B14*F$3 -> 0.00077249576 | BX15: =(G15-G14)/$B14*G$3 -> 0.00057147708 | BY15: =(H15-H14)/$B14*H$3 -> 0.00085976231 | BZ15: =(I15-I14)/$B14*I$3 -> 0.0010708829 | CA15: =(J15-J14)/$B14*J$3 -> 0.0014511036 | ... CE15: =(N15-N14)/$B14*N$3 -> 0.00043293718 | CF15: =+SUM(BT15:CE15) -> 0.018951528
A16: =+[1]NOA!A17 -> 43040 | B16: =+[1]NOA!B17 -> 121.5 | C16: =+[1]NOA!C17 -> 119.1 | D16: =+[1]NOA!D17 -> 120.9 | E16: =+[1]NOA!E17 -> 116.9 | F16: =+[1]NOA!F17 -> 144.1 | G16: =+[1]NOA!G17 -> 113.6 | H16: =+[1]NOA!H17 -> 123.9 | ... N16: =+[1]NOA!N17 -> 116.2 | O16: =+[1]NOA!R17 -> 121.3 | P16: =+[1]NOA!S17 -> 118.5 | Q16: =+[1]NOA!T17 -> 133.3 | R16: =+SUMPRODUCT($C$3:$N$3,C16:N16) -> 121.49589 | S16: =+($C$3*$C16+$D$3*$D16+$E$3*$E16+$G$3*$G16+$K$3*$K16+$M$3*$M16+$N$3*$N16)/SUM($C$3:$E$3,$G$3,$K$3,$M$3:$N$3) -> 118.44142 | T16: =+($E$3*$E16+$G$3*$G16+$K$3*$K16+$M$3*$M16+$N$3*$N16)/SUM($E$3,$G$3,$K$3,$M$3:$N$3) -> 117.58939 | U16: =+($E$3*$E16+$G$3*$G16+$K$3*$K16+$N$3*$N16)/SUM($E$3,$G$3,$K$3,$N$3) -> 117.41415 | W16: =($E$3*$E16+SUMPRODUCT($G$3:$L$3,$G16:$L16)+$N$3*$N16)/SUM($E$3,$G$3:$L$3,$N$3) -> 120.5011 | Y16: =+B16/B15-1 -> 0.0125 | Z16: =+C16/C15-1 -> 0.0084674005 | AA16: =+D16/D15-1 -> 0.0075 | AB16: =+E16/E15-1 -> 0.014756944 | AC16: =+F16/F15-1 -> 0.01122807 | AD16: =+G16/G15-1 -> 0.0097777778 | AE16: =+H16/H15-1 -> 0.012254902 | AF16: =+I16/I15-1 -> 0.027586207 | ... AT16: =+W16/W15-1 -> 0.016326846 | BS16: =+A16 -> 43040 | BT16: =(C16-C15)/$B15*C$3 -> 0.0028891667 | BU16: =(D16-D15)/$B15*D$3 -> 0.00023475 | BV16: =(E16-E15)/$B15*E$3 -> 0.0017524167 | BW16: =(F16-F15)/$B15*F$3 -> 0.00093333333 | BX16: =(G16-G15)/$B15*G$3 -> 0.000561 | BY16: =(H16-H15)/$B15*H$3 -> 0.00079125 | BZ16: =(I16-I15)/$B15*I$3 -> 0.0022426667 | CA16: =(J16-J15)/$B15*J$3 -> 0.0003885 | ... CE16: =(N16-N15)/$B15*N$3 -> 0.000425 | CF16: =+SUM(BT16:CE16) -> 0.01227225
A17: =+[1]NOA!A18 -> 43070 | B17: =+[1]NOA!B18 -> 124.3 | C17: =+[1]NOA!C18 -> 120.6 | D17: =+[1]NOA!D18 -> 121.5 | E17: =+[1]NOA!E18 -> 117.8 | F17: =+[1]NOA!F18 -> 163.7 | G17: =+[1]NOA!G18 -> 116.5 | H17: =+[1]NOA!H18 -> 125.6 | ... N17: =+[1]NOA!N18 -> 117.4 | O17: =+[1]NOA!R18 -> 122.2 | P17: =+[1]NOA!S18 -> 120 | Q17: =+[1]NOA!T18 -> 142.6 | R17: =+SUMPRODUCT($C$3:$N$3,C17:N17) -> 124.31195 | S17: =+($C$3*$C17+$D$3*$D17+$E$3*$E17+$G$3*$G17+$K$3*$K17+$M$3*$M17+$N$3*$N17)/SUM($C$3:$E$3,$G$3,$K$3,$M$3:$N$3) -> 119.79359 | T17: =+($E$3*$E17+$G$3*$G17+$K$3*$K17+$M$3*$M17+$N$3*$N17)/SUM($E$3,$G$3,$K$3,$M$3:$N$3) -> 118.86422 | U17: =+($E$3*$E17+$G$3*$G17+$K$3*$K17+$N$3*$N17)/SUM($E$3,$G$3,$K$3,$N$3) -> 118.94005 | W17: =($E$3*$E17+SUMPRODUCT($G$3:$L$3,$G17:$L17)+$N$3*$N17)/SUM($E$3,$G$3:$L$3,$N$3) -> 122.35086 | Y17: =+B17/B16-1 -> 0.023045267 | Z17: =+C17/C16-1 -> 0.012594458 | AA17: =+D17/D16-1 -> 0.0049627792 | AB17: =+E17/E16-1 -> 0.0076988879 | AC17: =+F17/F16-1 -> 0.13601666 | AD17: =+G17/G16-1 -> 0.025528169 | AE17: =+H17/H16-1 -> 0.013720743 | AF17: =+I17/I16-1 -> 0.031879195 | ... AT17: =+W17/W16-1 -> 0.015350535 | AV17: =+B17/B5-1 -> 0.243 | AW17: =+C17/C5-1 -> 0.206 | AX17: =+D17/D5-1 -> 0.215 | AY17: =+E17/E5-1 -> 0.178 | AZ17: =+F17/F5-1 -> 0.637 | BA17: =+G17/G5-1 -> 0.165 | BB17: =+H17/H5-1 -> 0.256 | BC17: =+I17/I5-1 -> 0.23 | ... BQ17: =+W17/W5-1 -> 0.22350858 | BS17: =+A17 -> 43070 | BT17: =(C17-C16)/$B16*C$3 -> 0.0042802469 | BU17: =(D17-D16)/$B16*D$3 -> 0.0001545679 | BV17: =(E17-E16)/$B16*E$3 -> 0.0009162963 | BW17: =(F17-F16)/$B16*F$3 -> 0.011292181 | BX17: =(G17-G16)/$B16*G$3 -> 0.0014607407 | BY17: =(H17-H16)/$B16*H$3 -> 0.00088567901 | BZ17: =(I17-I16)/$B16*I$3 -> 0.0026302881 | CA17: =(J17-J16)/$B16*J$3 -> 0.00019185185 | ... CE17: =(N17-N16)/$B16*N$3 -> 0.00033580247 | CF17: =+SUM(BT17:CE17) -> 0.023177449
A18: =+[1]NOA!A19 -> 43101 | B18: =+[1]NOA!B19 -> 126.6 | C18: =+[1]NOA!C19 -> 122.4 | D18: =+[1]NOA!D19 -> 124.4 | E18: =+[1]NOA!E19 -> 117.5 | F18: =+[1]NOA!F19 -> 170.9 | G18: =+[1]NOA!G19 -> 118.2 | H18: =+[1]NOA!H19 -> 127.6 | ... N18: =+[1]NOA!N19 -> 119.4 | O18: =+[1]NOA!R19 -> 123.8 | P18: =+[1]NOA!S19 -> 121.9 | Q18: =+[1]NOA!T19 -> 146.9 | R18: =+SUMPRODUCT($C$3:$N$3,C18:N18) -> 126.63525 | S18: =+($C$3*$C18+$D$3*$D18+$E$3*$E18+$G$3*$G18+$K$3*$K18+$M$3*$M18+$N$3*$N18)/SUM($C$3:$E$3,$G$3,$K$3,$M$3:$N$3) -> 121.65627 | T18: =+($E$3*$E18+$G$3*$G18+$K$3*$K18+$M$3*$M18+$N$3*$N18)/SUM($E$3,$G$3,$K$3,$M$3:$N$3) -> 120.69693 | U18: =+($E$3*$E18+$G$3*$G18+$K$3*$K18+$N$3*$N18)/SUM($E$3,$G$3,$K$3,$N$3) -> 120.23685 | W18: =($E$3*$E18+SUMPRODUCT($G$3:$L$3,$G18:$L18)+$N$3*$N18)/SUM($E$3,$G$3:$L$3,$N$3) -> 124.06414 | Y18: =+B18/B17-1 -> 0.01850362 | Z18: =+C18/C17-1 -> 0.014925373 | AA18: =+D18/D17-1 -> 0.023868313 | AB18: =+E18/E17-1 -> -0.0025466893 | AC18: =+F18/F17-1 -> 0.043982896 | AD18: =+G18/G17-1 -> 0.014592275 | AE18: =+H18/H17-1 -> 0.015923567 | AF18: =+I18/I17-1 -> 0.019512195 | ... AT18: =+W18/W17-1 -> 0.014003017 | AV18: =+B18/B6-1 -> 0.24606299 | AW18: =+C18/C6-1 -> 0.21188119 | AX18: =+D18/D6-1 -> 0.22803554 | AY18: =+E18/E6-1 -> 0.16915423 | AZ18: =+F18/F6-1 -> 0.68208661 | BA18: =+G18/G6-1 -> 0.17729084 | BB18: =+H18/H6-1 -> 0.24245375 | BC18: =+I18/I6-1 -> 0.21865889 | ... BQ18: =+W18/W6-1 -> 0.21774085 | BS18: =+A18 -> 43101 | BT18: =(C18-C17)/$B17*C$3 -> 0.0050205953 | BU18: =(D18-D17)/$B17*D$3 -> 0.0007302494 | BV18: =(E18-E17)/$B17*E$3 -> -0.00029855189 | BW18: =(F18-F17)/$B17*F$3 -> 0.0040547064 | BX18: =(G18-G17)/$B17*G$3 -> 0.00083700724 | BY18: =(H18-H17)/$B17*H$3 -> 0.0010185036 | BZ18: =(I18-I17)/$B17*I$3 -> 0.0016238134 | CA18: =(J18-J17)/$B17*J$3 -> 0.00081263073 | ... CE18: =(N18-N17)/$B17*N$3 -> 0.00054706356 | CF18: =+SUM(BT18:CE18) -> 0.01869107
A19: =+[1]NOA!A20 -> 43132 | B19: =+[1]NOA!B20 -> 129.2 | C19: =+[1]NOA!C20 -> 124.7 | D19: =+[1]NOA!D20 -> 126.9 | E19: =+[1]NOA!E20 -> 116.8 | F19: =+[1]NOA!F20 -> 175 | G19: =+[1]NOA!G20 -> 120 | H19: =+[1]NOA!H20 -> 129.7 | ... N19: =+[1]NOA!N20 -> 121.4 | O19: =+[1]NOA!R20 -> 123.7 | P19: =+[1]NOA!S20 -> 124 | Q19: =+[1]NOA!T20 -> 153.3 | R19: =+SUMPRODUCT($C$3:$N$3,C19:N19) -> 129.25464 | S19: =+($C$3*$C19+$D$3*$D19+$E$3*$E19+$G$3*$G19+$K$3*$K19+$M$3*$M19+$N$3*$N19)/SUM($C$3:$E$3,$G$3,$K$3,$M$3:$N$3) -> 123.38688 | T19: =+($E$3*$E19+$G$3*$G19+$K$3*$K19+$M$3*$M19+$N$3*$N19)/SUM($E$3,$G$3,$K$3,$M$3:$N$3) -> 121.80938 | U19: =+($E$3*$E19+$G$3*$G19+$K$3*$K19+$N$3*$N19)/SUM($E$3,$G$3,$K$3,$N$3) -> 120.86498 | W19: =($E$3*$E19+SUMPRODUCT($G$3:$L$3,$G19:$L19)+$N$3*$N19)/SUM($E$3,$G$3:$L$3,$N$3) -> 126.67589 | Y19: =+B19/B18-1 -> 0.020537125 | Z19: =+C19/C18-1 -> 0.01879085 | AA19: =+D19/D18-1 -> 0.020096463 | AB19: =+E19/E18-1 -> -0.0059574468 | AC19: =+F19/F18-1 -> 0.023990638 | AD19: =+G19/G18-1 -> 0.015228426 | AE19: =+H19/H18-1 -> 0.01645768 | AF19: =+I19/I18-1 -> 0.048644338 | ... AT19: =+W19/W18-1 -> 0.021051659 | AV19: =+B19/B7-1 -> 0.24590164 | AW19: =+C19/C7-1 -> 0.20019249 | AX19: =+D19/D7-1 -> 0.2028436 | AY19: =+E19/E7-1 -> 0.16334661 | AZ19: =+F19/F7-1 -> 0.62488394 | BA19: =+G19/G7-1 -> 0.19165839 | BB19: =+H19/H7-1 -> 0.24591739 | BC19: =+I19/I7-1 -> 0.24526515 | ... BQ19: =+W19/W7-1 -> 0.23044986 | BS19: =+A19 -> 43132 | BT19: =(C19-C18)/$B18*C$3 -> 0.0062986572 | BU19: =(D19-D18)/$B18*D$3 -> 0.00061808847 | BV19: =(E19-E18)/$B18*E$3 -> -0.00068396524 | BW19: =(F19-F18)/$B18*F$3 -> 0.0022669826 | BX19: =(G19-G18)/$B18*G$3 -> 0.00087014218 | BY19: =(H19-H18)/$B18*H$3 -> 0.00105 | BZ19: =(I19-I18)/$B18*I$3 -> 0.0040522117 | CA19: =(J19-J18)/$B18*J$3 -> 0.0031914692 | ... CE19: =(N19-N18)/$B18*N$3 -> 0.0005371248 | CF19: =+SUM(BT19:CE19) -> 0.020690284
A20: =+[1]NOA!A21 -> 43160 | B20: =+[1]NOA!B21 -> 133.2 | C20: =+[1]NOA!C21 -> 128.5 | D20: =+[1]NOA!D21 -> 127.5 | E20: =+[1]NOA!E21 -> 118.2 | F20: =+[1]NOA!F21 -> 178.9 | G20: =+[1]NOA!G21 -> 124.7 | H20: =+[1]NOA!H21 -> 131.9 | ... N20: =+[1]NOA!N21 -> 123 | O20: =+[1]NOA!R21 -> 124.5 | P20: =+[1]NOA!S21 -> 127.8 | Q20: =+[1]NOA!T21 -> 160.4 | R20: =+SUMPRODUCT($C$3:$N$3,C20:N20) -> 133.24947 | S20: =+($C$3*$C20+$D$3*$D20+$E$3*$E20+$G$3*$G20+$K$3*$K20+$M$3*$M20+$N$3*$N20)/SUM($C$3:$E$3,$G$3,$K$3,$M$3:$N$3) -> 126.71206 | T20: =+($E$3*$E20+$G$3*$G20+$K$3*$K20+$M$3*$M20+$N$3*$N20)/SUM($E$3,$G$3,$K$3,$M$3:$N$3) -> 124.91317 | U20: =+($E$3*$E20+$G$3*$G20+$K$3*$K20+$N$3*$N20)/SUM($E$3,$G$3,$K$3,$N$3) -> 123.91246 | W20: =($E$3*$E20+SUMPRODUCT($G$3:$L$3,$G20:$L20)+$N$3*$N20)/SUM($E$3,$G$3:$L$3,$N$3) -> 131.17054 | Y20: =+B20/B19-1 -> 0.030959752 | Z20: =+C20/C19-1 -> 0.030473136 | AA20: =+D20/D19-1 -> 0.0047281324 | AB20: =+E20/E19-1 -> 0.011986301 | AC20: =+F20/F19-1 -> 0.022285714 | AD20: =+G20/G19-1 -> 0.039166667 | AE20: =+H20/H19-1 -> 0.016962221 | AF20: =+I20/I19-1 -> 0.03878327 | ... AT20: =+W20/W19-1 -> 0.035481423 | AV20: =+B20/B8-1 -> 0.24369748 | AW20: =+C20/C8-1 -> 0.21226415 | AX20: =+D20/D8-1 -> 0.19047619 | AY20: =+E20/E8-1 -> 0.15655577 | AZ20: =+F20/F8-1 -> 0.47364086 | BA20: =+G20/G8-1 -> 0.22254902 | BB20: =+H20/H8-1 -> 0.23271028 | BC20: =+I20/I8-1 -> 0.28383459 | ... BQ20: =+W20/W8-1 -> 0.23719261 | BS20: =+A20 -> 43160 | BT20: =(C20-C19)/$B19*C$3 -> 0.010197059 | BU20: =(D20-D19)/$B19*D$3 -> 0.00014535604 | BV20: =(E20-E19)/$B19*E$3 -> 0.0013404025 | BW20: =(F20-F19)/$B19*F$3 -> 0.0021130031 | BX20: =(G20-G19)/$B19*G$3 -> 0.0022263158 | BY20: =(H20-H19)/$B19*H$3 -> 0.0010778638 | BZ20: =(I20-I19)/$B19*I$3 -> 0.0033197368 | CA20: =(J20-J19)/$B19*J$3 -> 0.0010223684 | ... CE20: =(N20-N19)/$B19*N$3 -> 0.00042105263 | CF20: =+SUM(BT20:CE20) -> 0.030919737
A21: =+[1]NOA!A22 -> 43191 | B21: =+[1]NOA!B22 -> 137 | C21: =+[1]NOA!C22 -> 129.9 | D21: =+[1]NOA!D22 -> 129.1 | E21: =+[1]NOA!E22 -> 123.3 | F21: =+[1]NOA!F22 -> 199.3 | G21: =+[1]NOA!G22 -> 126.1 | H21: =+[1]NOA!H22 -> 134.3 | ... N21: =+[1]NOA!N22 -> 125.5 | O21: =+[1]NOA!R22 -> 126.2 | P21: =+[1]NOA!S22 -> 130.4 | Q21: =+[1]NOA!T22 -> 170.2 | R21: =+SUMPRODUCT($C$3:$N$3,C21:N21) -> 137.03172 | S21: =+($C$3*$C21+$D$3*$D21+$E$3*$E21+$G$3*$G21+$K$3*$K21+$M$3*$M21+$N$3*$N21)/SUM($C$3:$E$3,$G$3,$K$3,$M$3:$N$3) -> 129.08988 | T21: =+($E$3*$E21+$G$3*$G21+$K$3*$K21+$M$3*$M21+$N$3*$N21)/SUM($E$3,$G$3,$K$3,$M$3:$N$3) -> 128.30511 | U21: =+($E$3*$E21+$G$3*$G21+$K$3*$K21+$N$3*$N21)/SUM($E$3,$G$3,$K$3,$N$3) -> 127.64648 | W21: =($E$3*$E21+SUMPRODUCT($G$3:$L$3,$G21:$L21)+$N$3*$N21)/SUM($E$3,$G$3:$L$3,$N$3) -> 134.65075 | Y21: =+B21/B20-1 -> 0.028528529 | Z21: =+C21/C20-1 -> 0.010894942 | AA21: =+D21/D20-1 -> 0.01254902 | AB21: =+E21/E20-1 -> 0.043147208 | AC21: =+F21/F20-1 -> 0.11403018 | AD21: =+G21/G20-1 -> 0.011226945 | AE21: =+H21/H20-1 -> 0.018195603 | AF21: =+I21/I20-1 -> 0.025622255 | ... AT21: =+W21/W20-1 -> 0.026531995 | AV21: =+B21/B9-1 -> 0.24545455 | AW21: =+C21/C9-1 -> 0.19833948 | AX21: =+D21/D9-1 -> 0.18115279 | AY21: =+E21/E9-1 -> 0.16430595 | AZ21: =+F21/F9-1 -> 0.51213961 | BA21: =+G21/G9-1 -> 0.22308438 | BB21: =+H21/H9-1 -> 0.22985348 | BC21: =+I21/I9-1 -> 0.30934579 | ... BQ21: =+W21/W9-1 -> 0.24210323 | BS21: =+A21 -> 43191 | BT21: =(C21-C20)/$B20*C$3 -> 0.003643994 | BU21: =(D21-D20)/$B20*D$3 -> 0.00037597598 | BV21: =(E21-E20)/$B20*E$3 -> 0.0047362613 | BW21: =(F21-F20)/$B20*F$3 -> 0.010720721 | BX21: =(G21-G20)/$B20*G$3 -> 0.00064324324 | BY21: =(H21-H20)/$B20*H$3 -> 0.0011405405 | BZ21: =(I21-I20)/$B20*I$3 -> 0.0022098348 | CA21: =(J21-J20)/$B20*J$3 -> 0.00079722222 | ... CE21: =(N21-N20)/$B20*N$3 -> 0.00063813814 | CF21: =+SUM(BT21:CE21) -> 0.02839527
A22: =+[1]NOA!A23 -> 43221 | B22: =+[1]NOA!B23 -> 140.2 | C22: =+[1]NOA!C23 -> 133.6 | D22: =+[1]NOA!D23 -> 131.4 | E22: =+[1]NOA!E23 -> 126.8 | F22: =+[1]NOA!F23 -> 202.7 | G22: =+[1]NOA!G23 -> 128.6 | H22: =+[1]NOA!H23 -> 138.3 | ... N22: =+[1]NOA!N23 -> 128.2 | O22: =+[1]NOA!R23 -> 128.9 | P22: =+[1]NOA!S23 -> 133.6 | Q22: =+[1]NOA!T23 -> 173.8 | R22: =+SUMPRODUCT($C$3:$N$3,C22:N22) -> 140.17353 | S22: =+($C$3*$C22+$D$3*$D22+$E$3*$E22+$G$3*$G22+$K$3*$K22+$M$3*$M22+$N$3*$N22)/SUM($C$3:$E$3,$G$3,$K$3,$M$3:$N$3) -> 132.12648 | T22: =+($E$3*$E22+$G$3*$G22+$K$3*$K22+$M$3*$M22+$N$3*$N22)/SUM($E$3,$G$3,$K$3,$M$3:$N$3) -> 130.76414 | U22: =+($E$3*$E22+$G$3*$G22+$K$3*$K22+$N$3*$N22)/SUM($E$3,$G$3,$K$3,$N$3) -> 130.29465 | W22: =($E$3*$E22+SUMPRODUCT($G$3:$L$3,$G22:$L22)+$N$3*$N22)/SUM($E$3,$G$3:$L$3,$N$3) -> 137.62726 | Y22: =+B22/B21-1 -> 0.023357664 | Z22: =+C22/C21-1 -> 0.028483449 | AA22: =+D22/D21-1 -> 0.017815647 | AB22: =+E22/E21-1 -> 0.02838605 | AC22: =+F22/F21-1 -> 0.017059709 | AD22: =+G22/G21-1 -> 0.019825535 | AE22: =+H22/H21-1 -> 0.029784066 | AF22: =+I22/I21-1 -> 0.021413276 | ... AT22: =+W22/W21-1 -> 0.022105404 | AV22: =+B22/B10-1 -> 0.2562724 | AW22: =+C22/C10-1 -> 0.2189781 | AX22: =+D22/D10-1 -> 0.18059299 | AY22: =+E22/E10-1 -> 0.17625232 | AZ22: =+F22/F10-1 -> 0.49483776 | BA22: =+G22/G10-1 -> 0.21206409 | BB22: =+H22/H10-1 -> 0.24706943 | BC22: =+I22/I10-1 -> 0.32255083 | ... BQ22: =+W22/W10-1 -> 0.25068416 | BS22: =+A22 -> 43221 | BT22: =(C22-C21)/$B21*C$3 -> 0.0093634307 | BU22: =(D22-D21)/$B21*D$3 -> 0.00052547445 | BV22: =(E22-E21)/$B21*E$3 -> 0.003160219 | BW22: =(F22-F21)/$B21*F$3 -> 0.0017372263 | BX22: =(G22-G21)/$B21*G$3 -> 0.0011167883 | BY22: =(H22-H21)/$B21*H$3 -> 0.0018481752 | BZ22: =(I22-I21)/$B21*I$3 -> 0.0018416058 | CA22: =(J22-J21)/$B21*J$3 -> 0.0010964964 | ... CE22: =(N22-N21)/$B21*N$3 -> 0.00067007299 | CF22: =+SUM(BT22:CE22) -> 0.02293292
A23: =+[1]NOA!A24 -> 43252 | B23: =+[1]NOA!B24 -> 144.9 | C23: =+[1]NOA!C24 -> 140.9 | D23: =+[1]NOA!D24 -> 132.5 | E23: =+[1]NOA!E24 -> 128.8 | F23: =+[1]NOA!F24 -> 206.6 | G23: =+[1]NOA!G24 -> 133 | H23: =+[1]NOA!H24 -> 142.5 | ... N23: =+[1]NOA!N24 -> 132.4 | O23: =+[1]NOA!R24 -> 133.5 | P23: =+[1]NOA!S24 -> 138.7 | Q23: =+[1]NOA!T24 -> 177.3 | R23: =+SUMPRODUCT($C$3:$N$3,C23:N23) -> 144.9529 | S23: =+($C$3*$C23+$D$3*$D23+$E$3*$E23+$G$3*$G23+$K$3*$K23+$M$3*$M23+$N$3*$N23)/SUM($C$3:$E$3,$G$3,$K$3,$M$3:$N$3) -> 137.06106 | T23: =+($E$3*$E23+$G$3*$G23+$K$3*$K23+$M$3*$M23+$N$3*$N23)/SUM($E$3,$G$3,$K$3,$M$3:$N$3) -> 133.74485 | U23: =+($E$3*$E23+$G$3*$G23+$K$3*$K23+$N$3*$N23)/SUM($E$3,$G$3,$K$3,$N$3) -> 133.15503 | W23: =($E$3*$E23+SUMPRODUCT($G$3:$L$3,$G23:$L23)+$N$3*$N23)/SUM($E$3,$G$3:$L$3,$N$3) -> 141.16331 | Y23: =+B23/B22-1 -> 0.033523538 | Z23: =+C23/C22-1 -> 0.054640719 | AA23: =+D23/D22-1 -> 0.0083713851 | AB23: =+E23/E22-1 -> 0.015772871 | AC23: =+F23/F22-1 -> 0.019240257 | AD23: =+G23/G22-1 -> 0.034214619 | AE23: =+H23/H22-1 -> 0.030368764 | AF23: =+I23/I22-1 -> 0.046820405 | ... AT23: =+W23/W22-1 -> 0.02569296 | AV23: =+B23/B11-1 -> 0.28571429 | AW23: =+C23/C11-1 -> 0.27858439 | AX23: =+D23/D11-1 -> 0.18727599 | AY23: =+E23/E11-1 -> 0.16140667 | AZ23: =+F23/F11-1 -> 0.51466276 | BA23: =+G23/G11-1 -> 0.24882629 | BB23: =+H23/H11-1 -> 0.26441881 | BC23: =+I23/I11-1 -> 0.37179487 | ... BQ23: =+W23/W11-1 -> 0.26501877 | BS23: =+A23 -> 43252 | BT23: =(C23-C22)/$B22*C$3 -> 0.01805214 | BU23: =(D23-D22)/$B22*D$3 -> 0.00024557775 | BV23: =(E23-E22)/$B22*E$3 -> 0.001764622 | BW23: =(F23-F22)/$B22*F$3 -> 0.0019472183 | BX23: =(G23-G22)/$B22*G$3 -> 0.0019206847 | BY23: =(H23-H22)/$B22*H$3 -> 0.001896291 | BZ23: =(I23-I22)/$B22*I$3 -> 0.0040190442 | CA23: =(J23-J22)/$B22*J$3 -> 0.00016626248 | ... CE23: =(N23-N22)/$B22*N$3 -> 0.0010185449 | CF23: =+SUM(BT23:CE23) -> 0.034089658
A24: =+[1]NOA!A25 -> 43282 | B24: =+[1]NOA!B25 -> 149.9 | C24: =+[1]NOA!C25 -> 146.9 | D24: =+[1]NOA!D25 -> 136.3 | E24: =+[1]NOA!E25 -> 130.8 | F24: =+[1]NOA!F25 -> 208.7 | G24: =+[1]NOA!G25 -> 138.6 | H24: =+[1]NOA!H25 -> 147.5 | ... N24: =+[1]NOA!N25 -> 137.4 | O24: =+[1]NOA!R25 -> 140.2 | P24: =+[1]NOA!S25 -> 143.5 | Q24: =+[1]NOA!T25 -> 181.6 | R24: =+SUMPRODUCT($C$3:$N$3,C24:N24) -> 149.91636 | S24: =+($C$3*$C24+$D$3*$D24+$E$3*$E24+$G$3*$G24+$K$3*$K24+$M$3*$M24+$N$3*$N24)/SUM($C$3:$E$3,$G$3,$K$3,$M$3:$N$3) -> 142.12976 | T24: =+($E$3*$E24+$G$3*$G24+$K$3*$K24+$M$3*$M24+$N$3*$N24)/SUM($E$3,$G$3,$K$3,$M$3:$N$3) -> 138.02322 | U24: =+($E$3*$E24+$G$3*$G24+$K$3*$K24+$N$3*$N24)/SUM($E$3,$G$3,$K$3,$N$3) -> 136.9967 | W24: =($E$3*$E24+SUMPRODUCT($G$3:$L$3,$G24:$L24)+$N$3*$N24)/SUM($E$3,$G$3:$L$3,$N$3) -> 145.72569 | Y24: =+B24/B23-1 -> 0.034506556 | Z24: =+C24/C23-1 -> 0.042583392 | AA24: =+D24/D23-1 -> 0.028679245 | AB24: =+E24/E23-1 -> 0.01552795 | AC24: =+F24/F23-1 -> 0.010164569 | AD24: =+G24/G23-1 -> 0.042105263 | AE24: =+H24/H23-1 -> 0.035087719 | AF24: =+I24/I23-1 -> 0.052069426 | ... AT24: =+W24/W23-1 -> 0.032319877 | AV24: =+B24/B12-1 -> 0.31146107 | AW24: =+C24/C12-1 -> 0.31985624 | AX24: =+D24/D12-1 -> 0.19666374 | AY24: =+E24/E12-1 -> 0.18264014 | AZ24: =+F24/F12-1 -> 0.50577201 | BA24: =+G24/G12-1 -> 0.26691042 | BB24: =+H24/H12-1 -> 0.2704565 | BC24: =+I24/I12-1 -> 0.40213523 | ... BQ24: =+W24/W12-1 -> 0.2849743 | BS24: =+A24 -> 43282 | BT24: =(C24-C23)/$B23*C$3 -> 0.014356108 | BU24: =(D24-D23)/$B23*D$3 -> 0.00082084196 | BV24: =(E24-E23)/$B23*E$3 -> 0.0017073844 | BW24: =(F24-F23)/$B23*F$3 -> 0.0010144928 | BX24: =(G24-G23)/$B23*G$3 -> 0.0023652174 | BY24: =(H24-H23)/$B23*H$3 -> 0.002184265 | BZ24: =(I24-I23)/$B23*I$3 -> 0.0045271222 | CA24: =(J24-J23)/$B23*J$3 -> 0.00032173913 | ... CE24: =(N24-N23)/$B23*N$3 -> 0.0011732229 | CF24: =+SUM(BT24:CE24) -> 0.034254382
A25: =+[1]NOA!A26 -> 43313 | B25: =+[1]NOA!B26 -> 155.9 | C25: =+[1]NOA!C26 -> 154.6 | D25: =+[1]NOA!D26 -> 138.2 | E25: =+[1]NOA!E26 -> 130.6 | F25: =+[1]NOA!F26 -> 221.8 | G25: =+[1]NOA!G26 -> 143.1 | H25: =+[1]NOA!H26 -> 151.9 | ... N25: =+[1]NOA!N26 -> 141.9 | O25: =+[1]NOA!R26 -> 147.2 | P25: =+[1]NOA!S26 -> 148 | Q25: =+[1]NOA!T26 -> 192.3 | R25: =+SUMPRODUCT($C$3:$N$3,C25:N25) -> 155.85424 | S25: =+($C$3*$C25+$D$3*$D25+$E$3*$E25+$G$3*$G25+$K$3*$K25+$M$3*$M25+$N$3*$N25)/SUM($C$3:$E$3,$G$3,$K$3,$M$3:$N$3) -> 147.14404 | T25: =+($E$3*$E25+$G$3*$G25+$K$3*$K25+$M$3*$M25+$N$3*$N25)/SUM($E$3,$G$3,$K$3,$M$3:$N$3) -> 140.7108 | U25: =+($E$3*$E25+$G$3*$G25+$K$3*$K25+$N$3*$N25)/SUM($E$3,$G$3,$K$3,$N$3) -> 139.45111 | W25: =($E$3*$E25+SUMPRODUCT($G$3:$L$3,$G25:$L25)+$N$3*$N25)/SUM($E$3,$G$3:$L$3,$N$3) -> 149.98786 | Y25: =+B25/B24-1 -> 0.040026684 | Z25: =+C25/C24-1 -> 0.05241661 | AA25: =+D25/D24-1 -> 0.013939839 | AB25: =+E25/E24-1 -> -0.001529052 | AC25: =+F25/F24-1 -> 0.062769526 | AD25: =+G25/G24-1 -> 0.032467532 | AE25: =+H25/H24-1 -> 0.029830508 | AF25: =+I25/I24-1 -> 0.045050761 | ... AT25: =+W25/W24-1 -> 0.02924789 | AV25: =+B25/B13-1 -> 0.3474503 | AW25: =+C25/C13-1 -> 0.37056738 | AX25: =+D25/D13-1 -> 0.19137931 | AY25: =+E25/E13-1 -> 0.18404352 | AZ25: =+F25/F13-1 -> 0.5876879 | BA25: =+G25/G13-1 -> 0.29972752 | BB25: =+H25/H13-1 -> 0.28185654 | BC25: =+I25/I13-1 -> 0.44854881 | ... BQ25: =+W25/W13-1 -> 0.30648604 | BS25: =+A25 -> 43313 | BT25: =(C25-C24)/$B24*C$3 -> 0.017809139 | BU25: =(D25-D24)/$B24*D$3 -> 0.00039673115 | BV25: =(E25-E24)/$B24*E$3 -> -0.00016504336 | BW25: =(F25-F24)/$B24*F$3 -> 0.0061174116 | BX25: =(G25-G24)/$B24*G$3 -> 0.0018372248 | BY25: =(H25-H24)/$B24*H$3 -> 0.0018580387 | BZ25: =(I25-I24)/$B24*I$3 -> 0.0039833889 | CA25: =(J25-J24)/$B24*J$3 -> 0.0025744496 | ... CE25: =(N25-N24)/$B24*N$3 -> 0.0010206805 | CF25: =+SUM(BT25:CE25) -> 0.039612275
A26: =+[1]NOA!A27 -> 43344 | B26: =+[1]NOA!B27 -> 165.2 | C26: =+[1]NOA!C27 -> 164.3 | D26: =+[1]NOA!D27 -> 144.3 | E26: =+[1]NOA!E27 -> 138.3 | F26: =+[1]NOA!F27 -> 227.9 | G26: =+[1]NOA!G27 -> 156.7 | H26: =+[1]NOA!H27 -> 158.6 | ... N26: =+[1]NOA!N27 -> 154.3 | O26: =+[1]NOA!R27 -> 147.8 | P26: =+[1]NOA!S27 -> 159.3 | Q26: =+[1]NOA!T27 -> 200.3 | R26: =+SUMPRODUCT($C$3:$N$3,C26:N26) -> 165.19063 | S26: =+($C$3*$C26+$D$3*$D26+$E$3*$E26+$G$3*$G26+$K$3*$K26+$M$3*$M26+$N$3*$N26)/SUM($C$3:$E$3,$G$3,$K$3,$M$3:$N$3) -> 156.94722 | T26: =+($E$3*$E26+$G$3*$G26+$K$3*$K26+$M$3*$M26+$N$3*$N26)/SUM($E$3,$G$3,$K$3,$M$3:$N$3) -> 150.93732 | U26: =+($E$3*$E26+$G$3*$G26+$K$3*$K26+$N$3*$N26)/SUM($E$3,$G$3,$K$3,$N$3) -> 149.59914 | W26: =($E$3*$E26+SUMPRODUCT($G$3:$L$3,$G26:$L26)+$N$3*$N26)/SUM($E$3,$G$3:$L$3,$N$3) -> 159.55473 | Y26: =+B26/B25-1 -> 0.059653624 | Z26: =+C26/C25-1 -> 0.062742561 | AA26: =+D26/D25-1 -> 0.044138929 | AB26: =+E26/E25-1 -> 0.058958652 | AC26: =+F26/F25-1 -> 0.027502254 | AD26: =+G26/G25-1 -> 0.095038435 | AE26: =+H26/H25-1 -> 0.044107966 | AF26: =+I26/I25-1 -> 0.078324226 | ... AT26: =+W26/W25-1 -> 0.063784304 | AV26: =+B26/B14-1 -> 0.40237691 | AW26: =+C26/C14-1 -> 0.41760138 | AX26: =+D26/D14-1 -> 0.23544521 | AY26: =+E26/E14-1 -> 0.23813787 | AZ26: =+F26/F14-1 -> 0.61402266 | BA26: =+G26/G14-1 -> 0.40664273 | BB26: =+H26/H14-1 -> 0.31291391 | BC26: =+I26/I14-1 -> 0.5510917 | ... BQ26: =+W26/W14-1 -> 0.37215844 | BS26: =+A26 -> 43344 | BT26: =(C26-C25)/$B25*C$3 -> 0.021571456 | BU26: =(D26-D25)/$B25*D$3 -> 0.0012246953 | BV26: =(E26-E25)/$B25*E$3 -> 0.0061096216 | BW26: =(F26-F25)/$B25*F$3 -> 0.0027389352 | BX26: =(G26-G25)/$B25*G$3 -> 0.0053388069 | BY26: =(H26-H25)/$B25*H$3 -> 0.0027203977 | BZ26: =(I26-I25)/$B25*I$3 -> 0.0069588839 | CA26: =(J26-J25)/$B25*J$3 -> 0.00094695318 | ... CE26: =(N26-N25)/$B25*N$3 -> 0.0027042976 | CF26: =+SUM(BT26:CE26) -> 0.059887043
A27: =+[1]NOA!A28 -> 43374 | B27: =+[1]NOA!B28 -> 174 | C27: =+[1]NOA!C28 -> 173.3 | D27: =+[1]NOA!D28 -> 147.9 | E27: =+[1]NOA!E28 -> 146.4 | F27: =+[1]NOA!F28 -> 244.4 | G27: =+[1]NOA!G28 -> 164.2 | H27: =+[1]NOA!H28 -> 165.8 | ... N27: =+[1]NOA!N28 -> 163.5 | O27: =+[1]NOA!R28 -> 157 | P27: =+[1]NOA!S28 -> 167.2 | Q27: =+[1]NOA!T28 -> 212.3 | R27: =+SUMPRODUCT($C$3:$N$3,C27:N27) -> 173.9703 | S27: =+($C$3*$C27+$D$3*$D27+$E$3*$E27+$G$3*$G27+$K$3*$K27+$M$3*$M27+$N$3*$N27)/SUM($C$3:$E$3,$G$3,$K$3,$M$3:$N$3) -> 164.92853 | T27: =+($E$3*$E27+$G$3*$G27+$K$3*$K27+$M$3*$M27+$N$3*$N27)/SUM($E$3,$G$3,$K$3,$M$3:$N$3) -> 158.31566 | U27: =+($E$3*$E27+$G$3*$G27+$K$3*$K27+$N$3*$N27)/SUM($E$3,$G$3,$K$3,$N$3) -> 157.48786 | W27: =($E$3*$E27+SUMPRODUCT($G$3:$L$3,$G27:$L27)+$N$3*$N27)/SUM($E$3,$G$3:$L$3,$N$3) -> 167.90943 | Y27: =+B27/B26-1 -> 0.053268765 | Z27: =+C27/C26-1 -> 0.054777845 | AA27: =+D27/D26-1 -> 0.024948025 | AB27: =+E27/E26-1 -> 0.05856833 | AC27: =+F27/F26-1 -> 0.072400176 | AD27: =+G27/G26-1 -> 0.047862157 | AE27: =+H27/H26-1 -> 0.045397226 | AF27: =+I27/I26-1 -> 0.081081081 | ... AT27: =+W27/W26-1 -> 0.052362544 | AV27: =+B27/B15-1 -> 0.45 | AW27: =+C27/C15-1 -> 0.46740051 | AX27: =+D27/D15-1 -> 0.2325 | AY27: =+E27/E15-1 -> 0.27083333 | AZ27: =+F27/F15-1 -> 0.71508772 | BA27: =+G27/G15-1 -> 0.45955556 | BB27: =+H27/H15-1 -> 0.35457516 | BC27: =+I27/I15-1 -> 0.65517241 | ... BQ27: =+W27/W15-1 -> 0.41617674 | BS27: =+A27 -> 43374 | BT27: =(C27-C26)/$B26*C$3 -> 0.018888015 | BU27: =(D27-D26)/$B26*D$3 -> 0.00068208232 | BV27: =(E27-E26)/$B26*E$3 -> 0.0060651937 | BW27: =(F27-F26)/$B26*F$3 -> 0.0069915254 | BX27: =(G27-G26)/$B26*G$3 -> 0.0027784504 | BY27: =(H27-H26)/$B26*H$3 -> 0.0027588378 | BZ27: =(I27-I26)/$B26*I$3 -> 0.0073307506 | CA27: =(J27-J26)/$B26*J$3 -> 0.00045466102 | ... CE27: =(N27-N26)/$B26*N$3 -> 0.0018934625 | CF27: =+SUM(BT27:CE27) -> 0.053145702
A28: =+[1]NOA!A29 -> 43405 | B28: =+[1]NOA!B29 -> 179.6 | C28: =+[1]NOA!C29 -> 178.3 | D28: =+[1]NOA!D29 -> 155.4 | E28: =+[1]NOA!E29 -> 150.5 | F28: =+[1]NOA!F29 -> 250.6 | G28: =+[1]NOA!G29 -> 169.3 | H28: =+[1]NOA!H29 -> 180.6 | ... N28: =+[1]NOA!N29 -> 172.3 | O28: =+[1]NOA!R29 -> 159.3 | P28: =+[1]NOA!S29 -> 173.4 | Q28: =+[1]NOA!T29 -> 218.2 | R28: =+SUMPRODUCT($C$3:$N$3,C28:N28) -> 179.65406 | S28: =+($C$3*$C28+$D$3*$D28+$E$3*$E28+$G$3*$G28+$K$3*$K28+$M$3*$M28+$N$3*$N28)/SUM($C$3:$E$3,$G$3,$K$3,$M$3:$N$3) -> 169.88061 | T28: =+($E$3*$E28+$G$3*$G28+$K$3*$K28+$M$3*$M28+$N$3*$N28)/SUM($E$3,$G$3,$K$3,$M$3:$N$3) -> 162.99877 | U28: =+($E$3*$E28+$G$3*$G28+$K$3*$K28+$N$3*$N28)/SUM($E$3,$G$3,$K$3,$N$3) -> 162.42443 | W28: =($E$3*$E28+SUMPRODUCT($G$3:$L$3,$G28:$L28)+$N$3*$N28)/SUM($E$3,$G$3:$L$3,$N$3) -> 174.21718 | Y28: =+B28/B27-1 -> 0.032183908 | Z28: =+C28/C27-1 -> 0.028851702 | AA28: =+D28/D27-1 -> 0.050709939 | AB28: =+E28/E27-1 -> 0.028005464 | AC28: =+F28/F27-1 -> 0.025368249 | AD28: =+G28/G27-1 -> 0.031059683 | AE28: =+H28/H27-1 -> 0.089264174 | AF28: =+I28/I27-1 -> 0.027604167 | ... AT28: =+W28/W27-1 -> 0.0375664 | AV28: =+B28/B16-1 -> 0.4781893 | AW28: =+C28/C16-1 -> 0.49706129 | AX28: =+D28/D16-1 -> 0.2853598 | AY28: =+E28/E16-1 -> 0.28742515 | AZ28: =+F28/F16-1 -> 0.73907009 | BA28: =+G28/G16-1 -> 0.4903169 | BB28: =+H28/H16-1 -> 0.45762712 | BC28: =+I28/I16-1 -> 0.65520134 | ... BQ28: =+W28/W16-1 -> 0.4457725 | BS28: =+A28 -> 43405 | BT28: =(C28-C27)/$B27*C$3 -> 0.0099626437 | BU28: =(D28-D27)/$B27*D$3 -> 0.0013491379 | BV28: =(E28-E27)/$B27*E$3 -> 0.0029147701 | BW28: =(F28-F27)/$B27*F$3 -> 0.0024942529 | BX28: =(G28-G27)/$B27*G$3 -> 0.0017937931 | BY28: =(H28-H27)/$B27*H$3 -> 0.0053841379 | BZ28: =(I28-I27)/$B27*I$3 -> 0.0025616667 | CA28: =(J28-J27)/$B27*J$3 -> 0.00062517241 | ... CE28: =(N28-N27)/$B27*N$3 -> 0.0017195402 | CF28: =+SUM(BT28:CE28) -> 0.032665287
... A118: =+[1]NOA!A119 -> 46143 | B118: =+[1]NOA!B119 -> 11747.5 | C118: =+[1]NOA!C119 -> 12201.6 | D118: =+[1]NOA!D119 -> 7644.9 | E118: =+[1]NOA!E119 -> 7757.6 | F118: =+[1]NOA!F119 -> 17022.2 | G118: =+[1]NOA!G119 -> 9079.2 | H118: =+[1]NOA!H119 -> 13151.1 | ... N118: =+[1]NOA!N119 -> 10669.4 | O118: =+[1]NOA!R119 -> 9239.2 | P118: =+[1]NOA!S119 -> 11666.1 | Q118: =+[1]NOA!T119 -> 13852.3 | R118: =+SUMPRODUCT($C$3:$N$3,C118:N118) -> 11747.603 | S118: =+($C$3*$C118+$D$3*$D118+$E$3*$E118+$G$3*$G118+$K$3*$K118+$M$3*$M118+$N$3*$N118)/SUM($C$3:$E$3,$G$3,$K$3,$M$3:$N$3) -> 11018.193 | T118: =+($E$3*$E118+$G$3*$G118+$K$3*$K118+$M$3*$M118+$N$3*$N118)/SUM($E$3,$G$3,$K$3,$M$3:$N$3) -> 10167.781 | U118: =+($E$3*$E118+$G$3*$G118+$K$3*$K118+$N$3*$N118)/SUM($E$3,$G$3,$K$3,$N$3) -> 8830.5119 | W118: =($E$3*$E118+SUMPRODUCT($G$3:$L$3,$G118:$L118)+$N$3*$N118)/SUM($E$3,$G$3:$L$3,$N$3) -> 10382.902 | Y118: =+B118/B117-1 -> 0.020935811 | Z118: =+C118/C117-1 -> 0.021336436 | AA118: =+D118/D117-1 -> 0.0042957358 | AB118: =+E118/E117-1 -> 0.0029217841 | AC118: =+F118/F117-1 -> 0.040381383 | AD118: =+G118/G117-1 -> 0.019150035 | AE118: =+H118/H117-1 -> 0.025890851 | AF118: =+I118/I117-1 -> 0.0088419412 | ... AT118: =+W118/W117-1 -> 0.017141351 | AV118: =+B118/B106-1 -> 0.33236929 | AW118: =+C118/C106-1 -> 0.34059946 | AX118: =+D118/D106-1 -> 0.23715895 | AY118: =+E118/E106-1 -> 0.13033469 | AZ118: =+F118/F106-1 -> 0.49648345 | BA118: =+G118/G106-1 -> 0.22446998 | BB118: =+H118/H106-1 -> 0.2786804 | BC118: =+I118/I106-1 -> 0.45707417 | ... BQ118: =+W118/W106-1 -> 0.28652892 | BS118: =+A118 -> 46143 | BT118: =(C118-C117)/$B117*C$3 -> 0.0076802731 | BU118: =(D118-D117)/$B117*D$3 -> 8.894982e-05 | BV118: =(E118-E117)/$B117*E$3 -> 0.00024295795 | BW118: =(F118-F117)/$B117*F$3 -> 0.0040193454 | BX118: =(G118-G117)/$B117*G$3 -> 0.00090736795 | BY118: =(H118-H117)/$B117*H$3 -> 0.0018258452 | BZ118: =(I118-I117)/$B117*I$3 -> 0.00079593364 | CA118: =(J118-J117)/$B117*J$3 -> 0.0009125076 | ... CE118: =(N118-N117)/$B117*N$3 -> 0.00086310465 | CF118: =+SUM(BT118:CE118) -> 0.020936238

Sheet NEA
B1: Índices | Y1: Tasas de inflación mensual | AV1: Tasas de inflación interanual | BS1: Incidencia mensual | CH1: Incidencia Feb 21 - Jun 24
R2: =+SUM(C3:N3) -> 1 | S2: =+SUM($C$3:$E$3,$G$3,$K$3,$M$3:$N$3) -> 0.7282 | T2: =+SUM($E$3,$G$3,$K$3,$M$3:$N$3) -> 0.3387 | U2: =+SUM($E$3,$G$3,$K$3,$N$3) -> 0.2892 | W2: =+SUM(E3,G3:L3,N3) -> 0.4799 | AT2: =+SUM(AB3,AD3:AI3,AK3) -> 0.4799 | BL2: =+SUM(AW3:BH3) -> 1 | BQ2: =+SUM(AY3,BA3:BF3,BH3) -> 0.4799
C3: =+[1]NEA!C3 -> 0.3531 | D3: =+[1]NEA!D3 -> 0.0364 | E3: =+[1]NEA!E3 -> 0.116 | F3: =+[1]NEA!F3 -> 0.0811 | G3: =+[1]NEA!G3 -> 0.0778 | H3: =+[1]NEA!H3 -> 0.0526 | I3: =+[1]NEA!I3 -> 0.0963 | J3: =+[1]NEA!J3 -> 0.0282 | ... N3: =+[1]NEA!N3 -> 0.033 | R3: headline | V3: no food & energy | W3: no food & energy & shelter | Z3: =+C3 -> 0.3531 | AA3: =+D3 -> 0.0364 | AB3: =+E3 -> 0.116 | AC3: =+F3 -> 0.0811 | AD3: =+G3 -> 0.0778 | AE3: =+H3 -> 0.0526 | AF3: =+I3 -> 0.0963 | AG3: =+J3 -> 0.0282 | ... AK3: =+N3 -> 0.033 | AO3: headline | AS3: no food & energy | AT3: no food & energy & shelter | AW3: =+Z3 -> 0.3531 | AX3: =+AA3 -> 0.0364 | AY3: =+AB3 -> 0.116 | AZ3: =+AC3 -> 0.0811 | BA3: =+AD3 -> 0.0778 | BB3: =+AE3 -> 0.0526 | BC3: =+AF3 -> 0.0963 | BD3: =+AG3 -> 0.0282 | ... BH3: =+AK3 -> 0.033 | BL3: headline | BP3: no food & energy | BQ3: no food & energy & shelter | BT3: =+AW3 -> 0.3531 | BU3: =+AX3 -> 0.0364 | BV3: =+AY3 -> 0.116 | BW3: =+AZ3 -> 0.0811 | BX3: =+BA3 -> 0.0778 | BY3: =+BB3 -> 0.0526 | BZ3: =+BC3 -> 0.0963 | CA3: =+BD3 -> 0.0282 | ... CE3: =+BH3 -> 0.033 | CH3: 1 | CI3: =+BT3 -> 0.3531 | CJ3: =+BU3 -> 0.0364 | CK3: =+BV3 -> 0.116 | CL3: =+BW3 -> 0.0811 | CM3: =+BX3 -> 0.0778 | CN3: =+BY3 -> 0.0526 | CO3: =+BZ3 -> 0.0963 | CP3: =+CA3 -> 0.0282 | ... CT3: =+CE3 -> 0.033
A4: Fecha | B4: Nivel general | C4: Alimentos y bebidas no alcohólicas | D4: Bebidas alcohólicas y tabaco | E4: Prendas de vestir y calzado | F4: Vivienda, agua, electricidad, gas y otros combustibles | G4: EquiNEAiento y mantenimiento del hogar | H4: Salud | I4: Transporte | J4: Comunicación | K4: Recreación y cultura | L4: Educación | M4: Restaurantes y hoteles | N4: Bienes y servicios varios | O4: Estacional | P4: Núcleo | Q4: Regulados | R4: Nivel General | S4: Subyacente | T4: Subyacente-AyB | U4: Subyacente-Food | V4: Core | W4: Supercore | Y4: Nivel general | Z4: Alimentos y bebidas no alcohólicas | AA4: Bebidas alcohólicas y tabaco | AB4: Prendas de vestir y calzado | AC4: Vivienda, agua, electricidad, gas y otros combustibles | AD4: EquiNEAiento y mantenimiento del hogar | AE4: Salud | AF4: Transporte | AG4: Comunicación | AH4: Recreación y cultura | AI4: Educación | AJ4: Restaurantes y hoteles | AK4: Bienes y servicios varios | AL4: Estacional | AM4: Núcleo | AN4: Regulados | AO4: =+R4 -> Nivel General | AP4: =+S4 -> Subyacente | AQ4: =+T4 -> Subyacente-AyB | AR4: =+U4 -> Subyacente-Food | AS4: Core | AT4: Supercore | AV4: Nivel general | AW4: Alimentos y bebidas no alcohólicas | AX4: Bebidas alcohólicas y tabaco | AY4: Prendas de vestir y calzado | AZ4: Vivienda, agua, electricidad, gas y otros combustibles | BA4: EquiNEAiento y mantenimiento del hogar | BB4: Salud | BC4: Transporte | BD4: Comunicación | BE4: Recreación y cultura | BF4: Educación | BG4: Restaurantes y hoteles | BH4: Bienes y servicios varios | BI4: Estacional | BJ4: Núcleo | BK4: Regulados | BL4: =+AO4 -> Nivel General | BM4: =+AP4 -> Subyacente | BN4: =+AQ4 -> Subyacente-AyB | BO4: =+AR4 -> Subyacente-Food | BP4: Core | BQ4: Supercore | BS4: Fecha | BT4: Alimentos y bebidas no alcohólicas | BU4: Bebidas alcohólicas y tabaco | BV4: Prendas de vestir y calzado | BW4: Vivienda, agua, electricidad, gas y otros combustibles | BX4: Equipamiento y mantenimiento del hogar | BY4: Salud | BZ4: Transporte | CA4: Comunicación | CB4: Recreación y cultura | CC4: Educación | CD4: Restaurantes y hoteles | CE4: Bienes y servicios varios | CF4: Nivel general | CH4: Fecha | CI4: Alimentos y bebidas no alcohólicas | CJ4: Bebidas alcohólicas y tabaco | CK4: Prendas de vestir y calzado | CL4: Vivienda, agua, electricidad, gas y otros combustibles | CM4: Equipamiento y mantenimiento del hogar | CN4: Salud | CO4: Transporte | CP4: Comunicación | CQ4: Recreación y cultura | CR4: Educación | CS4: Restaurantes y hoteles | CT4: Bienes y servicios varios | CU4: Nivel general
A5: =+[1]NEA!A6 -> 42705 | B5: =+[1]NEA!B6 -> 100 | C5: =+[1]NEA!C6 -> 100 | D5: =+[1]NEA!D6 -> 100 | E5: =+[1]NEA!E6 -> 100 | F5: =+[1]NEA!F6 -> 100 | G5: =+[1]NEA!G6 -> 100 | H5: =+[1]NEA!H6 -> 100 | ... N5: =+[1]NEA!N6 -> 100 | O5: =+[1]NEA!R6 -> 100 | P5: =+[1]NEA!S6 -> 100 | Q5: =+[1]NEA!T6 -> 100 | R5: =+SUMPRODUCT($C$3:$N$3,C5:N5) -> 100 | S5: =+($C$3*$C5+$D$3*$D5+$E$3*$E5+$G$3*$G5+$K$3*$K5+$M$3*$M5+$N$3*$N5)/SUM($C$3:$E$3,$G$3,$K$3,$M$3:$N$3) -> 100 | T5: =+($E$3*$E5+$G$3*$G5+$K$3*$K5+$M$3*$M5+$N$3*$N5)/SUM($E$3,$G$3,$K$3,$M$3:$N$3) -> 100 | U5: =+($E$3*$E5+$G$3*$G5+$K$3*$K5+$N$3*$N5)/SUM($E$3,$G$3,$K$3,$N$3) -> 100 | W5: =($E$3*$E5+SUMPRODUCT($G$3:$L$3,$G5:$L5)+$N$3*$N5)/SUM($E$3,$G$3:$L$3,$N$3) -> 100 | BS5: =+A5 -> 42705
A6: =+[1]NEA!A7 -> 42736 | B6: =+[1]NEA!B7 -> 101.7 | C6: =+[1]NEA!C7 -> 101.7 | D6: =+[1]NEA!D7 -> 100.8 | E6: =+[1]NEA!E7 -> 100.3 | F6: =+[1]NEA!F7 -> 101.4 | G6: =+[1]NEA!G7 -> 101.4 | H6: =+[1]NEA!H7 -> 102.6 | ... N6: =+[1]NEA!N7 -> 102.1 | O6: =+[1]NEA!R7 -> 102.5 | P6: =+[1]NEA!S7 -> 101.9 | Q6: =+[1]NEA!T7 -> 100.3 | R6: =+SUMPRODUCT($C$3:$N$3,C6:N6) -> 101.65835 | S6: =+($C$3*$C6+$D$3*$D6+$E$3*$E6+$G$3*$G6+$K$3*$K6+$M$3*$M6+$N$3*$N6)/SUM($C$3:$E$3,$G$3,$K$3,$M$3:$N$3) -> 101.75762 | T6: =+($E$3*$E6+$G$3*$G6+$K$3*$K6+$M$3*$M6+$N$3*$N6)/SUM($E$3,$G$3,$K$3,$M$3:$N$3) -> 101.92061 | U6: =+($E$3*$E6+$G$3*$G6+$K$3*$K6+$N$3*$N6)/SUM($E$3,$G$3,$K$3,$N$3) -> 101.51335 | W6: =($E$3*$E6+SUMPRODUCT($G$3:$L$3,$G6:$L6)+$N$3*$N6)/SUM($E$3,$G$3:$L$3,$N$3) -> 101.46399 | Y6: =+B6/B5-1 -> 0.017 | Z6: =+C6/C5-1 -> 0.017 | AA6: =+D6/D5-1 -> 0.008 | AB6: =+E6/E5-1 -> 0.003 | AC6: =+F6/F5-1 -> 0.014 | AD6: =+G6/G5-1 -> 0.014 | AE6: =+H6/H5-1 -> 0.026 | AF6: =+I6/I5-1 -> 0.003 | ... AT6: =+W6/W5-1 -> 0.014639925 | BS6: =+A6 -> 42736 | BT6: =(C6-C5)/$B5*C$3 -> 0.0060027 | BU6: =(D6-D5)/$B5*D$3 -> 0.0002912 | BV6: =(E6-E5)/$B5*E$3 -> 0.000348 | BW6: =(F6-F5)/$B5*F$3 -> 0.0011354 | BX6: =(G6-G5)/$B5*G$3 -> 0.0010892 | BY6: =(H6-H5)/$B5*H$3 -> 0.0013676 | BZ6: =(I6-I5)/$B5*I$3 -> 0.0002889 | CA6: =(J6-J5)/$B5*J$3 -> 0.0007614 | ... CE6: =(N6-N5)/$B5*N$3 -> 0.000693 | CF6: =+SUM(BT6:CE6) -> 0.0165835 | CH6: =+CH$3*(B$95-B$55)/$B$55 -> 13.563611 | CI6: =+CI$3*(C$95-C$55)/$B$55 -> 5.0926584 | CJ6: =+CJ$3*(D$95-D$55)/$B$55 -> 0.40113032 | CK6: =+CK$3*(E$95-E$55)/$B$55 -> 1.2346357 | CL6: =+CL$3*(F$95-F$55)/$B$55 -> 1.0586453 | CM6: =+CM$3*(G$95-G$55)/$B$55 -> 1.0209077 | CN6: =+CN$3*(H$95-H$55)/$B$55 -> 0.85168586 | CO6: =+CO$3*(I$95-I$55)/$B$55 -> 1.5666864 | ... CT6: =+CT$3*(N$95-N$55)/$B$55 -> 0.47757456
A7: =+[1]NEA!A8 -> 42767 | B7: =+[1]NEA!B8 -> 103.5 | C7: =+[1]NEA!C8 -> 103.4 | D7: =+[1]NEA!D8 -> 104.3 | E7: =+[1]NEA!E8 -> 100.4 | F7: =+[1]NEA!F8 -> 104 | G7: =+[1]NEA!G8 -> 101.8 | H7: =+[1]NEA!H8 -> 105.2 | ... N7: =+[1]NEA!N8 -> 103.2 | O7: =+[1]NEA!R8 -> 104.1 | P7: =+[1]NEA!S8 -> 103.4 | Q7: =+[1]NEA!T8 -> 103.1 | R7: =+SUMPRODUCT($C$3:$N$3,C7:N7) -> 103.47224 | S7: =+($C$3*$C7+$D$3*$D7+$E$3*$E7+$G$3*$G7+$K$3*$K7+$M$3*$M7+$N$3*$N7)/SUM($C$3:$E$3,$G$3,$K$3,$M$3:$N$3) -> 103.31726 | T7: =+($E$3*$E7+$G$3*$G7+$K$3*$K7+$M$3*$M7+$N$3*$N7)/SUM($E$3,$G$3,$K$3,$M$3:$N$3) -> 103.12539 | U7: =+($E$3*$E7+$G$3*$G7+$K$3*$K7+$N$3*$N7)/SUM($E$3,$G$3,$K$3,$N$3) -> 102.2397 | W7: =($E$3*$E7+SUMPRODUCT($G$3:$L$3,$G7:$L7)+$N$3*$N7)/SUM($E$3,$G$3:$L$3,$N$3) -> 102.87545 | Y7: =+B7/B6-1 -> 0.017699115 | Z7: =+C7/C6-1 -> 0.016715831 | AA7: =+D7/D6-1 -> 0.034722222 | AB7: =+E7/E6-1 -> 0.00099700897 | AC7: =+F7/F6-1 -> 0.025641026 | AD7: =+G7/G6-1 -> 0.0039447732 | AE7: =+H7/H6-1 -> 0.025341131 | AF7: =+I7/I6-1 -> 0.0099700897 | ... AT7: =+W7/W6-1 -> 0.013910952 | BS7: =+A7 -> 42767 | BT7: =(C7-C6)/$B6*C$3 -> 0.0059023599 | BU7: =(D7-D6)/$B6*D$3 -> 0.001252704 | BV7: =(E7-E6)/$B6*E$3 -> 0.00011406096 | BW7: =(F7-F6)/$B6*F$3 -> 0.002073353 | BX7: =(G7-G6)/$B6*G$3 -> 0.00030599803 | BY7: =(H7-H6)/$B6*H$3 -> 0.0013447394 | BZ7: =(I7-I6)/$B6*I$3 -> 0.00094690265 | CA7: =(J7-J6)/$B6*J$3 -> 0.001220059 | ... CE7: =(N7-N6)/$B6*N$3 -> 0.00035693215 | CF7: =+SUM(BT7:CE7) -> 0.017835693
A8: =+[1]NEA!A9 -> 42795 | B8: =+[1]NEA!B9 -> 106 | C8: =+[1]NEA!C9 -> 105 | D8: =+[1]NEA!D9 -> 106.3 | E8: =+[1]NEA!E9 -> 103.2 | F8: =+[1]NEA!F9 -> 113.2 | G8: =+[1]NEA!G9 -> 103.2 | H8: =+[1]NEA!H9 -> 107.6 | ... N8: =+[1]NEA!N9 -> 104.5 | O8: =+[1]NEA!R9 -> 104.9 | P8: =+[1]NEA!S9 -> 105.4 | Q8: =+[1]NEA!T9 -> 109 | R8: =+SUMPRODUCT($C$3:$N$3,C8:N8) -> 105.97127 | S8: =+($C$3*$C8+$D$3*$D8+$E$3*$E8+$G$3*$G8+$K$3*$K8+$M$3*$M8+$N$3*$N8)/SUM($C$3:$E$3,$G$3,$K$3,$M$3:$N$3) -> 104.99713 | T8: =+($E$3*$E8+$G$3*$G8+$K$3*$K8+$M$3*$M8+$N$3*$N8)/SUM($E$3,$G$3,$K$3,$M$3:$N$3) -> 104.85412 | U8: =+($E$3*$E8+$G$3*$G8+$K$3*$K8+$N$3*$N8)/SUM($E$3,$G$3,$K$3,$N$3) -> 103.88776 | W8: =($E$3*$E8+SUMPRODUCT($G$3:$L$3,$G8:$L8)+$N$3*$N8)/SUM($E$3,$G$3:$L$3,$N$3) -> 104.97224 | Y8: =+B8/B7-1 -> 0.024154589 | Z8: =+C8/C7-1 -> 0.015473888 | AA8: =+D8/D7-1 -> 0.019175455 | AB8: =+E8/E7-1 -> 0.027888446 | AC8: =+F8/F7-1 -> 0.088461538 | AD8: =+G8/G7-1 -> 0.013752456 | AE8: =+H8/H7-1 -> 0.022813688 | AF8: =+I8/I7-1 -> 0.010858835 | ... AT8: =+W8/W7-1 -> 0.02038184 | BS8: =+A8 -> 42795 | BT8: =(C8-C7)/$B7*C$3 -> 0.0054585507 | BU8: =(D8-D7)/$B7*D$3 -> 0.00070338164 | BV8: =(E8-E7)/$B7*E$3 -> 0.0031381643 | BW8: =(F8-F7)/$B7*F$3 -> 0.0072088889 | BX8: =(G8-G7)/$B7*G$3 -> 0.0010523671 | BY8: =(H8-H7)/$B7*H$3 -> 0.0012197101 | BZ8: =(I8-I7)/$B7*I$3 -> 0.0010234783 | CA8: =(J8-J7)/$B7*J$3 -> 0.0010081159 | ... CE8: =(N8-N7)/$B7*N$3 -> 0.00041449275 | CF8: =+SUM(BT8:CE8) -> 0.024145217
A9: =+[1]NEA!A10 -> 42826 | B9: =+[1]NEA!B10 -> 108.3 | C9: =+[1]NEA!C10 -> 107.9 | D9: =+[1]NEA!D10 -> 109.4 | E9: =+[1]NEA!E10 -> 103.3 | F9: =+[1]NEA!F10 -> 116.6 | G9: =+[1]NEA!G10 -> 105 | H9: =+[1]NEA!H10 -> 110.3 | ... N9: =+[1]NEA!N10 -> 107.7 | O9: =+[1]NEA!R10 -> 107.1 | P9: =+[1]NEA!S10 -> 107.6 | Q9: =+[1]NEA!T10 -> 112.2 | R9: =+SUMPRODUCT($C$3:$N$3,C9:N9) -> 108.34179 | S9: =+($C$3*$C9+$D$3*$D9+$E$3*$E9+$G$3*$G9+$K$3*$K9+$M$3*$M9+$N$3*$N9)/SUM($C$3:$E$3,$G$3,$K$3,$M$3:$N$3) -> 107.23007 | T9: =+($E$3*$E9+$G$3*$G9+$K$3*$K9+$M$3*$M9+$N$3*$N9)/SUM($E$3,$G$3,$K$3,$M$3:$N$3) -> 106.29846 | U9: =+($E$3*$E9+$G$3*$G9+$K$3*$K9+$N$3*$N9)/SUM($E$3,$G$3,$K$3,$N$3) -> 105.51086 | W9: =($E$3*$E9+SUMPRODUCT($G$3:$L$3,$G9:$L9)+$N$3*$N9)/SUM($E$3,$G$3:$L$3,$N$3) -> 106.92713 | Y9: =+B9/B8-1 -> 0.021698113 | Z9: =+C9/C8-1 -> 0.027619048 | AA9: =+D9/D8-1 -> 0.029162747 | AB9: =+E9/E8-1 -> 0.00096899225 | AC9: =+F9/F8-1 -> 0.030035336 | AD9: =+G9/G8-1 -> 0.01744186 | AE9: =+H9/H8-1 -> 0.025092937 | AF9: =+I9/I8-1 -> 0.0048828125 | ... AT9: =+W9/W8-1 -> 0.018622889 | BS9: =+A9 -> 42826 | BT9: =(C9-C8)/$B8*C$3 -> 0.009660283 | BU9: =(D9-D8)/$B8*D$3 -> 0.0010645283 | BV9: =(E9-E8)/$B8*E$3 -> 0.00010943396 | BW9: =(F9-F8)/$B8*F$3 -> 0.0026013208 | BX9: =(G9-G8)/$B8*G$3 -> 0.0013211321 | BY9: =(H9-H8)/$B8*H$3 -> 0.0013398113 | BZ9: =(I9-I8)/$B8*I$3 -> 0.00045424528 | CA9: =(J9-J8)/$B8*J$3 -> 0.0024741509 | ... CE9: =(N9-N8)/$B8*N$3 -> 0.00099622642 | CF9: =+SUM(BT9:CE9) -> 0.022363396
A10: =+[1]NEA!A11 -> 42856 | B10: =+[1]NEA!B11 -> 110.4 | C10: =+[1]NEA!C11 -> 109.9 | D10: =+[1]NEA!D11 -> 111.5 | E10: =+[1]NEA!E11 -> 107.4 | F10: =+[1]NEA!F11 -> 117.8 | G10: =+[1]NEA!G11 -> 106.8 | H10: =+[1]NEA!H11 -> 112.7 | ... N10: =+[1]NEA!N11 -> 110.1 | O10: =+[1]NEA!R11 -> 109.3 | P10: =+[1]NEA!S11 -> 109.8 | Q10: =+[1]NEA!T11 -> 113.6 | R10: =+SUMPRODUCT($C$3:$N$3,C10:N10) -> 110.44255 | S10: =+($C$3*$C10+$D$3*$D10+$E$3*$E10+$G$3*$G10+$K$3*$K10+$M$3*$M10+$N$3*$N10)/SUM($C$3:$E$3,$G$3,$K$3,$M$3:$N$3) -> 109.52796 | T10: =+($E$3*$E10+$G$3*$G10+$K$3*$K10+$M$3*$M10+$N$3*$N10)/SUM($E$3,$G$3,$K$3,$M$3:$N$3) -> 108.92817 | U10: =+($E$3*$E10+$G$3*$G10+$K$3*$K10+$N$3*$N10)/SUM($E$3,$G$3,$K$3,$N$3) -> 108.04295 | W10: =($E$3*$E10+SUMPRODUCT($G$3:$L$3,$G10:$L10)+$N$3*$N10)/SUM($E$3,$G$3:$L$3,$N$3) -> 109.14093 | Y10: =+B10/B9-1 -> 0.019390582 | Z10: =+C10/C9-1 -> 0.018535681 | AA10: =+D10/D9-1 -> 0.019195612 | AB10: =+E10/E9-1 -> 0.039690223 | AC10: =+F10/F9-1 -> 0.010291595 | AD10: =+G10/G9-1 -> 0.017142857 | AE10: =+H10/H9-1 -> 0.02175884 | AF10: =+I10/I9-1 -> 0.019436346 | ... AT10: =+W10/W9-1 -> 0.020703768 | BS10: =+A10 -> 42856 | BT10: =(C10-C9)/$B9*C$3 -> 0.0065207756 | BU10: =(D10-D9)/$B9*D$3 -> 0.00070581717 | BV10: =(E10-E9)/$B9*E$3 -> 0.0043915051 | BW10: =(F10-F9)/$B9*F$3 -> 0.00089861496 | BX10: =(G10-G9)/$B9*G$3 -> 0.0012930748 | BY10: =(H10-H9)/$B9*H$3 -> 0.001165651 | BZ10: =(I10-I9)/$B9*I$3 -> 0.0017783934 | CA10: =(J10-J9)/$B9*J$3 -> 0.00010415512 | ... CE10: =(N10-N9)/$B9*N$3 -> 0.00073130194 | CF10: =+SUM(BT10:CE10) -> 0.019397599
A11: =+[1]NEA!A12 -> 42887 | B11: =+[1]NEA!B12 -> 111.9 | C11: =+[1]NEA!C12 -> 111.3 | D11: =+[1]NEA!D12 -> 114.3 | E11: =+[1]NEA!E12 -> 107.7 | F11: =+[1]NEA!F12 -> 120.8 | G11: =+[1]NEA!G12 -> 107.5 | H11: =+[1]NEA!H12 -> 114.5 | ... N11: =+[1]NEA!N12 -> 112.9 | O11: =+[1]NEA!R12 -> 108.8 | P11: =+[1]NEA!S12 -> 111.5 | Q11: =+[1]NEA!T12 -> 115.7 | R11: =+SUMPRODUCT($C$3:$N$3,C11:N11) -> 111.93288 | S11: =+($C$3*$C11+$D$3*$D11+$E$3*$E11+$G$3*$G11+$K$3*$K11+$M$3*$M11+$N$3*$N11)/SUM($C$3:$E$3,$G$3,$K$3,$M$3:$N$3) -> 110.86839 | T11: =+($E$3*$E11+$G$3*$G11+$K$3*$K11+$M$3*$M11+$N$3*$N11)/SUM($E$3,$G$3,$K$3,$M$3:$N$3) -> 110.04963 | U11: =+($E$3*$E11+$G$3*$G11+$K$3*$K11+$N$3*$N11)/SUM($E$3,$G$3,$K$3,$N$3) -> 109.25367 | W11: =($E$3*$E11+SUMPRODUCT($G$3:$L$3,$G11:$L11)+$N$3*$N11)/SUM($E$3,$G$3:$L$3,$N$3) -> 110.43509 | Y11: =+B11/B10-1 -> 0.013586957 | Z11: =+C11/C10-1 -> 0.012738854 | AA11: =+D11/D10-1 -> 0.025112108 | AB11: =+E11/E10-1 -> 0.0027932961 | AC11: =+F11/F10-1 -> 0.025466893 | AD11: =+G11/G10-1 -> 0.0065543071 | AE11: =+H11/H10-1 -> 0.015971606 | AF11: =+I11/I10-1 -> 0.01620591 | ... AT11: =+W11/W10-1 -> 0.011857747 | BS11: =+A11 -> 42887 | BT11: =(C11-C10)/$B10*C$3 -> 0.0044777174 | BU11: =(D11-D10)/$B10*D$3 -> 0.00092318841 | BV11: =(E11-E10)/$B10*E$3 -> 0.00031521739 | BW11: =(F11-F10)/$B10*F$3 -> 0.0022038043 | BX11: =(G11-G10)/$B10*G$3 -> 0.0004932971 | BY11: =(H11-H10)/$B10*H$3 -> 0.0008576087 | BZ11: =(I11-I10)/$B10*I$3 -> 0.0014828804 | CA11: =(J11-J10)/$B10*J$3 -> 7.6630435e-05 | ... CE11: =(N11-N10)/$B10*N$3 -> 0.00083695652 | CF11: =+SUM(BT11:CE11) -> 0.013499366
A12: =+[1]NEA!A13 -> 42917 | B12: =+[1]NEA!B13 -> 113.4 | C12: =+[1]NEA!C13 -> 112.1 | D12: =+[1]NEA!D13 -> 117.5 | E12: =+[1]NEA!E13 -> 107.3 | F12: =+[1]NEA!F13 -> 122.7 | G12: =+[1]NEA!G13 -> 109.9 | H12: =+[1]NEA!H13 -> 116.3 | ... N12: =+[1]NEA!N13 -> 114 | O12: =+[1]NEA!R13 -> 107.6 | P12: =+[1]NEA!S13 -> 113.2 | Q12: =+[1]NEA!T13 -> 118.2 | R12: =+SUMPRODUCT($C$3:$N$3,C12:N12) -> 113.35478 | S12: =+($C$3*$C12+$D$3*$D12+$E$3*$E12+$G$3*$G12+$K$3*$K12+$M$3*$M12+$N$3*$N12)/SUM($C$3:$E$3,$G$3,$K$3,$M$3:$N$3) -> 111.87806 | T12: =+($E$3*$E12+$G$3*$G12+$K$3*$K12+$M$3*$M12+$N$3*$N12)/SUM($E$3,$G$3,$K$3,$M$3:$N$3) -> 111.04249 | U12: =+($E$3*$E12+$G$3*$G12+$K$3*$K12+$N$3*$N12)/SUM($E$3,$G$3,$K$3,$N$3) -> 110.38223 | W12: =($E$3*$E12+SUMPRODUCT($G$3:$L$3,$G12:$L12)+$N$3*$N12)/SUM($E$3,$G$3:$L$3,$N$3) -> 112.22494 | Y12: =+B12/B11-1 -> 0.013404826 | Z12: =+C12/C11-1 -> 0.0071877808 | AA12: =+D12/D11-1 -> 0.0279965 | AB12: =+E12/E11-1 -> -0.0037140204 | AC12: =+F12/F11-1 -> 0.015728477 | AD12: =+G12/G11-1 -> 0.022325581 | AE12: =+H12/H11-1 -> 0.015720524 | AF12: =+I12/I11-1 -> 0.038461538 | ... AT12: =+W12/W11-1 -> 0.016207277 | BS12: =+A12 -> 42917 | BT12: =(C12-C11)/$B11*C$3 -> 0.0025243968 | BU12: =(D12-D11)/$B11*D$3 -> 0.0010409294 | BV12: =(E12-E11)/$B11*E$3 -> -0.00041465594 | BW12: =(F12-F11)/$B11*F$3 -> 0.0013770331 | BX12: =(G12-G11)/$B11*G$3 -> 0.0016686327 | BY12: =(H12-H11)/$B11*H$3 -> 0.0008461126 | BZ12: =(I12-I11)/$B11*I$3 -> 0.0035284182 | CA12: =(J12-J11)/$B11*J$3 -> 0.00022680965 | ... CE12: =(N12-N11)/$B11*N$3 -> 0.00032439678 | CF12: =+SUM(BT12:CE12) -> 0.012706881
A13: =+[1]NEA!A14 -> 42948 | B13: =+[1]NEA!B14 -> 114.7 | C13: =+[1]NEA!C14 -> 113.7 | D13: =+[1]NEA!D14 -> 119.6 | E13: =+[1]NEA!E14 -> 106.1 | F13: =+[1]NEA!F14 -> 125.2 | G13: =+[1]NEA!G14 -> 110.2 | H13: =+[1]NEA!H14 -> 119.3 | ... N13: =+[1]NEA!N14 -> 117.3 | O13: =+[1]NEA!R14 -> 108.7 | P13: =+[1]NEA!S14 -> 114.4 | Q13: =+[1]NEA!T14 -> 120 | R13: =+SUMPRODUCT($C$3:$N$3,C13:N13) -> 114.68737 | S13: =+($C$3*$C13+$D$3*$D13+$E$3*$E13+$G$3*$G13+$K$3*$K13+$M$3*$M13+$N$3*$N13)/SUM($C$3:$E$3,$G$3,$K$3,$M$3:$N$3) -> 113.02528 | T13: =+($E$3*$E13+$G$3*$G13+$K$3*$K13+$M$3*$M13+$N$3*$N13)/SUM($E$3,$G$3,$K$3,$M$3:$N$3) -> 111.61529 | U13: =+($E$3*$E13+$G$3*$G13+$K$3*$K13+$N$3*$N13)/SUM($E$3,$G$3,$K$3,$N$3) -> 111.07019 | W13: =($E$3*$E13+SUMPRODUCT($G$3:$L$3,$G13:$L13)+$N$3*$N13)/SUM($E$3,$G$3:$L$3,$N$3) -> 113.25305 | Y13: =+B13/B12-1 -> 0.011463845 | Z13: =+C13/C12-1 -> 0.014272971 | AA13: =+D13/D12-1 -> 0.01787234 | AB13: =+E13/E12-1 -> -0.011183597 | AC13: =+F13/F12-1 -> 0.020374898 | AD13: =+G13/G12-1 -> 0.0027297543 | AE13: =+H13/H12-1 -> 0.025795357 | AF13: =+I13/I12-1 -> 0.0081300813 | ... AT13: =+W13/W12-1 -> 0.0091611544 | BS13: =+A13 -> 42948 | BT13: =(C13-C12)/$B12*C$3 -> 0.0049820106 | BU13: =(D13-D12)/$B12*D$3 -> 0.00067407407 | BV13: =(E13-E12)/$B12*E$3 -> -0.0012275132 | BW13: =(F13-F12)/$B12*F$3 -> 0.0017879189 | BX13: =(G13-G12)/$B12*G$3 -> 0.00020582011 | BY13: =(H13-H12)/$B12*H$3 -> 0.0013915344 | BZ13: =(I13-I12)/$B12*I$3 -> 0.00076428571 | CA13: =(J13-J12)/$B12*J$3 -> 0.00024867725 | ... CE13: =(N13-N12)/$B12*N$3 -> 0.00096031746 | CF13: =+SUM(BT13:CE13) -> 0.011751235
A14: =+[1]NEA!A15 -> 42979 | B14: =+[1]NEA!B15 -> 116.2 | C14: =+[1]NEA!C15 -> 115.5 | D14: =+[1]NEA!D15 -> 120.8 | E14: =+[1]NEA!E15 -> 108.4 | F14: =+[1]NEA!F15 -> 126.1 | G14: =+[1]NEA!G15 -> 111 | H14: =+[1]NEA!H15 -> 121.3 | ... N14: =+[1]NEA!N15 -> 118.4 | O14: =+[1]NEA!R15 -> 111.5 | P14: =+[1]NEA!S15 -> 115.9 | Q14: =+[1]NEA!T15 -> 120.4 | R14: =+SUMPRODUCT($C$3:$N$3,C14:N14) -> 116.15709 | S14: =+($C$3*$C14+$D$3*$D14+$E$3*$E14+$G$3*$G14+$K$3*$K14+$M$3*$M14+$N$3*$N14)/SUM($C$3:$E$3,$G$3,$K$3,$M$3:$N$3) -> 114.61728 | T14: =+($E$3*$E14+$G$3*$G14+$K$3*$K14+$M$3*$M14+$N$3*$N14)/SUM($E$3,$G$3,$K$3,$M$3:$N$3) -> 113.03257 | U14: =+($E$3*$E14+$G$3*$G14+$K$3*$K14+$N$3*$N14)/SUM($E$3,$G$3,$K$3,$N$3) -> 112.6787 | W14: =($E$3*$E14+SUMPRODUCT($G$3:$L$3,$G14:$L14)+$N$3*$N14)/SUM($E$3,$G$3:$L$3,$N$3) -> 114.71715 | Y14: =+B14/B13-1 -> 0.013077594 | Z14: =+C14/C13-1 -> 0.015831135 | AA14: =+D14/D13-1 -> 0.010033445 | AB14: =+E14/E13-1 -> 0.021677663 | AC14: =+F14/F13-1 -> 0.0071884984 | AD14: =+G14/G13-1 -> 0.0072595281 | AE14: =+H14/H13-1 -> 0.016764459 | AF14: =+I14/I13-1 -> 0.0071684588 | ... AT14: =+W14/W13-1 -> 0.012927658 | BS14: =+A14 -> 42979 | BT14: =(C14-C13)/$B13*C$3 -> 0.005541238 | BU14: =(D14-D13)/$B13*D$3 -> 0.00038081953 | BV14: =(E14-E13)/$B13*E$3 -> 0.002326068 | BW14: =(F14-F13)/$B13*F$3 -> 0.00063635571 | BX14: =(G14-G13)/$B13*G$3 -> 0.00054263296 | BY14: =(H14-H13)/$B13*H$3 -> 0.00091717524 | BZ14: =(I14-I13)/$B13*I$3 -> 0.00067166521 | CA14: =(J14-J13)/$B13*J$3 -> 0.00019668701 | ... CE14: =(N14-N13)/$B13*N$3 -> 0.00031647777 | CF14: =+SUM(BT14:CE14) -> 0.012813601
A15: =+[1]NEA!A16 -> 43009 | B15: =+[1]NEA!B16 -> 117.9 | C15: =+[1]NEA!C16 -> 117.3 | D15: =+[1]NEA!D16 -> 124.1 | E15: =+[1]NEA!E16 -> 109.2 | F15: =+[1]NEA!F16 -> 127.3 | G15: =+[1]NEA!G16 -> 112 | H15: =+[1]NEA!H16 -> 123 | ... N15: =+[1]NEA!N16 -> 119.6 | O15: =+[1]NEA!R16 -> 113.7 | P15: =+[1]NEA!S16 -> 117.4 | Q15: =+[1]NEA!T16 -> 123 | R15: =+SUMPRODUCT($C$3:$N$3,C15:N15) -> 117.89164 | S15: =+($C$3*$C15+$D$3*$D15+$E$3*$E15+$G$3*$G15+$K$3*$K15+$M$3*$M15+$N$3*$N15)/SUM($C$3:$E$3,$G$3,$K$3,$M$3:$N$3) -> 116.1405 | T15: =+($E$3*$E15+$G$3*$G15+$K$3*$K15+$M$3*$M15+$N$3*$N15)/SUM($E$3,$G$3,$K$3,$M$3:$N$3) -> 114.07629 | U15: =+($E$3*$E15+$G$3*$G15+$K$3*$K15+$N$3*$N15)/SUM($E$3,$G$3,$K$3,$N$3) -> 113.81549 | W15: =($E$3*$E15+SUMPRODUCT($G$3:$L$3,$G15:$L15)+$N$3*$N15)/SUM($E$3,$G$3:$L$3,$N$3) -> 116.50248 | Y15: =+B15/B14-1 -> 0.014629948 | Z15: =+C15/C14-1 -> 0.015584416 | AA15: =+D15/D14-1 -> 0.027317881 | AB15: =+E15/E14-1 -> 0.0073800738 | AC15: =+F15/F14-1 -> 0.0095162569 | AD15: =+G15/G14-1 -> 0.009009009 | AE15: =+H15/H14-1 -> 0.014014839 | AF15: =+I15/I14-1 -> 0.021352313 | ... AT15: =+W15/W14-1 -> 0.015562889 | BS15: =+A15 -> 43009 | BT15: =(C15-C14)/$B14*C$3 -> 0.0054697074 | BU15: =(D15-D14)/$B14*D$3 -> 0.0010337349 | BV15: =(E15-E14)/$B14*E$3 -> 0.00079862306 | BW15: =(F15-F14)/$B14*F$3 -> 0.00083752151 | BX15: =(G15-G14)/$B14*G$3 -> 0.00066953528 | BY15: =(H15-H14)/$B14*H$3 -> 0.00076953528 | BZ15: =(I15-I14)/$B14*I$3 -> 0.0019889845 | CA15: =(J15-J14)/$B14*J$3 -> 0.0015046472 | ... CE15: =(N15-N14)/$B14*N$3 -> 0.00034079174 | CF15: =+SUM(BT15:CE15) -> 0.014927281
